Workbook

Sheet Dashboard
B1: Invest Flex Vantage – Sum at Risk Analysis
B2: Client: female, non-smoker, entry age 74 · Income US Dividend and Growth Fund 100% · 5-year premium payment (MIP)
B4: Current scenario inputs | C4: Value
B5: Investment return (net of mgmt fee) | C5: =Inputs!$C$21 -> 0.08
B6: Dividend payout rate (cash scenario) | C6: =Inputs!$C$22 -> 0.08
B7: Annual premium | C7: =Inputs!$C$6 -> 24000
B8: Premium years | C8: =Inputs!$C$7 -> 5
B9: Total premiums | C9: =Inputs!$C$6*Inputs!$C$7 -> 120000
B10: Death benefit floor (101% of net premiums) | C10: =Inputs!$C$8*Inputs!$C$6*Inputs!$C$7 -> 121200
B11: COI rate multiplier | C11: =Inputs!$C$16 -> 1
B12: Years with a return override | C12: =COUNT('Return Path'!C5:C29) -> 0
B14: Key results | C14: Dividends reinvested | D14: Dividends paid out
B15: Age when sum at risk first triggers insurance charge | C15: =IFERROR(Inputs!$C$4+INDEX(Calc_Reinvest!$B$2:$B$301,MATCH(1,Calc_Reinvest!$S$2:$S$301,0))-1,"Never") -> Never | D15: =IFERROR(Inputs!$C$4+INDEX(Calc_Payout!$B$2:$B$301,MATCH(1,Calc_Payout!$S$2:$S$301,0))-1,"Never") -> 77
B16: Age when policy lapses (policy value hits $0) | C16: =IFERROR(Inputs!$C$4+INDEX(Calc_Reinvest!$B$2:$B$301,MATCH(1,Calc_Reinvest!$R$2:$R$301,0))-1,"No lapse to 99") -> No lapse to 99 | D16: =IFERROR(Inputs!$C$4+INDEX(Calc_Payout!$B$2:$B$301,MATCH(1,Calc_Payout!$R$2:$R$301,0))-1,"No lapse to 99") -> 93
B17: Total insurance charges (COI) to age 99 | C17: =SUM(Calc_Reinvest!M2:M301) -> 0 | D17: =SUM(Calc_Payout!M2:M301) -> 96105.262
B18: Largest sum at risk charged on | C18: =MAX(Calc_Reinvest!L2:L301) -> 0 | D18: =MAX(Calc_Payout!L2:L301) -> 120094.06
B19: Total dividends received in cash | C19: 0 | D19: =SUM(Calc_Payout!N2:N301) -> 116238.25
B20: Policy value at age 80 | C20: =IF(80-Inputs!$C$4<1,"n/a",INDEX(Calc_Reinvest!$Q$2:$Q$301,(80-Inputs!$C$4)*12)) -> 149416.85 | D20: =IF(80-Inputs!$C$4<1,"n/a",INDEX(Calc_Payout!$Q$2:$Q$301,(80-Inputs!$C$4)*12)) -> 107009.84
B21: Policy value at age 85 | C21: =IF(85-Inputs!$C$4<1,"n/a",INDEX(Calc_Reinvest!$Q$2:$Q$301,(85-Inputs!$C$4)*12)) -> 199420.28 | D21: =IF(85-Inputs!$C$4<1,"n/a",INDEX(Calc_Payout!$Q$2:$Q$301,(85-Inputs!$C$4)*12)) -> 87772.454
B22: Policy value at age 90 | C22: =IF(90-Inputs!$C$4<1,"n/a",INDEX(Calc_Reinvest!$Q$2:$Q$301,(90-Inputs!$C$4)*12)) -> 291532.05 | D22: =IF(90-Inputs!$C$4<1,"n/a",INDEX(Calc_Payout!$Q$2:$Q$301,(90-Inputs!$C$4)*12)) -> 59509.27
B23: Policy value at age 95 | C23: =IF(95-Inputs!$C$4<1,"n/a",INDEX(Calc_Reinvest!$Q$2:$Q$301,(95-Inputs!$C$4)*12)) -> 426190.05 | D23: =IF(95-Inputs!$C$4<1,"n/a",INDEX(Calc_Payout!$Q$2:$Q$301,(95-Inputs!$C$4)*12)) -> 0
B24: Policy value at age 99 | C24: =IF(99-Inputs!$C$4<1,"n/a",INDEX(Calc_Reinvest!$Q$2:$Q$301,(99-Inputs!$C$4)*12)) -> 577479.93 | D24: =IF(99-Inputs!$C$4<1,"n/a",INDEX(Calc_Payout!$Q$2:$Q$301,(99-Inputs!$C$4)*12)) -> 0
B26: How the sum at risk works
B27: =CONCATENATE("Sum at risk = 101% × net premiums ($",TEXT(Inputs!$C$8*Inputs!$C$6*Inputs!$C$7,"#,##0"),") − policy value. It only exists while the policy value is BELOW that floor.") -> Sum at risk = 101% × net premiums ($121,200) − policy value. It only exists while the policy value is BELOW that floor.
B28: =CONCATENATE("Years 1–10: policy fee ",TEXT(Inputs!$C$12,"0.0%")," + mgmt fee in model ",TEXT(Inputs!$C$14,"0.0%")," ≈ ",TEXT(Inputs!$C$12+Inputs!$C$14,"0.0%")," p.a. With dividends REINVESTED, a net return below ~this level shrinks the policy value toward/below the floor and SAR appears.") -> Years 1–10: policy fee 2.5% + mgmt fee in model 0.0% ≈ 2.5% p.a. With dividends REINVESTED, a net return below ~this level shrinks the policy value toward/below the floor and SAR appears.
B29: =CONCATENATE("With dividends PAID OUT at ",TEXT(Inputs!$C$22,"0%"),", the policy needs roughly ",TEXT(Inputs!$C$12+Inputs!$C$14+Inputs!$C$22,"0.0%")," net return (yrs 1–10) just to hold its value – otherwise it erodes, SAR grows and COI accelerates.") -> With dividends PAID OUT at 8%, the policy needs roughly 10.5% net return (yrs 1–10) just to hold its value – otherwise it erodes, SAR grows and COI accelerates.
B30: Payouts do NOT reduce net premiums (confirmed), so the $ floor stays fixed while the policy value falls – the gap is the sum at risk.
B31: COI rates per $1,000 SAR (female): age 80 $50.75 · age 85 $89.60 · age 90 $157.25 · age 95 $248.42 · age 99 $389.64 per year – i.e. 5%→39% of SAR p.a.

Sheet Inputs
B1: Invest Flex Vantage (VS2) – Inputs & Assumptions
B2: Blue text on yellow = change these. Everything else recalculates. Source references are to the Benefit Illustration (BI) dated 19/12/2024.
B3: Policy details
B4: Entry age (age last birthday at policy start) | C4: 74 | D4: BI p.2
B5: Gender (Male / Female) | C5: Female | D5: BI p.2 – selects COI rate column
B6: Annual regular premium ($) | C6: 24000 | D6: BI p.2 – $24,000 p.a. (paid at start of each policy year)
B7: Premium paying years (MIP) | C7: 5 | D7: BI p.2 – Minimum Investment Period 5 yrs; no premiums after
B8: Death benefit floor (% of net premiums) | C8: 1.01 | D8: Product Summary 3.1 – higher of 101% of net premiums or policy value
B9: Investment bonus (% of 1st-year premium) | C9: 0.04 | D9: Product Summary 2.2 – 4% for 5-yr MIP
B11: Charges
B12: Policy fee – policy years 1 to 10 (p.a. of policy value) | C12: 0.025 | D12: Product Summary 7.2
B13: Policy fee – policy year 11 onwards (p.a.) | C13: 0.006 | D13: Product Summary 7.2
B14: Fund management fee deducted by model (p.a.) | C14: 0 | D14: Set to 0% because the return you key in is already NET of the 1.50% fund management fee (Fund Summary). Enter 1.5% only if you key in gross returns
B15: Insurance cover charge (COI) starts after month | C15: 36 | D15: Product Summary 7.3 – from 3rd policy anniversary
B16: COI rate multiplier (stress test; 100% = current rates) | C16: 1 | D16: Rates are not guaranteed – raise to stress test
B17: Loyalty bonus (% of policy value, yearly) | C17: 0.005 | D17: Product Summary 2.3
B18: Loyalty bonus first paid at end of policy year | C18: 10 | D18: Product Summary 2.3 – from 10th anniversary
B19: Fund management fee used for BI Check only | C19: 0.015 | D19: BI illustrated rates (4%/8%) are before the 1.50% fee – used only on the BI Check sheet so it still reconciles to the BI
B20: Investment & dividend
B21: Investment return (p.a., NET of fund management fee) | C21: 0.08 | D21: Key in e.g. 8% or 5% – every column recalculates. Override any single year on the Return Path sheet
B22: Dividend payout rate (p.a. of fund value, paid monthly) | C22: 0.08 | D22: Fund currently distributes ~8% p.a. – not guaranteed. Used only in the "Dividend Paid Out" scenario
B24: Sensitivity return rates (net p.a.)
B25: Sensitivity rate 1 | C25: 0.02 | D25: Shown side by side on the Sensitivity sheet
B26: Sensitivity rate 2 | C26: 0.03
B27: Sensitivity rate 3 | C27: 0.04
B28: Sensitivity rate 4 | C28: 0.05
B29: Sensitivity rate 5 | C29: 0.06
B30: Sensitivity rate 6 | C30: 0.07
B31: Sensitivity rate 7 | C31: 0.08
B32: Sensitivity rate 8 | C32: 0.1

Sheet Return Path
A1: Year-by-year net return path (used by the main Projection & Dashboard)
A2: Leave Override blank to use the base return on Inputs. Type a rate (e.g. -15%) to model a bad year.
A4: Policy year | B4: Age at start (last b'day) | C4: Override return | D4: Return used
A5: 1 | B5: =Inputs!$C$4+A5-1 -> 74 | D5: =IF(C5="",Inputs!$C$21,C5) -> 0.08
A6: 2 | B6: =Inputs!$C$4+A6-1 -> 75 | D6: =IF(C6="",Inputs!$C$21,C6) -> 0.08
A7: 3 | B7: =Inputs!$C$4+A7-1 -> 76 | D7: =IF(C7="",Inputs!$C$21,C7) -> 0.08
A8: 4 | B8: =Inputs!$C$4+A8-1 -> 77 | D8: =IF(C8="",Inputs!$C$21,C8) -> 0.08
A9: 5 | B9: =Inputs!$C$4+A9-1 -> 78 | D9: =IF(C9="",Inputs!$C$21,C9) -> 0.08
A10: 6 | B10: =Inputs!$C$4+A10-1 -> 79 | D10: =IF(C10="",Inputs!$C$21,C10) -> 0.08
A11: 7 | B11: =Inputs!$C$4+A11-1 -> 80 | D11: =IF(C11="",Inputs!$C$21,C11) -> 0.08
A12: 8 | B12: =Inputs!$C$4+A12-1 -> 81 | D12: =IF(C12="",Inputs!$C$21,C12) -> 0.08
A13: 9 | B13: =Inputs!$C$4+A13-1 -> 82 | D13: =IF(C13="",Inputs!$C$21,C13) -> 0.08
A14: 10 | B14: =Inputs!$C$4+A14-1 -> 83 | D14: =IF(C14="",Inputs!$C$21,C14) -> 0.08
A15: 11 | B15: =Inputs!$C$4+A15-1 -> 84 | D15: =IF(C15="",Inputs!$C$21,C15) -> 0.08
A16: 12 | B16: =Inputs!$C$4+A16-1 -> 85 | D16: =IF(C16="",Inputs!$C$21,C16) -> 0.08
... A29: 25 | B29: =Inputs!$C$4+A29-1 -> 98 | D29: =IF(C29="",Inputs!$C$21,C29) -> 0.08

Sheet Projection
A1: Year-by-year projection – Dividends Reinvested vs Dividends Paid Out (cash)
A2: Values are end of policy year. Sum at risk (SAR) = 101% × net premiums − policy value (floor $0). Orange = SAR > 0 (insurance charges being deducted). Red = policy lapsed.
F3: DIVIDENDS REINVESTED (as in BI) | L3: DIVIDENDS PAID OUT AS CASH
A4: Policy year | B4: Age (end of year) | C4: Net return | D4: Premiums paid to date ($) | E4: Death benefit floor 101% ($) | F4: Policy value ($) | G4: Death benefit ($) | H4: Sum at risk ($) | I4: Insurance charge in year ($) | J4: Total charges in year ($) | K4: Surrender value ($) | L4: Policy value ($) | M4: Death benefit ($) | N4: Sum at risk ($) | O4: Insurance charge in year ($) | P4: Total charges in year ($) | Q4: Dividends received in year ($) | R4: Cumulative dividends ($) | S4: Policy value + cum. dividends ($) | T4: Status
A5: 1 | B5: =Inputs!$C$4+A5 -> 75 | C5: =INDEX('Return Path'!$D$5:$D$29,A5) -> 0.08 | D5: =Calc_Reinvest!I13 -> 24000 | E5: =Inputs!$C$8*D5 -> 24240 | F5: =Calc_Reinvest!Q13 -> 26290.549 | G5: =IF(Calc_Reinvest!R13=1,0,IF(A5=1,F5-SUMIFS(Calc_Reinvest!$H$2:$H$301,Calc_Reinvest!$B$2:$B$301,1),MAX(E5,F5))) -> 25330.549 | H5: =IF(OR(A5=1,Calc_Reinvest!R13=1),0,MAX(E5-F5,0)) -> 0 | I5: =SUMIFS(Calc_Reinvest!$M$2:$M$301,Calc_Reinvest!$B$2:$B$301,A5) -> 0 | J5: =SUMIFS(Calc_Reinvest!$M$2:$M$301,Calc_Reinvest!$B$2:$B$301,A5)+SUMIFS(Calc_Reinvest!$K$2:$K$301,Calc_Reinvest!$B$2:$B$301,A5) -> 643.21492 | K5: =F5*(1-INDEX(Rates!$F$4:$F$28,A5)) -> 0 | L5: =Calc_Payout!Q13 -> 24262.735 | M5: =IF(Calc_Payout!R13=1,0,IF(A5=1,L5-SUMIFS(Calc_Payout!$H$2:$H$301,Calc_Payout!$B$2:$B$301,1),MAX(E5,L5))) -> 23302.735 | N5: =IF(OR(A5=1,Calc_Payout!R13=1),0,MAX(E5-L5,0)) -> 0 | O5: =SUMIFS(Calc_Payout!$M$2:$M$301,Calc_Payout!$B$2:$B$301,A5) -> 0 | P5: =SUMIFS(Calc_Payout!$M$2:$M$301,Calc_Payout!$B$2:$B$301,A5)+SUMIFS(Calc_Payout!$K$2:$K$301,Calc_Payout!$B$2:$B$301,A5) -> 619.93281 | Q5: =SUMIFS(Calc_Payout!$N$2:$N$301,Calc_Payout!$B$2:$B$301,A5) -> 1979.6521 | R5: =Q5 -> 1979.6521 | S5: =L5+R5 -> 26242.387 | T5: =IF(Calc_Payout!R13=1,"LAPSED",IF(N5>0,"SAR active","OK")) -> OK
A6: 2 | B6: =Inputs!$C$4+A6 -> 76 | C6: =INDEX('Return Path'!$D$5:$D$29,A6) -> 0.08 | D6: =Calc_Reinvest!I25 -> 48000 | E6: =Inputs!$C$8*D6 -> 48480 | F6: =Calc_Reinvest!Q25 -> 52971.399 | G6: =IF(Calc_Reinvest!R25=1,0,IF(A6=1,F6-SUMIFS(Calc_Reinvest!$H$2:$H$301,Calc_Reinvest!$B$2:$B$301,1),MAX(E6,F6))) -> 52971.399 | H6: =IF(OR(A6=1,Calc_Reinvest!R25=1),0,MAX(E6-F6,0)) -> 0 | I6: =SUMIFS(Calc_Reinvest!$M$2:$M$301,Calc_Reinvest!$B$2:$B$301,A6) -> 0 | J6: =SUMIFS(Calc_Reinvest!$M$2:$M$301,Calc_Reinvest!$B$2:$B$301,A6)+SUMIFS(Calc_Reinvest!$K$2:$K$301,Calc_Reinvest!$B$2:$B$301,A6) -> 1295.9788 | K6: =F6*(1-INDEX(Rates!$F$4:$F$28,A6)) -> 0 | L6: =Calc_Payout!Q25 -> 46914.502 | M6: =IF(Calc_Payout!R25=1,0,IF(A6=1,L6-SUMIFS(Calc_Payout!$H$2:$H$301,Calc_Payout!$B$2:$B$301,1),MAX(E6,L6))) -> 48480 | N6: =IF(OR(A6=1,Calc_Payout!R25=1),0,MAX(E6-L6,0)) -> 1565.4978 | O6: =SUMIFS(Calc_Payout!$M$2:$M$301,Calc_Payout!$B$2:$B$301,A6) -> 0 | P6: =SUMIFS(Calc_Payout!$M$2:$M$301,Calc_Payout!$B$2:$B$301,A6)+SUMIFS(Calc_Payout!$K$2:$K$301,Calc_Payout!$B$2:$B$301,A6) -> 1198.704 | Q6: =SUMIFS(Calc_Payout!$N$2:$N$301,Calc_Payout!$B$2:$B$301,A6) -> 3827.8616 | R6: =R5+Q6 -> 5807.5137 | S6: =L6+R6 -> 52722.016 | T6: =IF(Calc_Payout!R25=1,"LAPSED",IF(N6>0,"SAR active","OK")) -> SAR active
A7: 3 | B7: =Inputs!$C$4+A7 -> 77 | C7: =INDEX('Return Path'!$D$5:$D$29,A7) -> 0.08 | D7: =Calc_Reinvest!I37 -> 72000 | E7: =Inputs!$C$8*D7 -> 72720 | F7: =Calc_Reinvest!Q37 -> 81074.531 | G7: =IF(Calc_Reinvest!R37=1,0,IF(A7=1,F7-SUMIFS(Calc_Reinvest!$H$2:$H$301,Calc_Reinvest!$B$2:$B$301,1),MAX(E7,F7))) -> 81074.531 | H7: =IF(OR(A7=1,Calc_Reinvest!R37=1),0,MAX(E7-F7,0)) -> 0 | I7: =SUMIFS(Calc_Reinvest!$M$2:$M$301,Calc_Reinvest!$B$2:$B$301,A7) -> 0 | J7: =SUMIFS(Calc_Reinvest!$M$2:$M$301,Calc_Reinvest!$B$2:$B$301,A7)+SUMIFS(Calc_Reinvest!$K$2:$K$301,Calc_Reinvest!$B$2:$B$301,A7) -> 1983.5398 | K7: =F7*(1-INDEX(Rates!$F$4:$F$28,A7)) -> 20268.633 | L7: =Calc_Payout!Q37 -> 68933.486 | M7: =IF(Calc_Payout!R37=1,0,IF(A7=1,L7-SUMIFS(Calc_Payout!$H$2:$H$301,Calc_Payout!$B$2:$B$301,1),MAX(E7,L7))) -> 72720 | N7: =IF(OR(A7=1,Calc_Payout!R37=1),0,MAX(E7-L7,0)) -> 3786.5144 | O7: =SUMIFS(Calc_Payout!$M$2:$M$301,Calc_Payout!$B$2:$B$301,A7) -> 0 | P7: =SUMIFS(Calc_Payout!$M$2:$M$301,Calc_Payout!$B$2:$B$301,A7)+SUMIFS(Calc_Payout!$K$2:$K$301,Calc_Payout!$B$2:$B$301,A7) -> 1761.3071 | Q7: =SUMIFS(Calc_Payout!$N$2:$N$301,Calc_Payout!$B$2:$B$301,A7) -> 5624.4408 | R7: =R6+Q7 -> 11431.954 | S7: =L7+R7 -> 80365.44 | T7: =IF(Calc_Payout!R37=1,"LAPSED",IF(N7>0,"SAR active","OK")) -> SAR active
A8: 4 | B8: =Inputs!$C$4+A8 -> 78 | C8: =INDEX('Return Path'!$D$5:$D$29,A8) -> 0.08 | D8: =Calc_Reinvest!I49 -> 96000 | E8: =Inputs!$C$8*D8 -> 96960 | F8: =Calc_Reinvest!Q49 -> 110675.76 | G8: =IF(Calc_Reinvest!R49=1,0,IF(A8=1,F8-SUMIFS(Calc_Reinvest!$H$2:$H$301,Calc_Reinvest!$B$2:$B$301,1),MAX(E8,F8))) -> 110675.76 | H8: =IF(OR(A8=1,Calc_Reinvest!R49=1),0,MAX(E8-F8,0)) -> 0 | I8: =SUMIFS(Calc_Reinvest!$M$2:$M$301,Calc_Reinvest!$B$2:$B$301,A8) -> 0 | J8: =SUMIFS(Calc_Reinvest!$M$2:$M$301,Calc_Reinvest!$B$2:$B$301,A8)+SUMIFS(Calc_Reinvest!$K$2:$K$301,Calc_Reinvest!$B$2:$B$301,A8) -> 2707.7527 | K8: =F8*(1-INDEX(Rates!$F$4:$F$28,A8)) -> 66405.459 | L8: =Calc_Payout!Q49 -> 90157.944 | M8: =IF(Calc_Payout!R49=1,0,IF(A8=1,L8-SUMIFS(Calc_Payout!$H$2:$H$301,Calc_Payout!$B$2:$B$301,1),MAX(E8,L8))) -> 96960 | N8: =IF(OR(A8=1,Calc_Payout!R49=1),0,MAX(E8-L8,0)) -> 6802.0558 | O8: =SUMIFS(Calc_Payout!$M$2:$M$301,Calc_Payout!$B$2:$B$301,A8) -> 182.73345 | P8: =SUMIFS(Calc_Payout!$M$2:$M$301,Calc_Payout!$B$2:$B$301,A8)+SUMIFS(Calc_Payout!$K$2:$K$301,Calc_Payout!$B$2:$B$301,A8) -> 2489.0628 | Q8: =SUMIFS(Calc_Payout!$N$2:$N$301,Calc_Payout!$B$2:$B$301,A8) -> 7363.6602 | R8: =R7+Q8 -> 18795.615 | S8: =L8+R8 -> 108953.56 | T8: =IF(Calc_Payout!R49=1,"LAPSED",IF(N8>0,"SAR active","OK")) -> SAR active
A9: 5 | B9: =Inputs!$C$4+A9 -> 79 | C9: =INDEX('Return Path'!$D$5:$D$29,A9) -> 0.08 | D9: =Calc_Reinvest!I61 -> 120000 | E9: =Inputs!$C$8*D9 -> 121200 | F9: =Calc_Reinvest!Q61 -> 141854.96 | G9: =IF(Calc_Reinvest!R61=1,0,IF(A9=1,F9-SUMIFS(Calc_Reinvest!$H$2:$H$301,Calc_Reinvest!$B$2:$B$301,1),MAX(E9,F9))) -> 141854.96 | H9: =IF(OR(A9=1,Calc_Reinvest!R61=1),0,MAX(E9-F9,0)) -> 0 | I9: =SUMIFS(Calc_Reinvest!$M$2:$M$301,Calc_Reinvest!$B$2:$B$301,A9) -> 0 | J9: =SUMIFS(Calc_Reinvest!$M$2:$M$301,Calc_Reinvest!$B$2:$B$301,A9)+SUMIFS(Calc_Reinvest!$K$2:$K$301,Calc_Reinvest!$B$2:$B$301,A9) -> 3470.5714 | K9: =F9*(1-INDEX(Rates!$F$4:$F$28,A9)) -> 113483.97 | L9: =Calc_Payout!Q61 -> 110633.99 | M9: =IF(Calc_Payout!R61=1,0,IF(A9=1,L9-SUMIFS(Calc_Payout!$H$2:$H$301,Calc_Payout!$B$2:$B$301,1),MAX(E9,L9))) -> 121200 | N9: =IF(OR(A9=1,Calc_Payout!R61=1),0,MAX(E9-L9,0)) -> 10566.015 | O9: =SUMIFS(Calc_Payout!$M$2:$M$301,Calc_Payout!$B$2:$B$301,A9) -> 341.22172 | P9: =SUMIFS(Calc_Payout!$M$2:$M$301,Calc_Payout!$B$2:$B$301,A9)+SUMIFS(Calc_Payout!$K$2:$K$301,Calc_Payout!$B$2:$B$301,A9) -> 3172.9924 | Q9: =SUMIFS(Calc_Payout!$N$2:$N$301,Calc_Payout!$B$2:$B$301,A9) -> 9040.513 | R9: =R8+Q9 -> 27836.128 | S9: =L9+R9 -> 138470.11 | T9: =IF(Calc_Payout!R61=1,"LAPSED",IF(N9>0,"SAR active","OK")) -> SAR active
A10: 6 | B10: =Inputs!$C$4+A10 -> 80 | C10: =INDEX('Return Path'!$D$5:$D$29,A10) -> 0.08 | D10: =Calc_Reinvest!I73 -> 120000 | E10: =Inputs!$C$8*D10 -> 121200 | F10: =Calc_Reinvest!Q73 -> 149416.85 | G10: =IF(Calc_Reinvest!R73=1,0,IF(A10=1,F10-SUMIFS(Calc_Reinvest!$H$2:$H$301,Calc_Reinvest!$B$2:$B$301,1),MAX(E10,F10))) -> 149416.85 | H10: =IF(OR(A10=1,Calc_Reinvest!R73=1),0,MAX(E10-F10,0)) -> 0 | I10: =SUMIFS(Calc_Reinvest!$M$2:$M$301,Calc_Reinvest!$B$2:$B$301,A10) -> 0 | J10: =SUMIFS(Calc_Reinvest!$M$2:$M$301,Calc_Reinvest!$B$2:$B$301,A10)+SUMIFS(Calc_Reinvest!$K$2:$K$301,Calc_Reinvest!$B$2:$B$301,A10) -> 3655.5779 | K10: =F10*(1-INDEX(Rates!$F$4:$F$28,A10)) -> 149416.85 | L10: =Calc_Payout!Q73 -> 107009.84 | M10: =IF(Calc_Payout!R73=1,0,IF(A10=1,L10-SUMIFS(Calc_Payout!$H$2:$H$301,Calc_Payout!$B$2:$B$301,1),MAX(E10,L10))) -> 121200 | N10: =IF(OR(A10=1,Calc_Payout!R73=1),0,MAX(E10-L10,0)) -> 14190.164 | O10: =SUMIFS(Calc_Payout!$M$2:$M$301,Calc_Payout!$B$2:$B$301,A10) -> 543.74635 | P10: =SUMIFS(Calc_Payout!$M$2:$M$301,Calc_Payout!$B$2:$B$301,A10)+SUMIFS(Calc_Payout!$K$2:$K$301,Calc_Payout!$B$2:$B$301,A10) -> 3285.7324 | Q10: =SUMIFS(Calc_Payout!$N$2:$N$301,Calc_Payout!$B$2:$B$301,A10) -> 8752.4505 | R10: =R9+Q10 -> 36588.578 | S10: =L10+R10 -> 143598.41 | T10: =IF(Calc_Payout!R73=1,"LAPSED",IF(N10>0,"SAR active","OK")) -> SAR active
A11: 7 | B11: =Inputs!$C$4+A11 -> 81 | C11: =INDEX('Return Path'!$D$5:$D$29,A11) -> 0.08 | D11: =Calc_Reinvest!I85 -> 120000 | E11: =Inputs!$C$8*D11 -> 121200 | F11: =Calc_Reinvest!Q85 -> 157381.85 | G11: =IF(Calc_Reinvest!R85=1,0,IF(A11=1,F11-SUMIFS(Calc_Reinvest!$H$2:$H$301,Calc_Reinvest!$B$2:$B$301,1),MAX(E11,F11))) -> 157381.85 | H11: =IF(OR(A11=1,Calc_Reinvest!R85=1),0,MAX(E11-F11,0)) -> 0 | I11: =SUMIFS(Calc_Reinvest!$M$2:$M$301,Calc_Reinvest!$B$2:$B$301,A11) -> 0 | J11: =SUMIFS(Calc_Reinvest!$M$2:$M$301,Calc_Reinvest!$B$2:$B$301,A11)+SUMIFS(Calc_Reinvest!$K$2:$K$301,Calc_Reinvest!$B$2:$B$301,A11) -> 3850.4467 | K11: =F11*(1-INDEX(Rates!$F$4:$F$28,A11)) -> 157381.85 | L11: =Calc_Payout!Q85 -> 103251.25 | M11: =IF(Calc_Payout!R85=1,0,IF(A11=1,L11-SUMIFS(Calc_Payout!$H$2:$H$301,Calc_Payout!$B$2:$B$301,1),MAX(E11,L11))) -> 121200 | N11: =IF(OR(A11=1,Calc_Payout!R85=1),0,MAX(E11-L11,0)) -> 17948.752 | O11: =SUMIFS(Calc_Payout!$M$2:$M$301,Calc_Payout!$B$2:$B$301,A11) -> 784.0479 | P11: =SUMIFS(Calc_Payout!$M$2:$M$301,Calc_Payout!$B$2:$B$301,A11)+SUMIFS(Calc_Payout!$K$2:$K$301,Calc_Payout!$B$2:$B$301,A11) -> 3433.3368 | Q11: =SUMIFS(Calc_Payout!$N$2:$N$301,Calc_Payout!$B$2:$B$301,A11) -> 8454.8354 | R11: =R10+Q11 -> 45043.414 | S11: =L11+R11 -> 148294.66 | T11: =IF(Calc_Payout!R85=1,"LAPSED",IF(N11>0,"SAR active","OK")) -> SAR active
A12: 8 | B12: =Inputs!$C$4+A12 -> 82 | C12: =INDEX('Return Path'!$D$5:$D$29,A12) -> 0.08 | D12: =Calc_Reinvest!I97 -> 120000 | E12: =Inputs!$C$8*D12 -> 121200 | F12: =Calc_Reinvest!Q97 -> 165771.44 | G12: =IF(Calc_Reinvest!R97=1,0,IF(A12=1,F12-SUMIFS(Calc_Reinvest!$H$2:$H$301,Calc_Reinvest!$B$2:$B$301,1),MAX(E12,F12))) -> 165771.44 | H12: =IF(OR(A12=1,Calc_Reinvest!R97=1),0,MAX(E12-F12,0)) -> 0 | I12: =SUMIFS(Calc_Reinvest!$M$2:$M$301,Calc_Reinvest!$B$2:$B$301,A12) -> 0 | J12: =SUMIFS(Calc_Reinvest!$M$2:$M$301,Calc_Reinvest!$B$2:$B$301,A12)+SUMIFS(Calc_Reinvest!$K$2:$K$301,Calc_Reinvest!$B$2:$B$301,A12) -> 4055.7034 | K12: =F12*(1-INDEX(Rates!$F$4:$F$28,A12)) -> 165771.44 | L12: =Calc_Payout!Q97 -> 99257.195 | M12: =IF(Calc_Payout!R97=1,0,IF(A12=1,L12-SUMIFS(Calc_Payout!$H$2:$H$301,Calc_Payout!$B$2:$B$301,1),MAX(E12,L12))) -> 121200 | N12: =IF(OR(A12=1,Calc_Payout!R97=1),0,MAX(E12-L12,0)) -> 21942.805 | O12: =SUMIFS(Calc_Payout!$M$2:$M$301,Calc_Payout!$B$2:$B$301,A12) -> 1131.1621 | P12: =SUMIFS(Calc_Payout!$M$2:$M$301,Calc_Payout!$B$2:$B$301,A12)+SUMIFS(Calc_Payout!$K$2:$K$301,Calc_Payout!$B$2:$B$301,A12) -> 3683.2415 | Q12: =SUMIFS(Calc_Payout!$N$2:$N$301,Calc_Payout!$B$2:$B$301,A12) -> 8142.0993 | R12: =R11+Q12 -> 53185.513 | S12: =L12+R12 -> 152442.71 | T12: =IF(Calc_Payout!R97=1,"LAPSED",IF(N12>0,"SAR active","OK")) -> SAR active
A13: 9 | B13: =Inputs!$C$4+A13 -> 83 | C13: =INDEX('Return Path'!$D$5:$D$29,A13) -> 0.08 | D13: =Calc_Reinvest!I109 -> 120000 | E13: =Inputs!$C$8*D13 -> 121200 | F13: =Calc_Reinvest!Q109 -> 174608.26 | G13: =IF(Calc_Reinvest!R109=1,0,IF(A13=1,F13-SUMIFS(Calc_Reinvest!$H$2:$H$301,Calc_Reinvest!$B$2:$B$301,1),MAX(E13,F13))) -> 174608.26 | H13: =IF(OR(A13=1,Calc_Reinvest!R109=1),0,MAX(E13-F13,0)) -> 0 | I13: =SUMIFS(Calc_Reinvest!$M$2:$M$301,Calc_Reinvest!$B$2:$B$301,A13) -> 0 | J13: =SUMIFS(Calc_Reinvest!$M$2:$M$301,Calc_Reinvest!$B$2:$B$301,A13)+SUMIFS(Calc_Reinvest!$K$2:$K$301,Calc_Reinvest!$B$2:$B$301,A13) -> 4271.9017 | K13: =F13*(1-INDEX(Rates!$F$4:$F$28,A13)) -> 174608.26 | L13: =Calc_Payout!Q109 -> 94957.678 | M13: =IF(Calc_Payout!R109=1,0,IF(A13=1,L13-SUMIFS(Calc_Payout!$H$2:$H$301,Calc_Payout!$B$2:$B$301,1),MAX(E13,L13))) -> 121200 | N13: =IF(OR(A13=1,Calc_Payout!R109=1),0,MAX(E13-L13,0)) -> 26242.322 | O13: =SUMIFS(Calc_Payout!$M$2:$M$301,Calc_Payout!$B$2:$B$301,A13) -> 1556.3538 | P13: =SUMIFS(Calc_Payout!$M$2:$M$301,Calc_Payout!$B$2:$B$301,A13)+SUMIFS(Calc_Payout!$K$2:$K$301,Calc_Payout!$B$2:$B$301,A13) -> 4004.5052 | Q13: =SUMIFS(Calc_Payout!$N$2:$N$301,Calc_Payout!$B$2:$B$301,A13) -> 7807.3877 | R13: =R12+Q13 -> 60992.901 | S13: =L13+R13 -> 155950.58 | T13: =IF(Calc_Payout!R109=1,"LAPSED",IF(N13>0,"SAR active","OK")) -> SAR active
A14: 10 | B14: =Inputs!$C$4+A14 -> 84 | C14: =INDEX('Return Path'!$D$5:$D$29,A14) -> 0.08 | D14: =Calc_Reinvest!I121 -> 120000 | E14: =Inputs!$C$8*D14 -> 121200 | F14: =Calc_Reinvest!Q121 -> 184835.73 | G14: =IF(Calc_Reinvest!R121=1,0,IF(A14=1,F14-SUMIFS(Calc_Reinvest!$H$2:$H$301,Calc_Reinvest!$B$2:$B$301,1),MAX(E14,F14))) -> 184835.73 | H14: =IF(OR(A14=1,Calc_Reinvest!R121=1),0,MAX(E14-F14,0)) -> 0 | I14: =SUMIFS(Calc_Reinvest!$M$2:$M$301,Calc_Reinvest!$B$2:$B$301,A14) -> 0 | J14: =SUMIFS(Calc_Reinvest!$M$2:$M$301,Calc_Reinvest!$B$2:$B$301,A14)+SUMIFS(Calc_Reinvest!$K$2:$K$301,Calc_Reinvest!$B$2:$B$301,A14) -> 4499.625 | K14: =F14*(1-INDEX(Rates!$F$4:$F$28,A14)) -> 184835.73 | L14: =Calc_Payout!Q121 -> 90724.467 | M14: =IF(Calc_Payout!R121=1,0,IF(A14=1,L14-SUMIFS(Calc_Payout!$H$2:$H$301,Calc_Payout!$B$2:$B$301,1),MAX(E14,L14))) -> 121200 | N14: =IF(OR(A14=1,Calc_Payout!R121=1),0,MAX(E14-L14,0)) -> 30475.533 | O14: =SUMIFS(Calc_Payout!$M$2:$M$301,Calc_Payout!$B$2:$B$301,A14) -> 2071.3959 | P14: =SUMIFS(Calc_Payout!$M$2:$M$301,Calc_Payout!$B$2:$B$301,A14)+SUMIFS(Calc_Payout!$K$2:$K$301,Calc_Payout!$B$2:$B$301,A14) -> 4407.0328 | Q14: =SUMIFS(Calc_Payout!$N$2:$N$301,Calc_Payout!$B$2:$B$301,A14) -> 7444.658 | R14: =R13+Q14 -> 68437.559 | S14: =L14+R14 -> 159162.03 | T14: =IF(Calc_Payout!R121=1,"LAPSED",IF(N14>0,"SAR active","OK")) -> SAR active
A15: 11 | B15: =Inputs!$C$4+A15 -> 85 | C15: =INDEX('Return Path'!$D$5:$D$29,A15) -> 0.08 | D15: =Calc_Reinvest!I133 -> 120000 | E15: =Inputs!$C$8*D15 -> 121200 | F15: =Calc_Reinvest!Q133 -> 199420.28 | G15: =IF(Calc_Reinvest!R133=1,0,IF(A15=1,F15-SUMIFS(Calc_Reinvest!$H$2:$H$301,Calc_Reinvest!$B$2:$B$301,1),MAX(E15,F15))) -> 199420.28 | H15: =IF(OR(A15=1,Calc_Reinvest!R133=1),0,MAX(E15-F15,0)) -> 0 | I15: =SUMIFS(Calc_Reinvest!$M$2:$M$301,Calc_Reinvest!$B$2:$B$301,A15) -> 0 | J15: =SUMIFS(Calc_Reinvest!$M$2:$M$301,Calc_Reinvest!$B$2:$B$301,A15)+SUMIFS(Calc_Reinvest!$K$2:$K$301,Calc_Reinvest!$B$2:$B$301,A15) -> 1153.2875 | K15: =F15*(1-INDEX(Rates!$F$4:$F$28,A15)) -> 199420.28 | L15: =Calc_Payout!Q133 -> 87772.454 | M15: =IF(Calc_Payout!R133=1,0,IF(A15=1,L15-SUMIFS(Calc_Payout!$H$2:$H$301,Calc_Payout!$B$2:$B$301,1),MAX(E15,L15))) -> 121200 | N15: =IF(OR(A15=1,Calc_Payout!R133=1),0,MAX(E15-L15,0)) -> 33427.546 | O15: =SUMIFS(Calc_Payout!$M$2:$M$301,Calc_Payout!$B$2:$B$301,A15) -> 2575.9632 | P15: =SUMIFS(Calc_Payout!$M$2:$M$301,Calc_Payout!$B$2:$B$301,A15)+SUMIFS(Calc_Payout!$K$2:$K$301,Calc_Payout!$B$2:$B$301,A15) -> 3114.5558 | Q15: =SUMIFS(Calc_Payout!$N$2:$N$301,Calc_Payout!$B$2:$B$301,A15) -> 7160.4711 | R15: =R14+Q15 -> 75598.03 | S15: =L15+R15 -> 163370.48 | T15: =IF(Calc_Payout!R133=1,"LAPSED",IF(N15>0,"SAR active","OK")) -> SAR active
A16: 12 | B16: =Inputs!$C$4+A16 -> 86 | C16: =INDEX('Return Path'!$D$5:$D$29,A16) -> 0.08 | D16: =Calc_Reinvest!I145 -> 120000 | E16: =Inputs!$C$8*D16 -> 121200 | F16: =Calc_Reinvest!Q145 -> 215155.63 | G16: =IF(Calc_Reinvest!R145=1,0,IF(A16=1,F16-SUMIFS(Calc_Reinvest!$H$2:$H$301,Calc_Reinvest!$B$2:$B$301,1),MAX(E16,F16))) -> 215155.63 | H16: =IF(OR(A16=1,Calc_Reinvest!R145=1),0,MAX(E16-F16,0)) -> 0 | I16: =SUMIFS(Calc_Reinvest!$M$2:$M$301,Calc_Reinvest!$B$2:$B$301,A16) -> 0 | J16: =SUMIFS(Calc_Reinvest!$M$2:$M$301,Calc_Reinvest!$B$2:$B$301,A16)+SUMIFS(Calc_Reinvest!$K$2:$K$301,Calc_Reinvest!$B$2:$B$301,A16) -> 1244.2882 | K16: =F16*(1-INDEX(Rates!$F$4:$F$28,A16)) -> 215155.63 | L16: =Calc_Payout!Q145 -> 84305.54 | M16: =IF(Calc_Payout!R145=1,0,IF(A16=1,L16-SUMIFS(Calc_Payout!$H$2:$H$301,Calc_Payout!$B$2:$B$301,1),MAX(E16,L16))) -> 121200 | N16: =IF(OR(A16=1,Calc_Payout!R145=1),0,MAX(E16-L16,0)) -> 36894.46 | O16: =SUMIFS(Calc_Payout!$M$2:$M$301,Calc_Payout!$B$2:$B$301,A16) -> 3106.694 | P16: =SUMIFS(Calc_Payout!$M$2:$M$301,Calc_Payout!$B$2:$B$301,A16)+SUMIFS(Calc_Payout!$K$2:$K$301,Calc_Payout!$B$2:$B$301,A16) -> 3626.1161 | Q16: =SUMIFS(Calc_Payout!$N$2:$N$301,Calc_Payout!$B$2:$B$301,A16) -> 6901.4548 | R16: =R15+Q16 -> 82499.484 | S16: =L16+R16 -> 166805.02 | T16: =IF(Calc_Payout!R145=1,"LAPSED",IF(N16>0,"SAR active","OK")) -> SAR active
A17: 13 | B17: =Inputs!$C$4+A17 -> 87 | C17: =INDEX('Return Path'!$D$5:$D$29,A17) -> 0.08 | D17: =Calc_Reinvest!I157 -> 120000 | E17: =Inputs!$C$8*D17 -> 121200 | F17: =Calc_Reinvest!Q157 -> 232132.59 | G17: =IF(Calc_Reinvest!R157=1,0,IF(A17=1,F17-SUMIFS(Calc_Reinvest!$H$2:$H$301,Calc_Reinvest!$B$2:$B$301,1),MAX(E17,F17))) -> 232132.59 | H17: =IF(OR(A17=1,Calc_Reinvest!R157=1),0,MAX(E17-F17,0)) -> 0 | I17: =SUMIFS(Calc_Reinvest!$M$2:$M$301,Calc_Reinvest!$B$2:$B$301,A17) -> 0 | J17: =SUMIFS(Calc_Reinvest!$M$2:$M$301,Calc_Reinvest!$B$2:$B$301,A17)+SUMIFS(Calc_Reinvest!$K$2:$K$301,Calc_Reinvest!$B$2:$B$301,A17) -> 1342.4693 | K17: =F17*(1-INDEX(Rates!$F$4:$F$28,A17)) -> 232132.59 | L17: =Calc_Payout!Q157 -> 79991.694 | M17: =IF(Calc_Payout!R157=1,0,IF(A17=1,L17-SUMIFS(Calc_Payout!$H$2:$H$301,Calc_Payout!$B$2:$B$301,1),MAX(E17,L17))) -> 121200 | N17: =IF(OR(A17=1,Calc_Payout!R157=1),0,MAX(E17-L17,0)) -> 41208.306 | O17: =SUMIFS(Calc_Payout!$M$2:$M$301,Calc_Payout!$B$2:$B$301,A17) -> 3973.6224 | P17: =SUMIFS(Calc_Payout!$M$2:$M$301,Calc_Payout!$B$2:$B$301,A17)+SUMIFS(Calc_Payout!$K$2:$K$301,Calc_Payout!$B$2:$B$301,A17) -> 4469.8891 | Q17: =SUMIFS(Calc_Payout!$N$2:$N$301,Calc_Payout!$B$2:$B$301,A17) -> 6587.091 | R17: =R16+Q17 -> 89086.575 | S17: =L17+R17 -> 169078.27 | T17: =IF(Calc_Payout!R157=1,"LAPSED",IF(N17>0,"SAR active","OK")) -> SAR active
A18: 14 | B18: =Inputs!$C$4+A18 -> 88 | C18: =INDEX('Return Path'!$D$5:$D$29,A18) -> 0.08 | D18: =Calc_Reinvest!I169 -> 120000 | E18: =Inputs!$C$8*D18 -> 121200 | F18: =Calc_Reinvest!Q169 -> 250449.12 | G18: =IF(Calc_Reinvest!R169=1,0,IF(A18=1,F18-SUMIFS(Calc_Reinvest!$H$2:$H$301,Calc_Reinvest!$B$2:$B$301,1),MAX(E18,F18))) -> 250449.12 | H18: =IF(OR(A18=1,Calc_Reinvest!R169=1),0,MAX(E18-F18,0)) -> 0 | I18: =SUMIFS(Calc_Reinvest!$M$2:$M$301,Calc_Reinvest!$B$2:$B$301,A18) -> 0 | J18: =SUMIFS(Calc_Reinvest!$M$2:$M$301,Calc_Reinvest!$B$2:$B$301,A18)+SUMIFS(Calc_Reinvest!$K$2:$K$301,Calc_Reinvest!$B$2:$B$301,A18) -> 1448.3975 | K18: =F18*(1-INDEX(Rates!$F$4:$F$28,A18)) -> 250449.12 | L18: =Calc_Payout!Q169 -> 74621.484 | M18: =IF(Calc_Payout!R169=1,0,IF(A18=1,L18-SUMIFS(Calc_Payout!$H$2:$H$301,Calc_Payout!$B$2:$B$301,1),MAX(E18,L18))) -> 121200 | N18: =IF(OR(A18=1,Calc_Payout!R169=1),0,MAX(E18-L18,0)) -> 46578.516 | O18: =SUMIFS(Calc_Payout!$M$2:$M$301,Calc_Payout!$B$2:$B$301,A18) -> 5054.8744 | P18: =SUMIFS(Calc_Payout!$M$2:$M$301,Calc_Payout!$B$2:$B$301,A18)+SUMIFS(Calc_Payout!$K$2:$K$301,Calc_Payout!$B$2:$B$301,A18) -> 5522.3283 | Q18: =SUMIFS(Calc_Payout!$N$2:$N$301,Calc_Payout!$B$2:$B$301,A18) -> 6195.9032 | R18: =R17+Q18 -> 95282.479 | S18: =L18+R18 -> 169903.96 | T18: =IF(Calc_Payout!R169=1,"LAPSED",IF(N18>0,"SAR active","OK")) -> SAR active
A19: 15 | B19: =Inputs!$C$4+A19 -> 89 | C19: =INDEX('Return Path'!$D$5:$D$29,A19) -> 0.08 | D19: =Calc_Reinvest!I181 -> 120000 | E19: =Inputs!$C$8*D19 -> 121200 | F19: =Calc_Reinvest!Q181 -> 270210.93 | G19: =IF(Calc_Reinvest!R181=1,0,IF(A19=1,F19-SUMIFS(Calc_Reinvest!$H$2:$H$301,Calc_Reinvest!$B$2:$B$301,1),MAX(E19,F19))) -> 270210.93 | H19: =IF(OR(A19=1,Calc_Reinvest!R181=1),0,MAX(E19-F19,0)) -> 0 | I19: =SUMIFS(Calc_Reinvest!$M$2:$M$301,Calc_Reinvest!$B$2:$B$301,A19) -> 0 | J19: =SUMIFS(Calc_Reinvest!$M$2:$M$301,Calc_Reinvest!$B$2:$B$301,A19)+SUMIFS(Calc_Reinvest!$K$2:$K$301,Calc_Reinvest!$B$2:$B$301,A19) -> 1562.684 | K19: =F19*(1-INDEX(Rates!$F$4:$F$28,A19)) -> 270210.93 | L19: =Calc_Payout!Q181 -> 67917.263 | M19: =IF(Calc_Payout!R181=1,0,IF(A19=1,L19-SUMIFS(Calc_Payout!$H$2:$H$301,Calc_Payout!$B$2:$B$301,1),MAX(E19,L19))) -> 121200 | N19: =IF(OR(A19=1,Calc_Payout!R181=1),0,MAX(E19-L19,0)) -> 53282.737 | O19: =SUMIFS(Calc_Payout!$M$2:$M$301,Calc_Payout!$B$2:$B$301,A19) -> 6419.9676 | P19: =SUMIFS(Calc_Payout!$M$2:$M$301,Calc_Payout!$B$2:$B$301,A19)+SUMIFS(Calc_Payout!$K$2:$K$301,Calc_Payout!$B$2:$B$301,A19) -> 6851.5096 | Q19: =SUMIFS(Calc_Payout!$N$2:$N$301,Calc_Payout!$B$2:$B$301,A19) -> 5708.2167 | R19: =R18+Q19 -> 100990.7 | S19: =L19+R19 -> 168907.96 | T19: =IF(Calc_Payout!R181=1,"LAPSED",IF(N19>0,"SAR active","OK")) -> SAR active
A20: 16 | B20: =Inputs!$C$4+A20 -> 90 | C20: =INDEX('Return Path'!$D$5:$D$29,A20) -> 0.08 | D20: =Calc_Reinvest!I193 -> 120000 | E20: =Inputs!$C$8*D20 -> 121200 | F20: =Calc_Reinvest!Q193 -> 291532.05 | G20: =IF(Calc_Reinvest!R193=1,0,IF(A20=1,F20-SUMIFS(Calc_Reinvest!$H$2:$H$301,Calc_Reinvest!$B$2:$B$301,1),MAX(E20,F20))) -> 291532.05 | H20: =IF(OR(A20=1,Calc_Reinvest!R193=1),0,MAX(E20-F20,0)) -> 0 | I20: =SUMIFS(Calc_Reinvest!$M$2:$M$301,Calc_Reinvest!$B$2:$B$301,A20) -> 0 | J20: =SUMIFS(Calc_Reinvest!$M$2:$M$301,Calc_Reinvest!$B$2:$B$301,A20)+SUMIFS(Calc_Reinvest!$K$2:$K$301,Calc_Reinvest!$B$2:$B$301,A20) -> 1685.9883 | K20: =F20*(1-INDEX(Rates!$F$4:$F$28,A20)) -> 291532.05 | L20: =Calc_Payout!Q193 -> 59509.27 | M20: =IF(Calc_Payout!R193=1,0,IF(A20=1,L20-SUMIFS(Calc_Payout!$H$2:$H$301,Calc_Payout!$B$2:$B$301,1),MAX(E20,L20))) -> 121200 | N20: =IF(OR(A20=1,Calc_Payout!R193=1),0,MAX(E20-L20,0)) -> 61690.73 | O20: =SUMIFS(Calc_Payout!$M$2:$M$301,Calc_Payout!$B$2:$B$301,A20) -> 8162.7512 | P20: =SUMIFS(Calc_Payout!$M$2:$M$301,Calc_Payout!$B$2:$B$301,A20)+SUMIFS(Calc_Payout!$K$2:$K$301,Calc_Payout!$B$2:$B$301,A20) -> 8549.3673 | Q20: =SUMIFS(Calc_Payout!$N$2:$N$301,Calc_Payout!$B$2:$B$301,A20) -> 5097.8849 | R20: =R19+Q20 -> 106088.58 | S20: =L20+R20 -> 165597.85 | T20: =IF(Calc_Payout!R193=1,"LAPSED",IF(N20>0,"SAR active","OK")) -> SAR active
A21: 17 | B21: =Inputs!$C$4+A21 -> 91 | C21: =INDEX('Return Path'!$D$5:$D$29,A21) -> 0.08 | D21: =Calc_Reinvest!I205 -> 120000 | E21: =Inputs!$C$8*D21 -> 121200 | F21: =Calc_Reinvest!Q205 -> 314535.53 | G21: =IF(Calc_Reinvest!R205=1,0,IF(A21=1,F21-SUMIFS(Calc_Reinvest!$H$2:$H$301,Calc_Reinvest!$B$2:$B$301,1),MAX(E21,F21))) -> 314535.53 | H21: =IF(OR(A21=1,Calc_Reinvest!R205=1),0,MAX(E21-F21,0)) -> 0 | I21: =SUMIFS(Calc_Reinvest!$M$2:$M$301,Calc_Reinvest!$B$2:$B$301,A21) -> 0 | J21: =SUMIFS(Calc_Reinvest!$M$2:$M$301,Calc_Reinvest!$B$2:$B$301,A21)+SUMIFS(Calc_Reinvest!$K$2:$K$301,Calc_Reinvest!$B$2:$B$301,A21) -> 1819.0221 | K21: =F21*(1-INDEX(Rates!$F$4:$F$28,A21)) -> 314535.53 | L21: =Calc_Payout!Q205 -> 48902.135 | M21: =IF(Calc_Payout!R205=1,0,IF(A21=1,L21-SUMIFS(Calc_Payout!$H$2:$H$301,Calc_Payout!$B$2:$B$301,1),MAX(E21,L21))) -> 121200 | N21: =IF(OR(A21=1,Calc_Payout!R205=1),0,MAX(E21-L21,0)) -> 72297.865 | O21: =SUMIFS(Calc_Payout!$M$2:$M$301,Calc_Payout!$B$2:$B$301,A21) -> 10411.167 | P21: =SUMIFS(Calc_Payout!$M$2:$M$301,Calc_Payout!$B$2:$B$301,A21)+SUMIFS(Calc_Payout!$K$2:$K$301,Calc_Payout!$B$2:$B$301,A21) -> 10741.286 | Q21: =SUMIFS(Calc_Payout!$N$2:$N$301,Calc_Payout!$B$2:$B$301,A21) -> 4329.9729 | R21: =R20+Q21 -> 110418.55 | S21: =L21+R21 -> 159320.69 | T21: =IF(Calc_Payout!R205=1,"LAPSED",IF(N21>0,"SAR active","OK")) -> SAR active
A22: 18 | B22: =Inputs!$C$4+A22 -> 92 | C22: =INDEX('Return Path'!$D$5:$D$29,A22) -> 0.08 | D22: =Calc_Reinvest!I217 -> 120000 | E22: =Inputs!$C$8*D22 -> 121200 | F22: =Calc_Reinvest!Q217 -> 339354.11 | G22: =IF(Calc_Reinvest!R217=1,0,IF(A22=1,F22-SUMIFS(Calc_Reinvest!$H$2:$H$301,Calc_Reinvest!$B$2:$B$301,1),MAX(E22,F22))) -> 339354.11 | H22: =IF(OR(A22=1,Calc_Reinvest!R217=1),0,MAX(E22-F22,0)) -> 0 | I22: =SUMIFS(Calc_Reinvest!$M$2:$M$301,Calc_Reinvest!$B$2:$B$301,A22) -> 0 | J22: =SUMIFS(Calc_Reinvest!$M$2:$M$301,Calc_Reinvest!$B$2:$B$301,A22)+SUMIFS(Calc_Reinvest!$K$2:$K$301,Calc_Reinvest!$B$2:$B$301,A22) -> 1962.5529 | K22: =F22*(1-INDEX(Rates!$F$4:$F$28,A22)) -> 339354.11 | L22: =Calc_Payout!Q217 -> 35032.777 | M22: =IF(Calc_Payout!R217=1,0,IF(A22=1,L22-SUMIFS(Calc_Payout!$H$2:$H$301,Calc_Payout!$B$2:$B$301,1),MAX(E22,L22))) -> 121200 | N22: =IF(OR(A22=1,Calc_Payout!R217=1),0,MAX(E22-L22,0)) -> 86167.223 | O22: =SUMIFS(Calc_Payout!$M$2:$M$301,Calc_Payout!$B$2:$B$301,A22) -> 13738.328 | P22: =SUMIFS(Calc_Payout!$M$2:$M$301,Calc_Payout!$B$2:$B$301,A22)+SUMIFS(Calc_Payout!$K$2:$K$301,Calc_Payout!$B$2:$B$301,A22) -> 13995.916 | Q22: =SUMIFS(Calc_Payout!$N$2:$N$301,Calc_Payout!$B$2:$B$301,A22) -> 3341.2119 | R22: =R21+Q22 -> 113759.77 | S22: =L22+R22 -> 148792.54 | T22: =IF(Calc_Payout!R217=1,"LAPSED",IF(N22>0,"SAR active","OK")) -> SAR active
A23: 19 | B23: =Inputs!$C$4+A23 -> 93 | C23: =INDEX('Return Path'!$D$5:$D$29,A23) -> 0.08 | D23: =Calc_Reinvest!I229 -> 120000 | E23: =Inputs!$C$8*D23 -> 121200 | F23: =Calc_Reinvest!Q229 -> 366131 | G23: =IF(Calc_Reinvest!R229=1,0,IF(A23=1,F23-SUMIFS(Calc_Reinvest!$H$2:$H$301,Calc_Reinvest!$B$2:$B$301,1),MAX(E23,F23))) -> 366131 | H23: =IF(OR(A23=1,Calc_Reinvest!R229=1),0,MAX(E23-F23,0)) -> 0 | I23: =SUMIFS(Calc_Reinvest!$M$2:$M$301,Calc_Reinvest!$B$2:$B$301,A23) -> 0 | J23: =SUMIFS(Calc_Reinvest!$M$2:$M$301,Calc_Reinvest!$B$2:$B$301,A23)+SUMIFS(Calc_Reinvest!$K$2:$K$301,Calc_Reinvest!$B$2:$B$301,A23) -> 2117.409 | K23: =F23*(1-INDEX(Rates!$F$4:$F$28,A23)) -> 366131 | L23: =Calc_Payout!Q229 -> 16750.11 | M23: =IF(Calc_Payout!R229=1,0,IF(A23=1,L23-SUMIFS(Calc_Payout!$H$2:$H$301,Calc_Payout!$B$2:$B$301,1),MAX(E23,L23))) -> 121200 | N23: =IF(OR(A23=1,Calc_Payout!R229=1),0,MAX(E23-L23,0)) -> 104449.89 | O23: =SUMIFS(Calc_Payout!$M$2:$M$301,Calc_Payout!$B$2:$B$301,A23) -> 18237.354 | P23: =SUMIFS(Calc_Payout!$M$2:$M$301,Calc_Payout!$B$2:$B$301,A23)+SUMIFS(Calc_Payout!$K$2:$K$301,Calc_Payout!$B$2:$B$301,A23) -> 18399.749 | Q23: =SUMIFS(Calc_Payout!$N$2:$N$301,Calc_Payout!$B$2:$B$301,A23) -> 2042.6003 | R23: =R22+Q23 -> 115802.37 | S23: =L23+R23 -> 132552.48 | T23: =IF(Calc_Payout!R229=1,"LAPSED",IF(N23>0,"SAR active","OK")) -> SAR active
A24: 20 | B24: =Inputs!$C$4+A24 -> 94 | C24: =INDEX('Return Path'!$D$5:$D$29,A24) -> 0.08 | D24: =Calc_Reinvest!I241 -> 120000 | E24: =Inputs!$C$8*D24 -> 121200 | F24: =Calc_Reinvest!Q241 -> 395020.75 | G24: =IF(Calc_Reinvest!R241=1,0,IF(A24=1,F24-SUMIFS(Calc_Reinvest!$H$2:$H$301,Calc_Reinvest!$B$2:$B$301,1),MAX(E24,F24))) -> 395020.75 | H24: =IF(OR(A24=1,Calc_Reinvest!R241=1),0,MAX(E24-F24,0)) -> 0 | I24: =SUMIFS(Calc_Reinvest!$M$2:$M$301,Calc_Reinvest!$B$2:$B$301,A24) -> 0 | J24: =SUMIFS(Calc_Reinvest!$M$2:$M$301,Calc_Reinvest!$B$2:$B$301,A24)+SUMIFS(Calc_Reinvest!$K$2:$K$301,Calc_Reinvest!$B$2:$B$301,A24) -> 2284.4842 | K24: =F24*(1-INDEX(Rates!$F$4:$F$28,A24)) -> 395020.75 | L24: =Calc_Payout!Q241 -> 0 | M24: =IF(Calc_Payout!R241=1,0,IF(A24=1,L24-SUMIFS(Calc_Payout!$H$2:$H$301,Calc_Payout!$B$2:$B$301,1),MAX(E24,L24))) -> 0 | N24: =IF(OR(A24=1,Calc_Payout!R241=1),0,MAX(E24-L24,0)) -> 0 | O24: =SUMIFS(Calc_Payout!$M$2:$M$301,Calc_Payout!$B$2:$B$301,A24) -> 17813.879 | P24: =SUMIFS(Calc_Payout!$M$2:$M$301,Calc_Payout!$B$2:$B$301,A24)+SUMIFS(Calc_Payout!$K$2:$K$301,Calc_Payout!$B$2:$B$301,A24) -> 17854.99 | Q24: =SUMIFS(Calc_Payout!$N$2:$N$301,Calc_Payout!$B$2:$B$301,A24) -> 435.88677 | R24: =R23+Q24 -> 116238.25 | S24: =L24+R24 -> 116238.25 | T24: =IF(Calc_Payout!R241=1,"LAPSED",IF(N24>0,"SAR active","OK")) -> LAPSED
A25: 21 | B25: =Inputs!$C$4+A25 -> 95 | C25: =INDEX('Return Path'!$D$5:$D$29,A25) -> 0.08 | D25: =Calc_Reinvest!I253 -> 120000 | E25: =Inputs!$C$8*D25 -> 121200 | F25: =Calc_Reinvest!Q253 -> 426190.05 | G25: =IF(Calc_Reinvest!R253=1,0,IF(A25=1,F25-SUMIFS(Calc_Reinvest!$H$2:$H$301,Calc_Reinvest!$B$2:$B$301,1),MAX(E25,F25))) -> 426190.05 | H25: =IF(OR(A25=1,Calc_Reinvest!R253=1),0,MAX(E25-F25,0)) -> 0 | I25: =SUMIFS(Calc_Reinvest!$M$2:$M$301,Calc_Reinvest!$B$2:$B$301,A25) -> 0 | J25: =SUMIFS(Calc_Reinvest!$M$2:$M$301,Calc_Reinvest!$B$2:$B$301,A25)+SUMIFS(Calc_Reinvest!$K$2:$K$301,Calc_Reinvest!$B$2:$B$301,A25) -> 2464.7425 | K25: =F25*(1-INDEX(Rates!$F$4:$F$28,A25)) -> 426190.05 | L25: =Calc_Payout!Q253 -> 0 | M25: =IF(Calc_Payout!R253=1,0,IF(A25=1,L25-SUMIFS(Calc_Payout!$H$2:$H$301,Calc_Payout!$B$2:$B$301,1),MAX(E25,L25))) -> 0 | N25: =IF(OR(A25=1,Calc_Payout!R253=1),0,MAX(E25-L25,0)) -> 0 | O25: =SUMIFS(Calc_Payout!$M$2:$M$301,Calc_Payout!$B$2:$B$301,A25) -> 0 | P25: =SUMIFS(Calc_Payout!$M$2:$M$301,Calc_Payout!$B$2:$B$301,A25)+SUMIFS(Calc_Payout!$K$2:$K$301,Calc_Payout!$B$2:$B$301,A25) -> 0 | Q25: =SUMIFS(Calc_Payout!$N$2:$N$301,Calc_Payout!$B$2:$B$301,A25) -> 0 | R25: =R24+Q25 -> 116238.25 | S25: =L25+R25 -> 116238.25 | T25: =IF(Calc_Payout!R253=1,"LAPSED",IF(N25>0,"SAR active","OK")) -> LAPSED
A26: 22 | B26: =Inputs!$C$4+A26 -> 96 | C26: =INDEX('Return Path'!$D$5:$D$29,A26) -> 0.08 | D26: =Calc_Reinvest!I265 -> 120000 | E26: =Inputs!$C$8*D26 -> 121200 | F26: =Calc_Reinvest!Q265 -> 459818.78 | G26: =IF(Calc_Reinvest!R265=1,0,IF(A26=1,F26-SUMIFS(Calc_Reinvest!$H$2:$H$301,Calc_Reinvest!$B$2:$B$301,1),MAX(E26,F26))) -> 459818.78 | H26: =IF(OR(A26=1,Calc_Reinvest!R265=1),0,MAX(E26-F26,0)) -> 0 | I26: =SUMIFS(Calc_Reinvest!$M$2:$M$301,Calc_Reinvest!$B$2:$B$301,A26) -> 0 | J26: =SUMIFS(Calc_Reinvest!$M$2:$M$301,Calc_Reinvest!$B$2:$B$301,A26)+SUMIFS(Calc_Reinvest!$K$2:$K$301,Calc_Reinvest!$B$2:$B$301,A26) -> 2659.2242 | K26: =F26*(1-INDEX(Rates!$F$4:$F$28,A26)) -> 459818.78 | L26: =Calc_Payout!Q265 -> 0 | M26: =IF(Calc_Payout!R265=1,0,IF(A26=1,L26-SUMIFS(Calc_Payout!$H$2:$H$301,Calc_Payout!$B$2:$B$301,1),MAX(E26,L26))) -> 0 | N26: =IF(OR(A26=1,Calc_Payout!R265=1),0,MAX(E26-L26,0)) -> 0 | O26: =SUMIFS(Calc_Payout!$M$2:$M$301,Calc_Payout!$B$2:$B$301,A26) -> 0 | P26: =SUMIFS(Calc_Payout!$M$2:$M$301,Calc_Payout!$B$2:$B$301,A26)+SUMIFS(Calc_Payout!$K$2:$K$301,Calc_Payout!$B$2:$B$301,A26) -> 0 | Q26: =SUMIFS(Calc_Payout!$N$2:$N$301,Calc_Payout!$B$2:$B$301,A26) -> 0 | R26: =R25+Q26 -> 116238.25 | S26: =L26+R26 -> 116238.25 | T26: =IF(Calc_Payout!R265=1,"LAPSED",IF(N26>0,"SAR active","OK")) -> LAPSED
A27: 23 | B27: =Inputs!$C$4+A27 -> 97 | C27: =INDEX('Return Path'!$D$5:$D$29,A27) -> 0.08 | D27: =Calc_Reinvest!I277 -> 120000 | E27: =Inputs!$C$8*D27 -> 121200 | F27: =Calc_Reinvest!Q277 -> 496101 | G27: =IF(Calc_Reinvest!R277=1,0,IF(A27=1,F27-SUMIFS(Calc_Reinvest!$H$2:$H$301,Calc_Reinvest!$B$2:$B$301,1),MAX(E27,F27))) -> 496101 | H27: =IF(OR(A27=1,Calc_Reinvest!R277=1),0,MAX(E27-F27,0)) -> 0 | I27: =SUMIFS(Calc_Reinvest!$M$2:$M$301,Calc_Reinvest!$B$2:$B$301,A27) -> 0 | J27: =SUMIFS(Calc_Reinvest!$M$2:$M$301,Calc_Reinvest!$B$2:$B$301,A27)+SUMIFS(Calc_Reinvest!$K$2:$K$301,Calc_Reinvest!$B$2:$B$301,A27) -> 2869.0516 | K27: =F27*(1-INDEX(Rates!$F$4:$F$28,A27)) -> 496101 | L27: =Calc_Payout!Q277 -> 0 | M27: =IF(Calc_Payout!R277=1,0,IF(A27=1,L27-SUMIFS(Calc_Payout!$H$2:$H$301,Calc_Payout!$B$2:$B$301,1),MAX(E27,L27))) -> 0 | N27: =IF(OR(A27=1,Calc_Payout!R277=1),0,MAX(E27-L27,0)) -> 0 | O27: =SUMIFS(Calc_Payout!$M$2:$M$301,Calc_Payout!$B$2:$B$301,A27) -> 0 | P27: =SUMIFS(Calc_Payout!$M$2:$M$301,Calc_Payout!$B$2:$B$301,A27)+SUMIFS(Calc_Payout!$K$2:$K$301,Calc_Payout!$B$2:$B$301,A27) -> 0 | Q27: =SUMIFS(Calc_Payout!$N$2:$N$301,Calc_Payout!$B$2:$B$301,A27) -> 0 | R27: =R26+Q27 -> 116238.25 | S27: =L27+R27 -> 116238.25 | T27: =IF(Calc_Payout!R277=1,"LAPSED",IF(N27>0,"SAR active","OK")) -> LAPSED
A28: 24 | B28: =Inputs!$C$4+A28 -> 98 | C28: =INDEX('Return Path'!$D$5:$D$29,A28) -> 0.08 | D28: =Calc_Reinvest!I289 -> 120000 | E28: =Inputs!$C$8*D28 -> 121200 | F28: =Calc_Reinvest!Q289 -> 535246.09 | G28: =IF(Calc_Reinvest!R289=1,0,IF(A28=1,F28-SUMIFS(Calc_Reinvest!$H$2:$H$301,Calc_Reinvest!$B$2:$B$301,1),MAX(E28,F28))) -> 535246.09 | H28: =IF(OR(A28=1,Calc_Reinvest!R289=1),0,MAX(E28-F28,0)) -> 0 | I28: =SUMIFS(Calc_Reinvest!$M$2:$M$301,Calc_Reinvest!$B$2:$B$301,A28) -> 0 | J28: =SUMIFS(Calc_Reinvest!$M$2:$M$301,Calc_Reinvest!$B$2:$B$301,A28)+SUMIFS(Calc_Reinvest!$K$2:$K$301,Calc_Reinvest!$B$2:$B$301,A28) -> 3095.4355 | K28: =F28*(1-INDEX(Rates!$F$4:$F$28,A28)) -> 535246.09 | L28: =Calc_Payout!Q289 -> 0 | M28: =IF(Calc_Payout!R289=1,0,IF(A28=1,L28-SUMIFS(Calc_Payout!$H$2:$H$301,Calc_Payout!$B$2:$B$301,1),MAX(E28,L28))) -> 0 | N28: =IF(OR(A28=1,Calc_Payout!R289=1),0,MAX(E28-L28,0)) -> 0 | O28: =SUMIFS(Calc_Payout!$M$2:$M$301,Calc_Payout!$B$2:$B$301,A28) -> 0 | P28: =SUMIFS(Calc_Payout!$M$2:$M$301,Calc_Payout!$B$2:$B$301,A28)+SUMIFS(Calc_Payout!$K$2:$K$301,Calc_Payout!$B$2:$B$301,A28) -> 0 | Q28: =SUMIFS(Calc_Payout!$N$2:$N$301,Calc_Payout!$B$2:$B$301,A28) -> 0 | R28: =R27+Q28 -> 116238.25 | S28: =L28+R28 -> 116238.25 | T28: =IF(Calc_Payout!R289=1,"LAPSED",IF(N28>0,"SAR active","OK")) -> LAPSED
A29: 25 | B29: =Inputs!$C$4+A29 -> 99 | C29: =INDEX('Return Path'!$D$5:$D$29,A29) -> 0.08 | D29: =Calc_Reinvest!I301 -> 120000 | E29: =Inputs!$C$8*D29 -> 121200 | F29: =Calc_Reinvest!Q301 -> 577479.93 | G29: =IF(Calc_Reinvest!R301=1,0,IF(A29=1,F29-SUMIFS(Calc_Reinvest!$H$2:$H$301,Calc_Reinvest!$B$2:$B$301,1),MAX(E29,F29))) -> 577479.93 | H29: =IF(OR(A29=1,Calc_Reinvest!R301=1),0,MAX(E29-F29,0)) -> 0 | I29: =SUMIFS(Calc_Reinvest!$M$2:$M$301,Calc_Reinvest!$B$2:$B$301,A29) -> 0 | J29: =SUMIFS(Calc_Reinvest!$M$2:$M$301,Calc_Reinvest!$B$2:$B$301,A29)+SUMIFS(Calc_Reinvest!$K$2:$K$301,Calc_Reinvest!$B$2:$B$301,A29) -> 3339.6823 | K29: =F29*(1-INDEX(Rates!$F$4:$F$28,A29)) -> 577479.93 | L29: =Calc_Payout!Q301 -> 0 | M29: =IF(Calc_Payout!R301=1,0,IF(A29=1,L29-SUMIFS(Calc_Payout!$H$2:$H$301,Calc_Payout!$B$2:$B$301,1),MAX(E29,L29))) -> 0 | N29: =IF(OR(A29=1,Calc_Payout!R301=1),0,MAX(E29-L29,0)) -> 0 | O29: =SUMIFS(Calc_Payout!$M$2:$M$301,Calc_Payout!$B$2:$B$301,A29) -> 0 | P29: =SUMIFS(Calc_Payout!$M$2:$M$301,Calc_Payout!$B$2:$B$301,A29)+SUMIFS(Calc_Payout!$K$2:$K$301,Calc_Payout!$B$2:$B$301,A29) -> 0 | Q29: =SUMIFS(Calc_Payout!$N$2:$N$301,Calc_Payout!$B$2:$B$301,A29) -> 0 | R29: =R28+Q29 -> 116238.25 | S29: =L29+R29 -> 116238.25 | T29: =IF(Calc_Payout!R301=1,"LAPSED",IF(N29>0,"SAR active","OK")) -> LAPSED
A31: Totals | I31: =SUM(I5:I29) -> 0 | J31: =SUM(J5:J29) -> 61483.031 | O31: =SUM(O5:O29) -> 96105.262 | P31: =SUM(P5:P29) -> 121181.56 | Q31: =SUM(Q5:Q29) -> 116238.25

Sheet Sensitivity
A1: Sensitivity – constant net return every year (rates set on Inputs C25:C32)
A3: Net return | B3: Scenario | C3: SAR first charged (age) | D3: Lapse age | E3: Total COI to 99 ($) | F3: Dividends received ($) | G3: PV age 80 ($) | H3: PV age 85 ($) | I3: PV age 90 ($) | J3: PV age 95 ($) | K3: PV age 99 ($)
A4: =Inputs!$C$25 -> 0.02 | B4: Reinvested | C4: =IFERROR(Inputs!$C$4+INDEX(S1_R!$B$2:$B$301,MATCH(1,S1_R!$S$2:$S$301,0))-1,"Never") -> 77 | D4: =IFERROR(Inputs!$C$4+INDEX(S1_R!$B$2:$B$301,MATCH(1,S1_R!$R$2:$R$301,0))-1,"No lapse to 99") -> No lapse to 99 | E4: =SUM(S1_R!M2:M301) -> 2387.5537 | F4: =SUM(S1_R!N2:N301) -> 0 | G4: =IF(80-Inputs!$C$4<1,"n/a",INDEX(S1_R!$Q$2:$Q$301,(80-Inputs!$C$4)*12)) -> 118212.55 | H4: =IF(85-Inputs!$C$4<1,"n/a",INDEX(S1_R!$Q$2:$Q$301,(85-Inputs!$C$4)*12)) -> 116876.99 | I4: =IF(90-Inputs!$C$4<1,"n/a",INDEX(S1_R!$Q$2:$Q$301,(90-Inputs!$C$4)*12)) -> 127853.8 | J4: =IF(95-Inputs!$C$4<1,"n/a",INDEX(S1_R!$Q$2:$Q$301,(95-Inputs!$C$4)*12)) -> 140447.08 | K4: =IF(99-Inputs!$C$4<1,"n/a",INDEX(S1_R!$Q$2:$Q$301,(99-Inputs!$C$4)*12)) -> 151409.1
A5: =Inputs!$C$25 -> 0.02 | B5: Paid out | C5: =IFERROR(Inputs!$C$4+INDEX(S1_P!$B$2:$B$301,MATCH(1,S1_P!$S$2:$S$301,0))-1,"Never") -> 77 | D5: =IFERROR(Inputs!$C$4+INDEX(S1_P!$B$2:$B$301,MATCH(1,S1_P!$R$2:$R$301,0))-1,"No lapse to 99") -> 88 | E5: =SUM(S1_P!M2:M301) -> 58230.468 | F5: =SUM(S1_P!N2:N301) -> 61827.611 | G5: =IF(80-Inputs!$C$4<1,"n/a",INDEX(S1_P!$Q$2:$Q$301,(80-Inputs!$C$4)*12)) -> 83682.07 | H5: =IF(85-Inputs!$C$4<1,"n/a",INDEX(S1_P!$Q$2:$Q$301,(85-Inputs!$C$4)*12)) -> 38369.977 | I5: =IF(90-Inputs!$C$4<1,"n/a",INDEX(S1_P!$Q$2:$Q$301,(90-Inputs!$C$4)*12)) -> 0 | J5: =IF(95-Inputs!$C$4<1,"n/a",INDEX(S1_P!$Q$2:$Q$301,(95-Inputs!$C$4)*12)) -> 0 | K5: =IF(99-Inputs!$C$4<1,"n/a",INDEX(S1_P!$Q$2:$Q$301,(99-Inputs!$C$4)*12)) -> 0
A6: =Inputs!$C$26 -> 0.03 | B6: Reinvested | C6: =IFERROR(Inputs!$C$4+INDEX(S2_R!$B$2:$B$301,MATCH(1,S2_R!$S$2:$S$301,0))-1,"Never") -> Never | D6: =IFERROR(Inputs!$C$4+INDEX(S2_R!$B$2:$B$301,MATCH(1,S2_R!$R$2:$R$301,0))-1,"No lapse to 99") -> No lapse to 99 | E6: =SUM(S2_R!M2:M301) -> 0 | F6: =SUM(S2_R!N2:N301) -> 0 | G6: =IF(80-Inputs!$C$4<1,"n/a",INDEX(S2_R!$Q$2:$Q$301,(80-Inputs!$C$4)*12)) -> 123184.53 | H6: =IF(85-Inputs!$C$4<1,"n/a",INDEX(S2_R!$Q$2:$Q$301,(85-Inputs!$C$4)*12)) -> 129715.91 | I6: =IF(90-Inputs!$C$4<1,"n/a",INDEX(S2_R!$Q$2:$Q$301,(90-Inputs!$C$4)*12)) -> 149615.84 | J6: =IF(95-Inputs!$C$4<1,"n/a",INDEX(S2_R!$Q$2:$Q$301,(95-Inputs!$C$4)*12)) -> 172568.66 | K6: =IF(99-Inputs!$C$4<1,"n/a",INDEX(S2_R!$Q$2:$Q$301,(99-Inputs!$C$4)*12)) -> 193441.39
A7: =Inputs!$C$26 -> 0.03 | B7: Paid out | C7: =IFERROR(Inputs!$C$4+INDEX(S2_P!$B$2:$B$301,MATCH(1,S2_P!$S$2:$S$301,0))-1,"Never") -> 77 | D7: =IFERROR(Inputs!$C$4+INDEX(S2_P!$B$2:$B$301,MATCH(1,S2_P!$R$2:$R$301,0))-1,"No lapse to 99") -> 88 | E7: =SUM(S2_P!M2:M301) -> 62457.918 | F7: =SUM(S2_P!N2:N301) -> 66712.931 | G7: =IF(80-Inputs!$C$4<1,"n/a",INDEX(S2_P!$Q$2:$Q$301,(80-Inputs!$C$4)*12)) -> 87248.523 | H7: =IF(85-Inputs!$C$4<1,"n/a",INDEX(S2_P!$Q$2:$Q$301,(85-Inputs!$C$4)*12)) -> 44911.91 | I7: =IF(90-Inputs!$C$4<1,"n/a",INDEX(S2_P!$Q$2:$Q$301,(90-Inputs!$C$4)*12)) -> 0 | J7: =IF(95-Inputs!$C$4<1,"n/a",INDEX(S2_P!$Q$2:$Q$301,(95-Inputs!$C$4)*12)) -> 0 | K7: =IF(99-Inputs!$C$4<1,"n/a",INDEX(S2_P!$Q$2:$Q$301,(99-Inputs!$C$4)*12)) -> 0
A8: =Inputs!$C$27 -> 0.04 | B8: Reinvested | C8: =IFERROR(Inputs!$C$4+INDEX(S3_R!$B$2:$B$301,MATCH(1,S3_R!$S$2:$S$301,0))-1,"Never") -> Never | D8: =IFERROR(Inputs!$C$4+INDEX(S3_R!$B$2:$B$301,MATCH(1,S3_R!$R$2:$R$301,0))-1,"No lapse to 99") -> No lapse to 99 | E8: =SUM(S3_R!M2:M301) -> 0 | F8: =SUM(S3_R!N2:N301) -> 0 | G8: =IF(80-Inputs!$C$4<1,"n/a",INDEX(S3_R!$Q$2:$Q$301,(80-Inputs!$C$4)*12)) -> 128081.5 | H8: =IF(85-Inputs!$C$4<1,"n/a",INDEX(S3_R!$Q$2:$Q$301,(85-Inputs!$C$4)*12)) -> 141548.11 | I8: =IF(90-Inputs!$C$4<1,"n/a",INDEX(S3_R!$Q$2:$Q$301,(90-Inputs!$C$4)*12)) -> 171344.03 | J8: =IF(95-Inputs!$C$4<1,"n/a",INDEX(S3_R!$Q$2:$Q$301,(95-Inputs!$C$4)*12)) -> 207412.01 | K8: =IF(99-Inputs!$C$4<1,"n/a",INDEX(S3_R!$Q$2:$Q$301,(99-Inputs!$C$4)*12)) -> 241660.58
A9: =Inputs!$C$27 -> 0.04 | B9: Paid out | C9: =IFERROR(Inputs!$C$4+INDEX(S3_P!$B$2:$B$301,MATCH(1,S3_P!$S$2:$S$301,0))-1,"Never") -> 77 | D9: =IFERROR(Inputs!$C$4+INDEX(S3_P!$B$2:$B$301,MATCH(1,S3_P!$R$2:$R$301,0))-1,"No lapse to 99") -> 89 | E9: =SUM(S3_P!M2:M301) -> 67495.516 | F9: =SUM(S3_P!N2:N301) -> 72505.846 | G9: =IF(80-Inputs!$C$4<1,"n/a",INDEX(S3_P!$Q$2:$Q$301,(80-Inputs!$C$4)*12)) -> 90938.709 | H9: =IF(85-Inputs!$C$4<1,"n/a",INDEX(S3_P!$Q$2:$Q$301,(85-Inputs!$C$4)*12)) -> 52064.365 | I9: =IF(90-Inputs!$C$4<1,"n/a",INDEX(S3_P!$Q$2:$Q$301,(90-Inputs!$C$4)*12)) -> 0 | J9: =IF(95-Inputs!$C$4<1,"n/a",INDEX(S3_P!$Q$2:$Q$301,(95-Inputs!$C$4)*12)) -> 0 | K9: =IF(99-Inputs!$C$4<1,"n/a",INDEX(S3_P!$Q$2:$Q$301,(99-Inputs!$C$4)*12)) -> 0
A10: =Inputs!$C$28 -> 0.05 | B10: Reinvested | C10: =IFERROR(Inputs!$C$4+INDEX(S4_R!$B$2:$B$301,MATCH(1,S4_R!$S$2:$S$301,0))-1,"Never") -> Never | D10: =IFERROR(Inputs!$C$4+INDEX(S4_R!$B$2:$B$301,MATCH(1,S4_R!$R$2:$R$301,0))-1,"No lapse to 99") -> No lapse to 99 | E10: =SUM(S4_R!M2:M301) -> 0 | F10: =SUM(S4_R!N2:N301) -> 0 | G10: =IF(80-Inputs!$C$4<1,"n/a",INDEX(S4_R!$Q$2:$Q$301,(80-Inputs!$C$4)*12)) -> 133148.16 | H10: =IF(85-Inputs!$C$4<1,"n/a",INDEX(S4_R!$Q$2:$Q$301,(85-Inputs!$C$4)*12)) -> 154359.23 | I10: =IF(90-Inputs!$C$4<1,"n/a",INDEX(S4_R!$Q$2:$Q$301,(90-Inputs!$C$4)*12)) -> 196009.59 | J10: =IF(95-Inputs!$C$4<1,"n/a",INDEX(S4_R!$Q$2:$Q$301,(95-Inputs!$C$4)*12)) -> 248898.36 | K10: =IF(99-Inputs!$C$4<1,"n/a",INDEX(S4_R!$Q$2:$Q$301,(99-Inputs!$C$4)*12)) -> 301312.95
A11: =Inputs!$C$28 -> 0.05 | B11: Paid out | C11: =IFERROR(Inputs!$C$4+INDEX(S4_P!$B$2:$B$301,MATCH(1,S4_P!$S$2:$S$301,0))-1,"Never") -> 77 | D11: =IFERROR(Inputs!$C$4+INDEX(S4_P!$B$2:$B$301,MATCH(1,S4_P!$R$2:$R$301,0))-1,"No lapse to 99") -> 90 | E11: =SUM(S4_P!M2:M301) -> 72717.002 | F11: =SUM(S4_P!N2:N301) -> 79534.908 | G11: =IF(80-Inputs!$C$4<1,"n/a",INDEX(S4_P!$Q$2:$Q$301,(80-Inputs!$C$4)*12)) -> 94756.218 | H11: =IF(85-Inputs!$C$4<1,"n/a",INDEX(S4_P!$Q$2:$Q$301,(85-Inputs!$C$4)*12)) -> 59874.556 | I11: =IF(90-Inputs!$C$4<1,"n/a",INDEX(S4_P!$Q$2:$Q$301,(90-Inputs!$C$4)*12)) -> 3183.3799 | J11: =IF(95-Inputs!$C$4<1,"n/a",INDEX(S4_P!$Q$2:$Q$301,(95-Inputs!$C$4)*12)) -> 0 | K11: =IF(99-Inputs!$C$4<1,"n/a",INDEX(S4_P!$Q$2:$Q$301,(99-Inputs!$C$4)*12)) -> 0
A12: =Inputs!$C$29 -> 0.06 | B12: Reinvested | C12: =IFERROR(Inputs!$C$4+INDEX(S5_R!$B$2:$B$301,MATCH(1,S5_R!$S$2:$S$301,0))-1,"Never") -> Never | D12: =IFERROR(Inputs!$C$4+INDEX(S5_R!$B$2:$B$301,MATCH(1,S5_R!$R$2:$R$301,0))-1,"No lapse to 99") -> No lapse to 99 | E12: =SUM(S5_R!M2:M301) -> 0 | F12: =SUM(S5_R!N2:N301) -> 0 | G12: =IF(80-Inputs!$C$4<1,"n/a",INDEX(S5_R!$Q$2:$Q$301,(80-Inputs!$C$4)*12)) -> 138389.5 | H12: =IF(85-Inputs!$C$4<1,"n/a",INDEX(S5_R!$Q$2:$Q$301,(85-Inputs!$C$4)*12)) -> 168222.24 | I12: =IF(90-Inputs!$C$4<1,"n/a",INDEX(S5_R!$Q$2:$Q$301,(90-Inputs!$C$4)*12)) -> 223980.88 | J12: =IF(95-Inputs!$C$4<1,"n/a",INDEX(S5_R!$Q$2:$Q$301,(95-Inputs!$C$4)*12)) -> 298221.19 | K12: =IF(99-Inputs!$C$4<1,"n/a",INDEX(S5_R!$Q$2:$Q$301,(99-Inputs!$C$4)*12)) -> 374973.46
A13: =Inputs!$C$29 -> 0.06 | B13: Paid out | C13: =IFERROR(Inputs!$C$4+INDEX(S5_P!$B$2:$B$301,MATCH(1,S5_P!$S$2:$S$301,0))-1,"Never") -> 77 | D13: =IFERROR(Inputs!$C$4+INDEX(S5_P!$B$2:$B$301,MATCH(1,S5_P!$R$2:$R$301,0))-1,"No lapse to 99") -> 91 | E13: =SUM(S5_P!M2:M301) -> 77478.13 | F13: =SUM(S5_P!N2:N301) -> 88342.321 | G13: =IF(80-Inputs!$C$4<1,"n/a",INDEX(S5_P!$Q$2:$Q$301,(80-Inputs!$C$4)*12)) -> 98704.723 | H13: =IF(85-Inputs!$C$4<1,"n/a",INDEX(S5_P!$Q$2:$Q$301,(85-Inputs!$C$4)*12)) -> 68392.873 | I13: =IF(90-Inputs!$C$4<1,"n/a",INDEX(S5_P!$Q$2:$Q$301,(90-Inputs!$C$4)*12)) -> 19136.644 | J13: =IF(95-Inputs!$C$4<1,"n/a",INDEX(S5_P!$Q$2:$Q$301,(95-Inputs!$C$4)*12)) -> 0 | K13: =IF(99-Inputs!$C$4<1,"n/a",INDEX(S5_P!$Q$2:$Q$301,(99-Inputs!$C$4)*12)) -> 0
A14: =Inputs!$C$30 -> 0.07 | B14: Reinvested | C14: =IFERROR(Inputs!$C$4+INDEX(S6_R!$B$2:$B$301,MATCH(1,S6_R!$S$2:$S$301,0))-1,"Never") -> Never | D14: =IFERROR(Inputs!$C$4+INDEX(S6_R!$B$2:$B$301,MATCH(1,S6_R!$R$2:$R$301,0))-1,"No lapse to 99") -> No lapse to 99 | E14: =SUM(S6_R!M2:M301) -> 0 | F14: =SUM(S6_R!N2:N301) -> 0 | G14: =IF(80-Inputs!$C$4<1,"n/a",INDEX(S6_R!$Q$2:$Q$301,(80-Inputs!$C$4)*12)) -> 143810.65 | H14: =IF(85-Inputs!$C$4<1,"n/a",INDEX(S6_R!$Q$2:$Q$301,(85-Inputs!$C$4)*12)) -> 183214.94 | I14: =IF(90-Inputs!$C$4<1,"n/a",INDEX(S6_R!$Q$2:$Q$301,(90-Inputs!$C$4)*12)) -> 255668.95 | J14: =IF(95-Inputs!$C$4<1,"n/a",INDEX(S6_R!$Q$2:$Q$301,(95-Inputs!$C$4)*12)) -> 356775.56 | K14: =IF(99-Inputs!$C$4<1,"n/a",INDEX(S6_R!$Q$2:$Q$301,(99-Inputs!$C$4)*12)) -> 465767.07
A15: =Inputs!$C$30 -> 0.07 | B15: Paid out | C15: =IFERROR(Inputs!$C$4+INDEX(S6_P!$B$2:$B$301,MATCH(1,S6_P!$S$2:$S$301,0))-1,"Never") -> 77 | D15: =IFERROR(Inputs!$C$4+INDEX(S6_P!$B$2:$B$301,MATCH(1,S6_P!$R$2:$R$301,0))-1,"No lapse to 99") -> 92 | E15: =SUM(S6_P!M2:M301) -> 86284.398 | F15: =SUM(S6_P!N2:N301) -> 99896.88 | G15: =IF(80-Inputs!$C$4<1,"n/a",INDEX(S6_P!$Q$2:$Q$301,(80-Inputs!$C$4)*12)) -> 102787.98 | H15: =IF(85-Inputs!$C$4<1,"n/a",INDEX(S6_P!$Q$2:$Q$301,(85-Inputs!$C$4)*12)) -> 77673.068 | I15: =IF(90-Inputs!$C$4<1,"n/a",INDEX(S6_P!$Q$2:$Q$301,(90-Inputs!$C$4)*12)) -> 37791.795 | J15: =IF(95-Inputs!$C$4<1,"n/a",INDEX(S6_P!$Q$2:$Q$301,(95-Inputs!$C$4)*12)) -> 0 | K15: =IF(99-Inputs!$C$4<1,"n/a",INDEX(S6_P!$Q$2:$Q$301,(99-Inputs!$C$4)*12)) -> 0
A16: =Inputs!$C$31 -> 0.08 | B16: Reinvested | C16: =IFERROR(Inputs!$C$4+INDEX(S7_R!$B$2:$B$301,MATCH(1,S7_R!$S$2:$S$301,0))-1,"Never") -> Never | D16: =IFERROR(Inputs!$C$4+INDEX(S7_R!$B$2:$B$301,MATCH(1,S7_R!$R$2:$R$301,0))-1,"No lapse to 99") -> No lapse to 99 | E16: =SUM(S7_R!M2:M301) -> 0 | F16: =SUM(S7_R!N2:N301) -> 0 | G16: =IF(80-Inputs!$C$4<1,"n/a",INDEX(S7_R!$Q$2:$Q$301,(80-Inputs!$C$4)*12)) -> 149416.85 | H16: =IF(85-Inputs!$C$4<1,"n/a",INDEX(S7_R!$Q$2:$Q$301,(85-Inputs!$C$4)*12)) -> 199420.28 | I16: =IF(90-Inputs!$C$4<1,"n/a",INDEX(S7_R!$Q$2:$Q$301,(90-Inputs!$C$4)*12)) -> 291532.05 | J16: =IF(95-Inputs!$C$4<1,"n/a",INDEX(S7_R!$Q$2:$Q$301,(95-Inputs!$C$4)*12)) -> 426190.05 | K16: =IF(99-Inputs!$C$4<1,"n/a",INDEX(S7_R!$Q$2:$Q$301,(99-Inputs!$C$4)*12)) -> 577479.93
A17: =Inputs!$C$31 -> 0.08 | B17: Paid out | C17: =IFERROR(Inputs!$C$4+INDEX(S7_P!$B$2:$B$301,MATCH(1,S7_P!$S$2:$S$301,0))-1,"Never") -> 77 | D17: =IFERROR(Inputs!$C$4+INDEX(S7_P!$B$2:$B$301,MATCH(1,S7_P!$R$2:$R$301,0))-1,"No lapse to 99") -> 93 | E17: =SUM(S7_P!M2:M301) -> 96105.262 | F17: =SUM(S7_P!N2:N301) -> 116238.25 | G17: =IF(80-Inputs!$C$4<1,"n/a",INDEX(S7_P!$Q$2:$Q$301,(80-Inputs!$C$4)*12)) -> 107009.84 | H17: =IF(85-Inputs!$C$4<1,"n/a",INDEX(S7_P!$Q$2:$Q$301,(85-Inputs!$C$4)*12)) -> 87772.454 | I17: =IF(90-Inputs!$C$4<1,"n/a",INDEX(S7_P!$Q$2:$Q$301,(90-Inputs!$C$4)*12)) -> 59509.27 | J17: =IF(95-Inputs!$C$4<1,"n/a",INDEX(S7_P!$Q$2:$Q$301,(95-Inputs!$C$4)*12)) -> 0 | K17: =IF(99-Inputs!$C$4<1,"n/a",INDEX(S7_P!$Q$2:$Q$301,(99-Inputs!$C$4)*12)) -> 0
A18: =Inputs!$C$32 -> 0.1 | B18: Reinvested | C18: =IFERROR(Inputs!$C$4+INDEX(S8_R!$B$2:$B$301,MATCH(1,S8_R!$S$2:$S$301,0))-1,"Never") -> Never | D18: =IFERROR(Inputs!$C$4+INDEX(S8_R!$B$2:$B$301,MATCH(1,S8_R!$R$2:$R$301,0))-1,"No lapse to 99") -> No lapse to 99 | E18: =SUM(S8_R!M2:M301) -> 0 | F18: =SUM(S8_R!N2:N301) -> 0 | G18: =IF(80-Inputs!$C$4<1,"n/a",INDEX(S8_R!$Q$2:$Q$301,(80-Inputs!$C$4)*12)) -> 161206.01 | H18: =IF(85-Inputs!$C$4<1,"n/a",INDEX(S8_R!$Q$2:$Q$301,(85-Inputs!$C$4)*12)) -> 235828.13 | I18: =IF(90-Inputs!$C$4<1,"n/a",INDEX(S8_R!$Q$2:$Q$301,(90-Inputs!$C$4)*12)) -> 377882.91 | J18: =IF(95-Inputs!$C$4<1,"n/a",INDEX(S8_R!$Q$2:$Q$301,(95-Inputs!$C$4)*12)) -> 605506.61 | K18: =IF(99-Inputs!$C$4<1,"n/a",INDEX(S8_R!$Q$2:$Q$301,(99-Inputs!$C$4)*12)) -> 882933.93
A19: =Inputs!$C$32 -> 0.1 | B19: Paid out | C19: =IFERROR(Inputs!$C$4+INDEX(S8_P!$B$2:$B$301,MATCH(1,S8_P!$S$2:$S$301,0))-1,"Never") -> 77 | D19: =IFERROR(Inputs!$C$4+INDEX(S8_P!$B$2:$B$301,MATCH(1,S8_P!$R$2:$R$301,0))-1,"No lapse to 99") -> No lapse to 99 | E19: =SUM(S8_P!M2:M301) -> 15255.142 | F19: =SUM(S8_P!N2:N301) -> 212935.47 | G19: =IF(80-Inputs!$C$4<1,"n/a",INDEX(S8_P!$Q$2:$Q$301,(80-Inputs!$C$4)*12)) -> 115885.14 | H19: =IF(85-Inputs!$C$4<1,"n/a",INDEX(S8_P!$Q$2:$Q$301,(85-Inputs!$C$4)*12)) -> 110677.09 | I19: =IF(90-Inputs!$C$4<1,"n/a",INDEX(S8_P!$Q$2:$Q$301,(90-Inputs!$C$4)*12)) -> 113789.43 | J19: =IF(95-Inputs!$C$4<1,"n/a",INDEX(S8_P!$Q$2:$Q$301,(95-Inputs!$C$4)*12)) -> 116777.15 | K19: =IF(99-Inputs!$C$4<1,"n/a",INDEX(S8_P!$Q$2:$Q$301,(99-Inputs!$C$4)*12)) -> 121246.54

Sheet BI Check
A1: Calibration – model vs Benefit Illustration supplementary illustration (premiums stop after MIP), dividends reinvested
A2: BI figures typed from BI pp.7–8 (Non-guaranteed policy value). Valid only while Inputs match the BI (age 74 F, $24,000 × 5 yrs, current charges).
A4: Policy year | B4: Age | C4: BI @4% ($) | D4: Model @4% ($) | E4: Diff % | F4: BI @8% ($) | G4: Model @8% ($) | H4: Diff %
A5: 1 | B5: =Inputs!$C$4+A5 -> 75 | C5: 24942 | D5: =Calc_BI4!Q13 -> 24938.89 | E5: =D5/C5-1 -> -0.00012468026 | F5: 25902 | G5: =Calc_BI8!Q13 -> 25898.078 | H5: =G5/F5-1 -> -0.00015140489
A6: 2 | B6: =Inputs!$C$4+A6 -> 76 | C6: 48907 | D6: =Calc_BI4!Q25 -> 48897.5 | E6: =D6/C6-1 -> -0.00019423716 | F6: 51784 | G6: =Calc_BI8!Q25 -> 51773.411 | H6: =G6/F6-1 -> -0.00020448318
A7: 3 | B7: =Inputs!$C$4+A7 -> 77 | C7: 72855 | D7: =Calc_BI4!Q37 -> 72835.848 | E7: =D7/C7-1 -> -0.00026288099 | F7: 78643 | G7: =Calc_BI8!Q37 -> 78621.223 | H7: =G7/F7-1 -> -0.00027690602
A8: 4 | B8: =Inputs!$C$4+A8 -> 78 | C8: 96781 | D8: =Calc_BI4!Q49 -> 96747.567 | E8: =D8/C8-1 -> -0.00034545065 | F8: 106515 | G8: =Calc_BI8!Q49 -> 106478.06 | H8: =G8/F8-1 -> -0.00034676829
A9: 5 | B9: =Inputs!$C$4+A9 -> 79 | C9: 120676 | D9: =Calc_BI4!Q61 -> 120623.84 | E9: =D9/C9-1 -> -0.00043224636 | F9: 135438 | G9: =Calc_BI8!Q61 -> 135381.86 | H9: =G9/F9-1 -> -0.00041453864
A10: 6 | B10: =Inputs!$C$4+A10 -> 80 | C10: 120563 | D10: =Calc_BI4!Q73 -> 120492 | E10: =D10/C10-1 -> -0.00058889793 | F10: 140547 | G10: =Calc_BI8!Q73 -> 140469.95 | H10: =G10/F10-1 -> -0.00054822968
A11: 7 | B11: =Inputs!$C$4+A11 -> 81 | C11: 120442 | D11: =Calc_BI4!Q85 -> 120350.49 | E11: =D11/C11-1 -> -0.0007598165 | F11: 145848 | G11: =Calc_BI8!Q85 -> 145749.27 | H11: =G11/F11-1 -> -0.00067695592
A12: 8 | B12: =Inputs!$C$4+A12 -> 82 | C12: 120308 | D12: =Calc_BI4!Q97 -> 120194.37 | E12: =D12/C12-1 -> -0.00094451582 | F12: 151350 | G12: =Calc_BI8!Q97 -> 151227 | H12: =G12/F12-1 -> -0.00081268077
A13: 9 | B13: =Inputs!$C$4+A13 -> 83 | C13: 120159 | D13: =Calc_BI4!Q109 -> 120020.29 | E13: =D13/C13-1 -> -0.0011543928 | F13: 157059 | G13: =Calc_BI8!Q109 -> 156910.61 | H13: =G13/F13-1 -> -0.00094483406
A14: 10 | B14: =Inputs!$C$4+A14 -> 84 | C14: 120590 | D14: =Calc_BI4!Q121 -> 120423.38 | E14: =D14/C14-1 -> -0.001381726 | F14: 163799 | G14: =Calc_BI8!Q121 -> 163621.86 | H14: =G14/F14-1 -> -0.0010814635
A15: 11 | B15: =Inputs!$C$4+A15 -> 85 | C15: 123424 | D15: =Calc_BI4!Q133 -> 123239.6 | E15: =D15/C15-1 -> -0.001494067 | F15: 174109 | G15: =Calc_BI8!Q133 -> 173901.35 | H15: =G15/F15-1 -> -0.0011926242
A16: 12 | B16: =Inputs!$C$4+A16 -> 86 | C16: 126333 | D16: =Calc_BI4!Q145 -> 126130.9 | E16: =D16/C16-1 -> -0.0015997409 | F16: 185067 | G16: =Calc_BI8!Q145 -> 184826.66 | H16: =G16/F16-1 -> -0.0012986876
A17: 13 | B17: =Inputs!$C$4+A17 -> 87 | C17: 129311 | D17: =Calc_BI4!Q157 -> 129090.04 | E17: =D17/C17-1 -> -0.0017087798 | F17: 196716 | G17: =Calc_BI8!Q157 -> 196438.34 | H17: =G17/F17-1 -> -0.0014114909
A18: 14 | B18: =Inputs!$C$4+A18 -> 88 | C18: 132360 | D18: =Calc_BI4!Q169 -> 132118.6 | E18: =D18/C18-1 -> -0.0018238454 | F18: 209097 | G18: =Calc_BI8!Q169 -> 208779.52 | H18: =G18/F18-1 -> -0.0015183429
A19: 15 | B19: =Inputs!$C$4+A19 -> 89 | C19: 135480 | D19: =Calc_BI4!Q181 -> 135218.21 | E19: =D19/C19-1 -> -0.001932328 | F19: 222258 | G19: =Calc_BI8!Q181 -> 221896.03 | H19: =G19/F19-1 -> -0.001628593
A20: 16 | B20: =Inputs!$C$4+A20 -> 90 | C20: 138673 | D20: =Calc_BI4!Q193 -> 138390.54 | E20: =D20/C20-1 -> -0.0020368776 | F20: 236247 | G20: =Calc_BI8!Q193 -> 235836.59 | H20: =G20/F20-1 -> -0.0017372224
A21: 17 | B21: =Inputs!$C$4+A21 -> 91 | C21: 141942 | D21: =Calc_BI4!Q205 -> 141637.3 | E21: =D21/C21-1 -> -0.0021466691 | F21: 251117 | G21: =Calc_BI8!Q205 -> 250652.95 | H21: =G21/F21-1 -> -0.0018479355
A22: 18 | B22: =Inputs!$C$4+A22 -> 92 | C22: 145288 | D22: =Calc_BI4!Q217 -> 144960.23 | E22: =D22/C22-1 -> -0.0022560256 | F22: 266923 | G22: =Calc_BI8!Q217 -> 266400.15 | H22: =G22/F22-1 -> -0.0019587992
A23: 19 | B23: =Inputs!$C$4+A23 -> 93 | C23: 148713 | D23: =Calc_BI4!Q229 -> 148361.11 | E23: =D23/C23-1 -> -0.0023662067 | F23: 283723 | G23: =Calc_BI8!Q229 -> 283136.66 | H23: =G23/F23-1 -> -0.0020665784
A24: 20 | B24: =Inputs!$C$4+A24 -> 94 | C24: 152219 | D24: =Calc_BI4!Q241 -> 151841.79 | E24: =D24/C24-1 -> -0.0024780763 | F24: 301581 | G24: =Calc_BI8!Q241 -> 300924.64 | H24: =G24/F24-1 -> -0.0021763855
A25: 21 | B25: =Inputs!$C$4+A25 -> 95 | C25: 155807 | D25: =Calc_BI4!Q253 -> 155404.12 | E25: =D25/C25-1 -> -0.0025857333 | F25: 320563 | G25: =Calc_BI8!Q253 -> 319830.15 | H25: =G25/F25-1 -> -0.002286142
A26: 22 | B26: =Inputs!$C$4+A26 -> 96 | C26: 159480 | D26: =Calc_BI4!Q265 -> 159050.03 | E26: =D26/C26-1 -> -0.0026960437 | F26: 340740 | G26: =Calc_BI8!Q265 -> 339923.38 | H26: =G26/F26-1 -> -0.0023965948
A27: 23 | B27: =Inputs!$C$4+A27 -> 97 | C27: 163240 | D27: =Calc_BI4!Q277 -> 162781.48 | E27: =D27/C27-1 -> -0.0028088621 | F27: 362186 | G27: =Calc_BI8!Q277 -> 361278.97 | H27: =G27/F27-1 -> -0.0025043129
A28: 24 | B28: =Inputs!$C$4+A28 -> 98 | C28: 167088 | D28: =Calc_BI4!Q289 -> 166600.47 | E28: =D28/C28-1 -> -0.0029178003 | F28: 384983 | G28: =Calc_BI8!Q289 -> 383976.22 | H28: =G28/F28-1 -> -0.0026151278
A29: 25 | B29: =Inputs!$C$4+A29 -> 99 | C29: 171026 | D29: =Calc_BI4!Q301 -> 170509.06 | E29: =D29/C29-1 -> -0.0030226019 | F29: 409214 | G29: =Calc_BI8!Q301 -> 408099.42 | H29: =G29/F29-1 -> -0.0027237201
A31: Max absolute difference | E31: =MAX(MAX(E5:E29),-MIN(E5:E29)) -> 0.0030226019 | H31: =MAX(MAX(H5:H29),-MIN(H5:H29)) -> 0.0027237201

Sheet Rates
A1: Age (last b'day) | B1: Male ($ per $1,000 SAR p.a.) | C1: Female ($ per $1,000 SAR p.a.) | E1: Source: BI Product Summary Appendix 1 – yearly insurance cover charge rates for death & TI per $1,000 sum at risk. Age > 99 uses the age-99 rate. Rates are not guaranteed.
A2: 0 | B2: 0.46 | C2: 0.48
A3: 1 | B3: 0.42 | C3: 0.45 | E3: Policy year | F3: Surrender charge (5-yr MIP)
A4: 2 | B4: 0.38 | C4: 0.42 | E4: 1 | F4: 1
A5: 3 | B5: 0.34 | C5: 0.39 | E5: 2 | F5: 1
A6: 4 | B6: 0.3 | C6: 0.36 | E6: 3 | F6: 0.75
A7: 5 | B7: 0.27 | C7: 0.33 | E7: 4 | F7: 0.4
A8: 6 | B8: 0.27 | C8: 0.32 | E8: 5 | F8: 0.2
A9: 7 | B9: 0.27 | C9: 0.31 | E9: 6 | F9: 0
A10: 8 | B10: 0.27 | C10: 0.3 | E10: 7 | F10: 0
A11: 9 | B11: 0.27 | C11: 0.29 | E11: 8 | F11: 0
A12: 10 | B12: 0.27 | C12: 0.3 | E12: 9 | F12: 0
A13: 11 | B13: 0.31 | C13: 0.32 | E13: 10 | F13: 0
A14: 12 | B14: 0.35 | C14: 0.34 | E14: 11 | F14: 0
A15: 13 | B15: 0.39 | C15: 0.36 | E15: 12 | F15: 0
... A28: 26 | B28: 0.48 | C28: 0.3 | E28: 25 | F28: 0
A29: 27 | B29: 0.47 | C29: 0.29
A30: 28 | B30: 0.46 | C30: 0.28
A31: 29 | B31: 0.45 | C31: 0.27 | E31: Source: Appendix 2 (applies during MIP only).
A32: 30 | B32: 0.46 | C32: 0.27
A33: 31 | B33: 0.48 | C33: 0.29
A34: 32 | B34: 0.5 | C34: 0.31
A35: 33 | B35: 0.52 | C35: 0.33
A36: 34 | B36: 0.54 | C36: 0.35
A37: 35 | B37: 0.58 | C37: 0.37
A38: 36 | B38: 0.62 | C38: 0.43
A39: 37 | B39: 0.66 | C39: 0.49
A40: 38 | B40: 0.7 | C40: 0.55
A41: 39 | B41: 0.74 | C41: 0.61
A42: 40 | B42: 0.79 | C42: 0.65
A43: 41 | B43: 0.89 | C43: 0.73
... A101: 99 | B101: 391.65 | C101: 389.64

Sheet Read Me
B1: Invest Flex Vantage (VS2) – Sum at Risk Model
B3: PURPOSE
B4: Shows whether, and from what age, the policy's sum at risk (SAR) triggers insurance charges that erode the cash value – with dividends reinvested (as in the BI) vs taken as cash.
B6: HOW TO USE
B7: 1. Inputs: change blue-on-yellow cells (return, dividend payout rate, premium, years, charges, COI stress multiplier).
B8: 2. Return Path: optionally override the return for specific years (e.g. -15% in a crash year).
B9: 3. Dashboard: key answers + charts. Projection: year-by-year detail. Sensitivity: side-by-side constant returns. BI Check: proof the model reproduces the insurer's numbers.
B11: POLICY MECHANICS MODELLED (from BI Product Summary v1.24)
B12: • Premiums buy units at 100% allocation (yrs 1-10); 4% investment bonus on 1st-year premium.
B13: • Death benefit after year 1 = higher of 101% of net premiums or policy value. Net premiums = premiums + top-ups − withdrawals.
B14: • Sum at risk = 101% × net premiums − policy value (if ≤ 0, no charge). Insurance cover charge = SAR × Appendix 1 rate ÷ 1,000, deducted monthly from the 3rd policy anniversary.
B15: • Policy fee 2.5% p.a. of policy value (yrs 1-10), 0.6% p.a. thereafter, deducted monthly. Fund management fee 1.5% p.a. (inside the fund).
... B29: Illustrative only. Fees, insurance charges and fund distributions are not guaranteed and may be revised by Income Insurance. Returns are not guaranteed. This model is not an Income Insurance document and does not replace the official Benefit Illustration.

Sheet Calc_Reinvest
A1: Month | B1: Policy year | C1: Age (last b'day) | D1: Gross return p.a. | E1: Lapsed before? | F1: Policy value b/f | G1: Premium | H1: Investment bonus | I1: Net premiums to date | J1: Investment growth | K1: Policy fee + mgmt fee | L1: Sum at risk (charged) | M1: Insurance charge (COI) | N1: Dividend paid out | O1: Loyalty bonus | P1: PV before floor | Q1: Policy value c/f | R1: Lapsed? | S1: SAR>0 flag | U1: Dividend payout on? (1/0) | V1: 0
A2: 1 | B2: =INT((A2-1)/12)+1 -> 1 | C2: =MIN(Inputs!$C$4+B2-1,99) -> 74 | D2: =INDEX('Return Path'!$D$5:$D$29,B2) -> 0.08 | E2: 0 | F2: 0 | G2: =IF(AND(MOD(A2-1,12)=0,B2<=Inputs!$C$7,E2=0),Inputs!$C$6,0) -> 24000 | H2: =IF(B2=1,G2*Inputs!$C$9,0) -> 960 | I2: =G2 -> 24000 | J2: =(F2+G2+H2)*((1+D2)^(1/12)-1) -> 160.59339 | K2: =(F2+G2+H2+J2)*(Inputs!$C$14+IF(B2<=10,Inputs!$C$12,Inputs!$C$13))/12 -> 52.33457 | L2: =IF(OR(E2=1,A2<=Inputs!$C$15),0,MAX(Inputs!$C$8*I2-(F2+G2+H2+J2-K2),0)) -> 0 | M2: =L2*INDEX(Rates!$B$2:$C$101,C2+1,IF(Inputs!$C$5="Male",1,2))/1000/12*Inputs!$C$16 -> 0 | N2: =IF($V$1=1,MAX(F2+G2+H2+J2-K2-M2,0)*Inputs!$C$22/12,0) -> 0 | O2: =IF(AND(MOD(A2,12)=0,B2>=Inputs!$C$18),MAX(F2+G2+H2+J2-K2-M2-N2,0)*Inputs!$C$17,0) -> 0 | P2: =F2+G2+H2+J2-K2-M2-N2+O2 -> 25068.259 | Q2: =IF(OR(E2=1,P2<=0),0,P2) -> 25068.259 | R2: =IF(OR(E2=1,AND(P2<=0,I2>0)),1,0) -> 0 | S2: =IF(L2>0,1,0) -> 0 | U2: Main – dividends reinvested
A3: 2 | B3: =INT((A3-1)/12)+1 -> 1 | C3: =MIN(Inputs!$C$4+B3-1,99) -> 74 | D3: =INDEX('Return Path'!$D$5:$D$29,B3) -> 0.08 | E3: =R2 -> 0 | F3: =Q2 -> 25068.259 | G3: =IF(AND(MOD(A3-1,12)=0,B3<=Inputs!$C$7,E3=0),Inputs!$C$6,0) -> 0 | H3: =IF(B3=1,G3*Inputs!$C$9,0) -> 0 | I3: =I2+G3 -> 24000 | J3: =(F3+G3+H3)*((1+D3)^(1/12)-1) -> 161.28993 | K3: =(F3+G3+H3+J3)*(Inputs!$C$14+IF(B3<=10,Inputs!$C$12,Inputs!$C$13))/12 -> 52.56156 | L3: =IF(OR(E3=1,A3<=Inputs!$C$15),0,MAX(Inputs!$C$8*I3-(F3+G3+H3+J3-K3),0)) -> 0 | M3: =L3*INDEX(Rates!$B$2:$C$101,C3+1,IF(Inputs!$C$5="Male",1,2))/1000/12*Inputs!$C$16 -> 0 | N3: =IF($V$1=1,MAX(F3+G3+H3+J3-K3-M3,0)*Inputs!$C$22/12,0) -> 0 | O3: =IF(AND(MOD(A3,12)=0,B3>=Inputs!$C$18),MAX(F3+G3+H3+J3-K3-M3-N3,0)*Inputs!$C$17,0) -> 0 | P3: =F3+G3+H3+J3-K3-M3-N3+O3 -> 25176.987 | Q3: =IF(OR(E3=1,P3<=0),0,P3) -> 25176.987 | R3: =IF(OR(E3=1,AND(P3<=0,I3>0)),1,0) -> 0 | S3: =IF(L3>0,1,0) -> 0
A4: 3 | B4: =INT((A4-1)/12)+1 -> 1 | C4: =MIN(Inputs!$C$4+B4-1,99) -> 74 | D4: =INDEX('Return Path'!$D$5:$D$29,B4) -> 0.08 | E4: =R3 -> 0 | F4: =Q3 -> 25176.987 | G4: =IF(AND(MOD(A4-1,12)=0,B4<=Inputs!$C$7,E4=0),Inputs!$C$6,0) -> 0 | H4: =IF(B4=1,G4*Inputs!$C$9,0) -> 0 | I4: =I3+G4 -> 24000 | J4: =(F4+G4+H4)*((1+D4)^(1/12)-1) -> 161.98949 | K4: =(F4+G4+H4+J4)*(Inputs!$C$14+IF(B4<=10,Inputs!$C$12,Inputs!$C$13))/12 -> 52.789535 | L4: =IF(OR(E4=1,A4<=Inputs!$C$15),0,MAX(Inputs!$C$8*I4-(F4+G4+H4+J4-K4),0)) -> 0 | M4: =L4*INDEX(Rates!$B$2:$C$101,C4+1,IF(Inputs!$C$5="Male",1,2))/1000/12*Inputs!$C$16 -> 0 | N4: =IF($V$1=1,MAX(F4+G4+H4+J4-K4-M4,0)*Inputs!$C$22/12,0) -> 0 | O4: =IF(AND(MOD(A4,12)=0,B4>=Inputs!$C$18),MAX(F4+G4+H4+J4-K4-M4-N4,0)*Inputs!$C$17,0) -> 0 | P4: =F4+G4+H4+J4-K4-M4-N4+O4 -> 25286.187 | Q4: =IF(OR(E4=1,P4<=0),0,P4) -> 25286.187 | R4: =IF(OR(E4=1,AND(P4<=0,I4>0)),1,0) -> 0 | S4: =IF(L4>0,1,0) -> 0
A5: 4 | B5: =INT((A5-1)/12)+1 -> 1 | C5: =MIN(Inputs!$C$4+B5-1,99) -> 74 | D5: =INDEX('Return Path'!$D$5:$D$29,B5) -> 0.08 | E5: =R4 -> 0 | F5: =Q4 -> 25286.187 | G5: =IF(AND(MOD(A5-1,12)=0,B5<=Inputs!$C$7,E5=0),Inputs!$C$6,0) -> 0 | H5: =IF(B5=1,G5*Inputs!$C$9,0) -> 0 | I5: =I4+G5 -> 24000 | J5: =(F5+G5+H5)*((1+D5)^(1/12)-1) -> 162.69209 | K5: =(F5+G5+H5+J5)*(Inputs!$C$14+IF(B5<=10,Inputs!$C$12,Inputs!$C$13))/12 -> 53.018498 | L5: =IF(OR(E5=1,A5<=Inputs!$C$15),0,MAX(Inputs!$C$8*I5-(F5+G5+H5+J5-K5),0)) -> 0 | M5: =L5*INDEX(Rates!$B$2:$C$101,C5+1,IF(Inputs!$C$5="Male",1,2))/1000/12*Inputs!$C$16 -> 0 | N5: =IF($V$1=1,MAX(F5+G5+H5+J5-K5-M5,0)*Inputs!$C$22/12,0) -> 0 | O5: =IF(AND(MOD(A5,12)=0,B5>=Inputs!$C$18),MAX(F5+G5+H5+J5-K5-M5-N5,0)*Inputs!$C$17,0) -> 0 | P5: =F5+G5+H5+J5-K5-M5-N5+O5 -> 25395.861 | Q5: =IF(OR(E5=1,P5<=0),0,P5) -> 25395.861 | R5: =IF(OR(E5=1,AND(P5<=0,I5>0)),1,0) -> 0 | S5: =IF(L5>0,1,0) -> 0
A6: 5 | B6: =INT((A6-1)/12)+1 -> 1 | C6: =MIN(Inputs!$C$4+B6-1,99) -> 74 | D6: =INDEX('Return Path'!$D$5:$D$29,B6) -> 0.08 | E6: =R5 -> 0 | F6: =Q5 -> 25395.861 | G6: =IF(AND(MOD(A6-1,12)=0,B6<=Inputs!$C$7,E6=0),Inputs!$C$6,0) -> 0 | H6: =IF(B6=1,G6*Inputs!$C$9,0) -> 0 | I6: =I5+G6 -> 24000 | J6: =(F6+G6+H6)*((1+D6)^(1/12)-1) -> 163.39773 | K6: =(F6+G6+H6+J6)*(Inputs!$C$14+IF(B6<=10,Inputs!$C$12,Inputs!$C$13))/12 -> 53.248455 | L6: =IF(OR(E6=1,A6<=Inputs!$C$15),0,MAX(Inputs!$C$8*I6-(F6+G6+H6+J6-K6),0)) -> 0 | M6: =L6*INDEX(Rates!$B$2:$C$101,C6+1,IF(Inputs!$C$5="Male",1,2))/1000/12*Inputs!$C$16 -> 0 | N6: =IF($V$1=1,MAX(F6+G6+H6+J6-K6-M6,0)*Inputs!$C$22/12,0) -> 0 | O6: =IF(AND(MOD(A6,12)=0,B6>=Inputs!$C$18),MAX(F6+G6+H6+J6-K6-M6-N6,0)*Inputs!$C$17,0) -> 0 | P6: =F6+G6+H6+J6-K6-M6-N6+O6 -> 25506.01 | Q6: =IF(OR(E6=1,P6<=0),0,P6) -> 25506.01 | R6: =IF(OR(E6=1,AND(P6<=0,I6>0)),1,0) -> 0 | S6: =IF(L6>0,1,0) -> 0
A7: 6 | B7: =INT((A7-1)/12)+1 -> 1 | C7: =MIN(Inputs!$C$4+B7-1,99) -> 74 | D7: =INDEX('Return Path'!$D$5:$D$29,B7) -> 0.08 | E7: =R6 -> 0 | F7: =Q6 -> 25506.01 | G7: =IF(AND(MOD(A7-1,12)=0,B7<=Inputs!$C$7,E7=0),Inputs!$C$6,0) -> 0 | H7: =IF(B7=1,G7*Inputs!$C$9,0) -> 0 | I7: =I6+G7 -> 24000 | J7: =(F7+G7+H7)*((1+D7)^(1/12)-1) -> 164.10644 | K7: =(F7+G7+H7+J7)*(Inputs!$C$14+IF(B7<=10,Inputs!$C$12,Inputs!$C$13))/12 -> 53.479409 | L7: =IF(OR(E7=1,A7<=Inputs!$C$15),0,MAX(Inputs!$C$8*I7-(F7+G7+H7+J7-K7),0)) -> 0 | M7: =L7*INDEX(Rates!$B$2:$C$101,C7+1,IF(Inputs!$C$5="Male",1,2))/1000/12*Inputs!$C$16 -> 0 | N7: =IF($V$1=1,MAX(F7+G7+H7+J7-K7-M7,0)*Inputs!$C$22/12,0) -> 0 | O7: =IF(AND(MOD(A7,12)=0,B7>=Inputs!$C$18),MAX(F7+G7+H7+J7-K7-M7-N7,0)*Inputs!$C$17,0) -> 0 | P7: =F7+G7+H7+J7-K7-M7-N7+O7 -> 25616.637 | Q7: =IF(OR(E7=1,P7<=0),0,P7) -> 25616.637 | R7: =IF(OR(E7=1,AND(P7<=0,I7>0)),1,0) -> 0 | S7: =IF(L7>0,1,0) -> 0
A8: 7 | B8: =INT((A8-1)/12)+1 -> 1 | C8: =MIN(Inputs!$C$4+B8-1,99) -> 74 | D8: =INDEX('Return Path'!$D$5:$D$29,B8) -> 0.08 | E8: =R7 -> 0 | F8: =Q7 -> 25616.637 | G8: =IF(AND(MOD(A8-1,12)=0,B8<=Inputs!$C$7,E8=0),Inputs!$C$6,0) -> 0 | H8: =IF(B8=1,G8*Inputs!$C$9,0) -> 0 | I8: =I7+G8 -> 24000 | J8: =(F8+G8+H8)*((1+D8)^(1/12)-1) -> 164.81821 | K8: =(F8+G8+H8+J8)*(Inputs!$C$14+IF(B8<=10,Inputs!$C$12,Inputs!$C$13))/12 -> 53.711365 | L8: =IF(OR(E8=1,A8<=Inputs!$C$15),0,MAX(Inputs!$C$8*I8-(F8+G8+H8+J8-K8),0)) -> 0 | M8: =L8*INDEX(Rates!$B$2:$C$101,C8+1,IF(Inputs!$C$5="Male",1,2))/1000/12*Inputs!$C$16 -> 0 | N8: =IF($V$1=1,MAX(F8+G8+H8+J8-K8-M8,0)*Inputs!$C$22/12,0) -> 0 | O8: =IF(AND(MOD(A8,12)=0,B8>=Inputs!$C$18),MAX(F8+G8+H8+J8-K8-M8-N8,0)*Inputs!$C$17,0) -> 0 | P8: =F8+G8+H8+J8-K8-M8-N8+O8 -> 25727.744 | Q8: =IF(OR(E8=1,P8<=0),0,P8) -> 25727.744 | R8: =IF(OR(E8=1,AND(P8<=0,I8>0)),1,0) -> 0 | S8: =IF(L8>0,1,0) -> 0
A9: 8 | B9: =INT((A9-1)/12)+1 -> 1 | C9: =MIN(Inputs!$C$4+B9-1,99) -> 74 | D9: =INDEX('Return Path'!$D$5:$D$29,B9) -> 0.08 | E9: =R8 -> 0 | F9: =Q8 -> 25727.744 | G9: =IF(AND(MOD(A9-1,12)=0,B9<=Inputs!$C$7,E9=0),Inputs!$C$6,0) -> 0 | H9: =IF(B9=1,G9*Inputs!$C$9,0) -> 0 | I9: =I8+G9 -> 24000 | J9: =(F9+G9+H9)*((1+D9)^(1/12)-1) -> 165.53308 | K9: =(F9+G9+H9+J9)*(Inputs!$C$14+IF(B9<=10,Inputs!$C$12,Inputs!$C$13))/12 -> 53.944327 | L9: =IF(OR(E9=1,A9<=Inputs!$C$15),0,MAX(Inputs!$C$8*I9-(F9+G9+H9+J9-K9),0)) -> 0 | M9: =L9*INDEX(Rates!$B$2:$C$101,C9+1,IF(Inputs!$C$5="Male",1,2))/1000/12*Inputs!$C$16 -> 0 | N9: =IF($V$1=1,MAX(F9+G9+H9+J9-K9-M9,0)*Inputs!$C$22/12,0) -> 0 | O9: =IF(AND(MOD(A9,12)=0,B9>=Inputs!$C$18),MAX(F9+G9+H9+J9-K9-M9-N9,0)*Inputs!$C$17,0) -> 0 | P9: =F9+G9+H9+J9-K9-M9-N9+O9 -> 25839.333 | Q9: =IF(OR(E9=1,P9<=0),0,P9) -> 25839.333 | R9: =IF(OR(E9=1,AND(P9<=0,I9>0)),1,0) -> 0 | S9: =IF(L9>0,1,0) -> 0
A10: 9 | B10: =INT((A10-1)/12)+1 -> 1 | C10: =MIN(Inputs!$C$4+B10-1,99) -> 74 | D10: =INDEX('Return Path'!$D$5:$D$29,B10) -> 0.08 | E10: =R9 -> 0 | F10: =Q9 -> 25839.333 | G10: =IF(AND(MOD(A10-1,12)=0,B10<=Inputs!$C$7,E10=0),Inputs!$C$6,0) -> 0 | H10: =IF(B10=1,G10*Inputs!$C$9,0) -> 0 | I10: =I9+G10 -> 24000 | J10: =(F10+G10+H10)*((1+D10)^(1/12)-1) -> 166.25104 | K10: =(F10+G10+H10+J10)*(Inputs!$C$14+IF(B10<=10,Inputs!$C$12,Inputs!$C$13))/12 -> 54.178299 | L10: =IF(OR(E10=1,A10<=Inputs!$C$15),0,MAX(Inputs!$C$8*I10-(F10+G10+H10+J10-K10),0)) -> 0 | M10: =L10*INDEX(Rates!$B$2:$C$101,C10+1,IF(Inputs!$C$5="Male",1,2))/1000/12*Inputs!$C$16 -> 0 | N10: =IF($V$1=1,MAX(F10+G10+H10+J10-K10-M10,0)*Inputs!$C$22/12,0) -> 0 | O10: =IF(AND(MOD(A10,12)=0,B10>=Inputs!$C$18),MAX(F10+G10+H10+J10-K10-M10-N10,0)*Inputs!$C$17,0) -> 0 | P10: =F10+G10+H10+J10-K10-M10-N10+O10 -> 25951.405 | Q10: =IF(OR(E10=1,P10<=0),0,P10) -> 25951.405 | R10: =IF(OR(E10=1,AND(P10<=0,I10>0)),1,0) -> 0 | S10: =IF(L10>0,1,0) -> 0
A11: 10 | B11: =INT((A11-1)/12)+1 -> 1 | C11: =MIN(Inputs!$C$4+B11-1,99) -> 74 | D11: =INDEX('Return Path'!$D$5:$D$29,B11) -> 0.08 | E11: =R10 -> 0 | F11: =Q10 -> 25951.405 | G11: =IF(AND(MOD(A11-1,12)=0,B11<=Inputs!$C$7,E11=0),Inputs!$C$6,0) -> 0 | H11: =IF(B11=1,G11*Inputs!$C$9,0) -> 0 | I11: =I10+G11 -> 24000 | J11: =(F11+G11+H11)*((1+D11)^(1/12)-1) -> 166.97212 | K11: =(F11+G11+H11+J11)*(Inputs!$C$14+IF(B11<=10,Inputs!$C$12,Inputs!$C$13))/12 -> 54.413286 | L11: =IF(OR(E11=1,A11<=Inputs!$C$15),0,MAX(Inputs!$C$8*I11-(F11+G11+H11+J11-K11),0)) -> 0 | M11: =L11*INDEX(Rates!$B$2:$C$101,C11+1,IF(Inputs!$C$5="Male",1,2))/1000/12*Inputs!$C$16 -> 0 | N11: =IF($V$1=1,MAX(F11+G11+H11+J11-K11-M11,0)*Inputs!$C$22/12,0) -> 0 | O11: =IF(AND(MOD(A11,12)=0,B11>=Inputs!$C$18),MAX(F11+G11+H11+J11-K11-M11-N11,0)*Inputs!$C$17,0) -> 0 | P11: =F11+G11+H11+J11-K11-M11-N11+O11 -> 26063.964 | Q11: =IF(OR(E11=1,P11<=0),0,P11) -> 26063.964 | R11: =IF(OR(E11=1,AND(P11<=0,I11>0)),1,0) -> 0 | S11: =IF(L11>0,1,0) -> 0
A12: 11 | B12: =INT((A12-1)/12)+1 -> 1 | C12: =MIN(Inputs!$C$4+B12-1,99) -> 74 | D12: =INDEX('Return Path'!$D$5:$D$29,B12) -> 0.08 | E12: =R11 -> 0 | F12: =Q11 -> 26063.964 | G12: =IF(AND(MOD(A12-1,12)=0,B12<=Inputs!$C$7,E12=0),Inputs!$C$6,0) -> 0 | H12: =IF(B12=1,G12*Inputs!$C$9,0) -> 0 | I12: =I11+G12 -> 24000 | J12: =(F12+G12+H12)*((1+D12)^(1/12)-1) -> 167.69633 | K12: =(F12+G12+H12+J12)*(Inputs!$C$14+IF(B12<=10,Inputs!$C$12,Inputs!$C$13))/12 -> 54.649293 | L12: =IF(OR(E12=1,A12<=Inputs!$C$15),0,MAX(Inputs!$C$8*I12-(F12+G12+H12+J12-K12),0)) -> 0 | M12: =L12*INDEX(Rates!$B$2:$C$101,C12+1,IF(Inputs!$C$5="Male",1,2))/1000/12*Inputs!$C$16 -> 0 | N12: =IF($V$1=1,MAX(F12+G12+H12+J12-K12-M12,0)*Inputs!$C$22/12,0) -> 0 | O12: =IF(AND(MOD(A12,12)=0,B12>=Inputs!$C$18),MAX(F12+G12+H12+J12-K12-M12-N12,0)*Inputs!$C$17,0) -> 0 | P12: =F12+G12+H12+J12-K12-M12-N12+O12 -> 26177.011 | Q12: =IF(OR(E12=1,P12<=0),0,P12) -> 26177.011 | R12: =IF(OR(E12=1,AND(P12<=0,I12>0)),1,0) -> 0 | S12: =IF(L12>0,1,0) -> 0
A13: 12 | B13: =INT((A13-1)/12)+1 -> 1 | C13: =MIN(Inputs!$C$4+B13-1,99) -> 74 | D13: =INDEX('Return Path'!$D$5:$D$29,B13) -> 0.08 | E13: =R12 -> 0 | F13: =Q12 -> 26177.011 | G13: =IF(AND(MOD(A13-1,12)=0,B13<=Inputs!$C$7,E13=0),Inputs!$C$6,0) -> 0 | H13: =IF(B13=1,G13*Inputs!$C$9,0) -> 0 | I13: =I12+G13 -> 24000 | J13: =(F13+G13+H13)*((1+D13)^(1/12)-1) -> 168.42368 | K13: =(F13+G13+H13+J13)*(Inputs!$C$14+IF(B13<=10,Inputs!$C$12,Inputs!$C$13))/12 -> 54.886323 | L13: =IF(OR(E13=1,A13<=Inputs!$C$15),0,MAX(Inputs!$C$8*I13-(F13+G13+H13+J13-K13),0)) -> 0 | M13: =L13*INDEX(Rates!$B$2:$C$101,C13+1,IF(Inputs!$C$5="Male",1,2))/1000/12*Inputs!$C$16 -> 0 | N13: =IF($V$1=1,MAX(F13+G13+H13+J13-K13-M13,0)*Inputs!$C$22/12,0) -> 0 | O13: =IF(AND(MOD(A13,12)=0,B13>=Inputs!$C$18),MAX(F13+G13+H13+J13-K13-M13-N13,0)*Inputs!$C$17,0) -> 0 | P13: =F13+G13+H13+J13-K13-M13-N13+O13 -> 26290.549 | Q13: =IF(OR(E13=1,P13<=0),0,P13) -> 26290.549 | R13: =IF(OR(E13=1,AND(P13<=0,I13>0)),1,0) -> 0 | S13: =IF(L13>0,1,0) -> 0
A14: 13 | B14: =INT((A14-1)/12)+1 -> 2 | C14: =MIN(Inputs!$C$4+B14-1,99) -> 75 | D14: =INDEX('Return Path'!$D$5:$D$29,B14) -> 0.08 | E14: =R13 -> 0 | F14: =Q13 -> 26290.549 | G14: =IF(AND(MOD(A14-1,12)=0,B14<=Inputs!$C$7,E14=0),Inputs!$C$6,0) -> 24000 | H14: =IF(B14=1,G14*Inputs!$C$9,0) -> 0 | I14: =I13+G14 -> 48000 | J14: =(F14+G14+H14)*((1+D14)^(1/12)-1) -> 323.5709 | K14: =(F14+G14+H14+J14)*(Inputs!$C$14+IF(B14<=10,Inputs!$C$12,Inputs!$C$13))/12 -> 105.44608 | L14: =IF(OR(E14=1,A14<=Inputs!$C$15),0,MAX(Inputs!$C$8*I14-(F14+G14+H14+J14-K14),0)) -> 0 | M14: =L14*INDEX(Rates!$B$2:$C$101,C14+1,IF(Inputs!$C$5="Male",1,2))/1000/12*Inputs!$C$16 -> 0 | N14: =IF($V$1=1,MAX(F14+G14+H14+J14-K14-M14,0)*Inputs!$C$22/12,0) -> 0 | O14: =IF(AND(MOD(A14,12)=0,B14>=Inputs!$C$18),MAX(F14+G14+H14+J14-K14-M14-N14,0)*Inputs!$C$17,0) -> 0 | P14: =F14+G14+H14+J14-K14-M14-N14+O14 -> 50508.673 | Q14: =IF(OR(E14=1,P14<=0),0,P14) -> 50508.673 | R14: =IF(OR(E14=1,AND(P14<=0,I14>0)),1,0) -> 0 | S14: =IF(L14>0,1,0) -> 0
... A301: 300 | B301: =INT((A301-1)/12)+1 -> 25 | C301: =MIN(Inputs!$C$4+B301-1,99) -> 98 | D301: =INDEX('Return Path'!$D$5:$D$29,B301) -> 0.08 | E301: =R300 -> 0 | F301: =Q300 -> 571219.11 | G301: =IF(AND(MOD(A301-1,12)=0,B301<=Inputs!$C$7,E301=0),Inputs!$C$6,0) -> 0 | H301: =IF(B301=1,G301*Inputs!$C$9,0) -> 0 | I301: =I300+G301 -> 120000 | J301: =(F301+G301+H301)*((1+D301)^(1/12)-1) -> 3675.2409 | K301: =(F301+G301+H301+J301)*(Inputs!$C$14+IF(B301<=10,Inputs!$C$12,Inputs!$C$13))/12 -> 287.44717 | L301: =IF(OR(E301=1,A301<=Inputs!$C$15),0,MAX(Inputs!$C$8*I301-(F301+G301+H301+J301-K301),0)) -> 0 | M301: =L301*INDEX(Rates!$B$2:$C$101,C301+1,IF(Inputs!$C$5="Male",1,2))/1000/12*Inputs!$C$16 -> 0 | N301: =IF($V$1=1,MAX(F301+G301+H301+J301-K301-M301,0)*Inputs!$C$22/12,0) -> 0 | O301: =IF(AND(MOD(A301,12)=0,B301>=Inputs!$C$18),MAX(F301+G301+H301+J301-K301-M301-N301,0)*Inputs!$C$17,0) -> 2873.0345 | P301: =F301+G301+H301+J301-K301-M301-N301+O301 -> 577479.93 | Q301: =IF(OR(E301=1,P301<=0),0,P301) -> 577479.93 | R301: =IF(OR(E301=1,AND(P301<=0,I301>0)),1,0) -> 0 | S301: =IF(L301>0,1,0) -> 0

Sheet Calc_Payout
A1: Month | B1: Policy year | C1: Age (last b'day) | D1: Gross return p.a. | E1: Lapsed before? | F1: Policy value b/f | G1: Premium | H1: Investment bonus | I1: Net premiums to date | J1: Investment growth | K1: Policy fee + mgmt fee | L1: Sum at risk (charged) | M1: Insurance charge (COI) | N1: Dividend paid out | O1: Loyalty bonus | P1: PV before floor | Q1: Policy value c/f | R1: Lapsed? | S1: SAR>0 flag | U1: Dividend payout on? (1/0) | V1: 1
A2: 1 | B2: =INT((A2-1)/12)+1 -> 1 | C2: =MIN(Inputs!$C$4+B2-1,99) -> 74 | D2: =INDEX('Return Path'!$D$5:$D$29,B2) -> 0.08 | E2: 0 | F2: 0 | G2: =IF(AND(MOD(A2-1,12)=0,B2<=Inputs!$C$7,E2=0),Inputs!$C$6,0) -> 24000 | H2: =IF(B2=1,G2*Inputs!$C$9,0) -> 960 | I2: =G2 -> 24000 | J2: =(F2+G2+H2)*((1+D2)^(1/12)-1) -> 160.59339 | K2: =(F2+G2+H2+J2)*(Inputs!$C$14+IF(B2<=10,Inputs!$C$12,Inputs!$C$13))/12 -> 52.33457 | L2: =IF(OR(E2=1,A2<=Inputs!$C$15),0,MAX(Inputs!$C$8*I2-(F2+G2+H2+J2-K2),0)) -> 0 | M2: =L2*INDEX(Rates!$B$2:$C$101,C2+1,IF(Inputs!$C$5="Male",1,2))/1000/12*Inputs!$C$16 -> 0 | N2: =IF($V$1=1,MAX(F2+G2+H2+J2-K2-M2,0)*Inputs!$C$22/12,0) -> 167.12173 | O2: =IF(AND(MOD(A2,12)=0,B2>=Inputs!$C$18),MAX(F2+G2+H2+J2-K2-M2-N2,0)*Inputs!$C$17,0) -> 0 | P2: =F2+G2+H2+J2-K2-M2-N2+O2 -> 24901.137 | Q2: =IF(OR(E2=1,P2<=0),0,P2) -> 24901.137 | R2: =IF(OR(E2=1,AND(P2<=0,I2>0)),1,0) -> 0 | S2: =IF(L2>0,1,0) -> 0 | U2: Main – dividends paid out
A3: 2 | B3: =INT((A3-1)/12)+1 -> 1 | C3: =MIN(Inputs!$C$4+B3-1,99) -> 74 | D3: =INDEX('Return Path'!$D$5:$D$29,B3) -> 0.08 | E3: =R2 -> 0 | F3: =Q2 -> 24901.137 | G3: =IF(AND(MOD(A3-1,12)=0,B3<=Inputs!$C$7,E3=0),Inputs!$C$6,0) -> 0 | H3: =IF(B3=1,G3*Inputs!$C$9,0) -> 0 | I3: =I2+G3 -> 24000 | J3: =(F3+G3+H3)*((1+D3)^(1/12)-1) -> 160.21467 | K3: =(F3+G3+H3+J3)*(Inputs!$C$14+IF(B3<=10,Inputs!$C$12,Inputs!$C$13))/12 -> 52.21115 | L3: =IF(OR(E3=1,A3<=Inputs!$C$15),0,MAX(Inputs!$C$8*I3-(F3+G3+H3+J3-K3),0)) -> 0 | M3: =L3*INDEX(Rates!$B$2:$C$101,C3+1,IF(Inputs!$C$5="Male",1,2))/1000/12*Inputs!$C$16 -> 0 | N3: =IF($V$1=1,MAX(F3+G3+H3+J3-K3-M3,0)*Inputs!$C$22/12,0) -> 166.7276 | O3: =IF(AND(MOD(A3,12)=0,B3>=Inputs!$C$18),MAX(F3+G3+H3+J3-K3-M3-N3,0)*Inputs!$C$17,0) -> 0 | P3: =F3+G3+H3+J3-K3-M3-N3+O3 -> 24842.413 | Q3: =IF(OR(E3=1,P3<=0),0,P3) -> 24842.413 | R3: =IF(OR(E3=1,AND(P3<=0,I3>0)),1,0) -> 0 | S3: =IF(L3>0,1,0) -> 0
A4: 3 | B4: =INT((A4-1)/12)+1 -> 1 | C4: =MIN(Inputs!$C$4+B4-1,99) -> 74 | D4: =INDEX('Return Path'!$D$5:$D$29,B4) -> 0.08 | E4: =R3 -> 0 | F4: =Q3 -> 24842.413 | G4: =IF(AND(MOD(A4-1,12)=0,B4<=Inputs!$C$7,E4=0),Inputs!$C$6,0) -> 0 | H4: =IF(B4=1,G4*Inputs!$C$9,0) -> 0 | I4: =I3+G4 -> 24000 | J4: =(F4+G4+H4)*((1+D4)^(1/12)-1) -> 159.83683 | K4: =(F4+G4+H4+J4)*(Inputs!$C$14+IF(B4<=10,Inputs!$C$12,Inputs!$C$13))/12 -> 52.088021 | L4: =IF(OR(E4=1,A4<=Inputs!$C$15),0,MAX(Inputs!$C$8*I4-(F4+G4+H4+J4-K4),0)) -> 0 | M4: =L4*INDEX(Rates!$B$2:$C$101,C4+1,IF(Inputs!$C$5="Male",1,2))/1000/12*Inputs!$C$16 -> 0 | N4: =IF($V$1=1,MAX(F4+G4+H4+J4-K4-M4,0)*Inputs!$C$22/12,0) -> 166.33441 | O4: =IF(AND(MOD(A4,12)=0,B4>=Inputs!$C$18),MAX(F4+G4+H4+J4-K4-M4-N4,0)*Inputs!$C$17,0) -> 0 | P4: =F4+G4+H4+J4-K4-M4-N4+O4 -> 24783.827 | Q4: =IF(OR(E4=1,P4<=0),0,P4) -> 24783.827 | R4: =IF(OR(E4=1,AND(P4<=0,I4>0)),1,0) -> 0 | S4: =IF(L4>0,1,0) -> 0
A5: 4 | B5: =INT((A5-1)/12)+1 -> 1 | C5: =MIN(Inputs!$C$4+B5-1,99) -> 74 | D5: =INDEX('Return Path'!$D$5:$D$29,B5) -> 0.08 | E5: =R4 -> 0 | F5: =Q4 -> 24783.827 | G5: =IF(AND(MOD(A5-1,12)=0,B5<=Inputs!$C$7,E5=0),Inputs!$C$6,0) -> 0 | H5: =IF(B5=1,G5*Inputs!$C$9,0) -> 0 | I5: =I4+G5 -> 24000 | J5: =(F5+G5+H5)*((1+D5)^(1/12)-1) -> 159.45989 | K5: =(F5+G5+H5+J5)*(Inputs!$C$14+IF(B5<=10,Inputs!$C$12,Inputs!$C$13))/12 -> 51.965182 | L5: =IF(OR(E5=1,A5<=Inputs!$C$15),0,MAX(Inputs!$C$8*I5-(F5+G5+H5+J5-K5),0)) -> 0 | M5: =L5*INDEX(Rates!$B$2:$C$101,C5+1,IF(Inputs!$C$5="Male",1,2))/1000/12*Inputs!$C$16 -> 0 | N5: =IF($V$1=1,MAX(F5+G5+H5+J5-K5-M5,0)*Inputs!$C$22/12,0) -> 165.94215 | O5: =IF(AND(MOD(A5,12)=0,B5>=Inputs!$C$18),MAX(F5+G5+H5+J5-K5-M5-N5,0)*Inputs!$C$17,0) -> 0 | P5: =F5+G5+H5+J5-K5-M5-N5+O5 -> 24725.38 | Q5: =IF(OR(E5=1,P5<=0),0,P5) -> 24725.38 | R5: =IF(OR(E5=1,AND(P5<=0,I5>0)),1,0) -> 0 | S5: =IF(L5>0,1,0) -> 0
A6: 5 | B6: =INT((A6-1)/12)+1 -> 1 | C6: =MIN(Inputs!$C$4+B6-1,99) -> 74 | D6: =INDEX('Return Path'!$D$5:$D$29,B6) -> 0.08 | E6: =R5 -> 0 | F6: =Q5 -> 24725.38 | G6: =IF(AND(MOD(A6-1,12)=0,B6<=Inputs!$C$7,E6=0),Inputs!$C$6,0) -> 0 | H6: =IF(B6=1,G6*Inputs!$C$9,0) -> 0 | I6: =I5+G6 -> 24000 | J6: =(F6+G6+H6)*((1+D6)^(1/12)-1) -> 159.08384 | K6: =(F6+G6+H6+J6)*(Inputs!$C$14+IF(B6<=10,Inputs!$C$12,Inputs!$C$13))/12 -> 51.842633 | L6: =IF(OR(E6=1,A6<=Inputs!$C$15),0,MAX(Inputs!$C$8*I6-(F6+G6+H6+J6-K6),0)) -> 0 | M6: =L6*INDEX(Rates!$B$2:$C$101,C6+1,IF(Inputs!$C$5="Male",1,2))/1000/12*Inputs!$C$16 -> 0 | N6: =IF($V$1=1,MAX(F6+G6+H6+J6-K6-M6,0)*Inputs!$C$22/12,0) -> 165.55081 | O6: =IF(AND(MOD(A6,12)=0,B6>=Inputs!$C$18),MAX(F6+G6+H6+J6-K6-M6-N6,0)*Inputs!$C$17,0) -> 0 | P6: =F6+G6+H6+J6-K6-M6-N6+O6 -> 24667.07 | Q6: =IF(OR(E6=1,P6<=0),0,P6) -> 24667.07 | R6: =IF(OR(E6=1,AND(P6<=0,I6>0)),1,0) -> 0 | S6: =IF(L6>0,1,0) -> 0
A7: 6 | B7: =INT((A7-1)/12)+1 -> 1 | C7: =MIN(Inputs!$C$4+B7-1,99) -> 74 | D7: =INDEX('Return Path'!$D$5:$D$29,B7) -> 0.08 | E7: =R6 -> 0 | F7: =Q6 -> 24667.07 | G7: =IF(AND(MOD(A7-1,12)=0,B7<=Inputs!$C$7,E7=0),Inputs!$C$6,0) -> 0 | H7: =IF(B7=1,G7*Inputs!$C$9,0) -> 0 | I7: =I6+G7 -> 24000 | J7: =(F7+G7+H7)*((1+D7)^(1/12)-1) -> 158.70867 | K7: =(F7+G7+H7+J7)*(Inputs!$C$14+IF(B7<=10,Inputs!$C$12,Inputs!$C$13))/12 -> 51.720373 | L7: =IF(OR(E7=1,A7<=Inputs!$C$15),0,MAX(Inputs!$C$8*I7-(F7+G7+H7+J7-K7),0)) -> 0 | M7: =L7*INDEX(Rates!$B$2:$C$101,C7+1,IF(Inputs!$C$5="Male",1,2))/1000/12*Inputs!$C$16 -> 0 | N7: =IF($V$1=1,MAX(F7+G7+H7+J7-K7-M7,0)*Inputs!$C$22/12,0) -> 165.16039 | O7: =IF(AND(MOD(A7,12)=0,B7>=Inputs!$C$18),MAX(F7+G7+H7+J7-K7-M7-N7,0)*Inputs!$C$17,0) -> 0 | P7: =F7+G7+H7+J7-K7-M7-N7+O7 -> 24608.898 | Q7: =IF(OR(E7=1,P7<=0),0,P7) -> 24608.898 | R7: =IF(OR(E7=1,AND(P7<=0,I7>0)),1,0) -> 0 | S7: =IF(L7>0,1,0) -> 0
A8: 7 | B8: =INT((A8-1)/12)+1 -> 1 | C8: =MIN(Inputs!$C$4+B8-1,99) -> 74 | D8: =INDEX('Return Path'!$D$5:$D$29,B8) -> 0.08 | E8: =R7 -> 0 | F8: =Q7 -> 24608.898 | G8: =IF(AND(MOD(A8-1,12)=0,B8<=Inputs!$C$7,E8=0),Inputs!$C$6,0) -> 0 | H8: =IF(B8=1,G8*Inputs!$C$9,0) -> 0 | I8: =I7+G8 -> 24000 | J8: =(F8+G8+H8)*((1+D8)^(1/12)-1) -> 158.33439 | K8: =(F8+G8+H8+J8)*(Inputs!$C$14+IF(B8<=10,Inputs!$C$12,Inputs!$C$13))/12 -> 51.598401 | L8: =IF(OR(E8=1,A8<=Inputs!$C$15),0,MAX(Inputs!$C$8*I8-(F8+G8+H8+J8-K8),0)) -> 0 | M8: =L8*INDEX(Rates!$B$2:$C$101,C8+1,IF(Inputs!$C$5="Male",1,2))/1000/12*Inputs!$C$16 -> 0 | N8: =IF($V$1=1,MAX(F8+G8+H8+J8-K8-M8,0)*Inputs!$C$22/12,0) -> 164.7709 | O8: =IF(AND(MOD(A8,12)=0,B8>=Inputs!$C$18),MAX(F8+G8+H8+J8-K8-M8-N8,0)*Inputs!$C$17,0) -> 0 | P8: =F8+G8+H8+J8-K8-M8-N8+O8 -> 24550.863 | Q8: =IF(OR(E8=1,P8<=0),0,P8) -> 24550.863 | R8: =IF(OR(E8=1,AND(P8<=0,I8>0)),1,0) -> 0 | S8: =IF(L8>0,1,0) -> 0
A9: 8 | B9: =INT((A9-1)/12)+1 -> 1 | C9: =MIN(Inputs!$C$4+B9-1,99) -> 74 | D9: =INDEX('Return Path'!$D$5:$D$29,B9) -> 0.08 | E9: =R8 -> 0 | F9: =Q8 -> 24550.863 | G9: =IF(AND(MOD(A9-1,12)=0,B9<=Inputs!$C$7,E9=0),Inputs!$C$6,0) -> 0 | H9: =IF(B9=1,G9*Inputs!$C$9,0) -> 0 | I9: =I8+G9 -> 24000 | J9: =(F9+G9+H9)*((1+D9)^(1/12)-1) -> 157.96099 | K9: =(F9+G9+H9+J9)*(Inputs!$C$14+IF(B9<=10,Inputs!$C$12,Inputs!$C$13))/12 -> 51.476717 | L9: =IF(OR(E9=1,A9<=Inputs!$C$15),0,MAX(Inputs!$C$8*I9-(F9+G9+H9+J9-K9),0)) -> 0 | M9: =L9*INDEX(Rates!$B$2:$C$101,C9+1,IF(Inputs!$C$5="Male",1,2))/1000/12*Inputs!$C$16 -> 0 | N9: =IF($V$1=1,MAX(F9+G9+H9+J9-K9-M9,0)*Inputs!$C$22/12,0) -> 164.38232 | O9: =IF(AND(MOD(A9,12)=0,B9>=Inputs!$C$18),MAX(F9+G9+H9+J9-K9-M9-N9,0)*Inputs!$C$17,0) -> 0 | P9: =F9+G9+H9+J9-K9-M9-N9+O9 -> 24492.965 | Q9: =IF(OR(E9=1,P9<=0),0,P9) -> 24492.965 | R9: =IF(OR(E9=1,AND(P9<=0,I9>0)),1,0) -> 0 | S9: =IF(L9>0,1,0) -> 0
A10: 9 | B10: =INT((A10-1)/12)+1 -> 1 | C10: =MIN(Inputs!$C$4+B10-1,99) -> 74 | D10: =INDEX('Return Path'!$D$5:$D$29,B10) -> 0.08 | E10: =R9 -> 0 | F10: =Q9 -> 24492.965 | G10: =IF(AND(MOD(A10-1,12)=0,B10<=Inputs!$C$7,E10=0),Inputs!$C$6,0) -> 0 | H10: =IF(B10=1,G10*Inputs!$C$9,0) -> 0 | I10: =I9+G10 -> 24000 | J10: =(F10+G10+H10)*((1+D10)^(1/12)-1) -> 157.58848 | K10: =(F10+G10+H10+J10)*(Inputs!$C$14+IF(B10<=10,Inputs!$C$12,Inputs!$C$13))/12 -> 51.35532 | L10: =IF(OR(E10=1,A10<=Inputs!$C$15),0,MAX(Inputs!$C$8*I10-(F10+G10+H10+J10-K10),0)) -> 0 | M10: =L10*INDEX(Rates!$B$2:$C$101,C10+1,IF(Inputs!$C$5="Male",1,2))/1000/12*Inputs!$C$16 -> 0 | N10: =IF($V$1=1,MAX(F10+G10+H10+J10-K10-M10,0)*Inputs!$C$22/12,0) -> 163.99466 | O10: =IF(AND(MOD(A10,12)=0,B10>=Inputs!$C$18),MAX(F10+G10+H10+J10-K10-M10-N10,0)*Inputs!$C$17,0) -> 0 | P10: =F10+G10+H10+J10-K10-M10-N10+O10 -> 24435.204 | Q10: =IF(OR(E10=1,P10<=0),0,P10) -> 24435.204 | R10: =IF(OR(E10=1,AND(P10<=0,I10>0)),1,0) -> 0 | S10: =IF(L10>0,1,0) -> 0
A11: 10 | B11: =INT((A11-1)/12)+1 -> 1 | C11: =MIN(Inputs!$C$4+B11-1,99) -> 74 | D11: =INDEX('Return Path'!$D$5:$D$29,B11) -> 0.08 | E11: =R10 -> 0 | F11: =Q10 -> 24435.204 | G11: =IF(AND(MOD(A11-1,12)=0,B11<=Inputs!$C$7,E11=0),Inputs!$C$6,0) -> 0 | H11: =IF(B11=1,G11*Inputs!$C$9,0) -> 0 | I11: =I10+G11 -> 24000 | J11: =(F11+G11+H11)*((1+D11)^(1/12)-1) -> 157.21684 | K11: =(F11+G11+H11+J11)*(Inputs!$C$14+IF(B11<=10,Inputs!$C$12,Inputs!$C$13))/12 -> 51.23421 | L11: =IF(OR(E11=1,A11<=Inputs!$C$15),0,MAX(Inputs!$C$8*I11-(F11+G11+H11+J11-K11),0)) -> 0 | M11: =L11*INDEX(Rates!$B$2:$C$101,C11+1,IF(Inputs!$C$5="Male",1,2))/1000/12*Inputs!$C$16 -> 0 | N11: =IF($V$1=1,MAX(F11+G11+H11+J11-K11-M11,0)*Inputs!$C$22/12,0) -> 163.60791 | O11: =IF(AND(MOD(A11,12)=0,B11>=Inputs!$C$18),MAX(F11+G11+H11+J11-K11-M11-N11,0)*Inputs!$C$17,0) -> 0 | P11: =F11+G11+H11+J11-K11-M11-N11+O11 -> 24377.579 | Q11: =IF(OR(E11=1,P11<=0),0,P11) -> 24377.579 | R11: =IF(OR(E11=1,AND(P11<=0,I11>0)),1,0) -> 0 | S11: =IF(L11>0,1,0) -> 0
A12: 11 | B12: =INT((A12-1)/12)+1 -> 1 | C12: =MIN(Inputs!$C$4+B12-1,99) -> 74 | D12: =INDEX('Return Path'!$D$5:$D$29,B12) -> 0.08 | E12: =R11 -> 0 | F12: =Q11 -> 24377.579 | G12: =IF(AND(MOD(A12-1,12)=0,B12<=Inputs!$C$7,E12=0),Inputs!$C$6,0) -> 0 | H12: =IF(B12=1,G12*Inputs!$C$9,0) -> 0 | I12: =I11+G12 -> 24000 | J12: =(F12+G12+H12)*((1+D12)^(1/12)-1) -> 156.84607 | K12: =(F12+G12+H12+J12)*(Inputs!$C$14+IF(B12<=10,Inputs!$C$12,Inputs!$C$13))/12 -> 51.113385 | L12: =IF(OR(E12=1,A12<=Inputs!$C$15),0,MAX(Inputs!$C$8*I12-(F12+G12+H12+J12-K12),0)) -> 0 | M12: =L12*INDEX(Rates!$B$2:$C$101,C12+1,IF(Inputs!$C$5="Male",1,2))/1000/12*Inputs!$C$16 -> 0 | N12: =IF($V$1=1,MAX(F12+G12+H12+J12-K12-M12,0)*Inputs!$C$22/12,0) -> 163.22207 | O12: =IF(AND(MOD(A12,12)=0,B12>=Inputs!$C$18),MAX(F12+G12+H12+J12-K12-M12-N12,0)*Inputs!$C$17,0) -> 0 | P12: =F12+G12+H12+J12-K12-M12-N12+O12 -> 24320.089 | Q12: =IF(OR(E12=1,P12<=0),0,P12) -> 24320.089 | R12: =IF(OR(E12=1,AND(P12<=0,I12>0)),1,0) -> 0 | S12: =IF(L12>0,1,0) -> 0
A13: 12 | B13: =INT((A13-1)/12)+1 -> 1 | C13: =MIN(Inputs!$C$4+B13-1,99) -> 74 | D13: =INDEX('Return Path'!$D$5:$D$29,B13) -> 0.08 | E13: =R12 -> 0 | F13: =Q12 -> 24320.089 | G13: =IF(AND(MOD(A13-1,12)=0,B13<=Inputs!$C$7,E13=0),Inputs!$C$6,0) -> 0 | H13: =IF(B13=1,G13*Inputs!$C$9,0) -> 0 | I13: =I12+G13 -> 24000 | J13: =(F13+G13+H13)*((1+D13)^(1/12)-1) -> 156.47619 | K13: =(F13+G13+H13+J13)*(Inputs!$C$14+IF(B13<=10,Inputs!$C$12,Inputs!$C$13))/12 -> 50.992844 | L13: =IF(OR(E13=1,A13<=Inputs!$C$15),0,MAX(Inputs!$C$8*I13-(F13+G13+H13+J13-K13),0)) -> 0 | M13: =L13*INDEX(Rates!$B$2:$C$101,C13+1,IF(Inputs!$C$5="Male",1,2))/1000/12*Inputs!$C$16 -> 0 | N13: =IF($V$1=1,MAX(F13+G13+H13+J13-K13-M13,0)*Inputs!$C$22/12,0) -> 162.83715 | O13: =IF(AND(MOD(A13,12)=0,B13>=Inputs!$C$18),MAX(F13+G13+H13+J13-K13-M13-N13,0)*Inputs!$C$17,0) -> 0 | P13: =F13+G13+H13+J13-K13-M13-N13+O13 -> 24262.735 | Q13: =IF(OR(E13=1,P13<=0),0,P13) -> 24262.735 | R13: =IF(OR(E13=1,AND(P13<=0,I13>0)),1,0) -> 0 | S13: =IF(L13>0,1,0) -> 0
A14: 13 | B14: =INT((A14-1)/12)+1 -> 2 | C14: =MIN(Inputs!$C$4+B14-1,99) -> 75 | D14: =INDEX('Return Path'!$D$5:$D$29,B14) -> 0.08 | E14: =R13 -> 0 | F14: =Q13 -> 24262.735 | G14: =IF(AND(MOD(A14-1,12)=0,B14<=Inputs!$C$7,E14=0),Inputs!$C$6,0) -> 24000 | H14: =IF(B14=1,G14*Inputs!$C$9,0) -> 0 | I14: =I13+G14 -> 48000 | J14: =(F14+G14+H14)*((1+D14)^(1/12)-1) -> 310.52389 | K14: =(F14+G14+H14+J14)*(Inputs!$C$14+IF(B14<=10,Inputs!$C$12,Inputs!$C$13))/12 -> 101.19429 | L14: =IF(OR(E14=1,A14<=Inputs!$C$15),0,MAX(Inputs!$C$8*I14-(F14+G14+H14+J14-K14),0)) -> 0 | M14: =L14*INDEX(Rates!$B$2:$C$101,C14+1,IF(Inputs!$C$5="Male",1,2))/1000/12*Inputs!$C$16 -> 0 | N14: =IF($V$1=1,MAX(F14+G14+H14+J14-K14-M14,0)*Inputs!$C$22/12,0) -> 323.1471 | O14: =IF(AND(MOD(A14,12)=0,B14>=Inputs!$C$18),MAX(F14+G14+H14+J14-K14-M14-N14,0)*Inputs!$C$17,0) -> 0 | P14: =F14+G14+H14+J14-K14-M14-N14+O14 -> 48148.918 | Q14: =IF(OR(E14=1,P14<=0),0,P14) -> 48148.918 | R14: =IF(OR(E14=1,AND(P14<=0,I14>0)),1,0) -> 0 | S14: =IF(L14>0,1,0) -> 0
... A301: 300 | B301: =INT((A301-1)/12)+1 -> 25 | C301: =MIN(Inputs!$C$4+B301-1,99) -> 98 | D301: =INDEX('Return Path'!$D$5:$D$29,B301) -> 0.08 | E301: =R300 -> 1 | F301: =Q300 -> 0 | G301: =IF(AND(MOD(A301-1,12)=0,B301<=Inputs!$C$7,E301=0),Inputs!$C$6,0) -> 0 | H301: =IF(B301=1,G301*Inputs!$C$9,0) -> 0 | I301: =I300+G301 -> 120000 | J301: =(F301+G301+H301)*((1+D301)^(1/12)-1) -> 0 | K301: =(F301+G301+H301+J301)*(Inputs!$C$14+IF(B301<=10,Inputs!$C$12,Inputs!$C$13))/12 -> 0 | L301: =IF(OR(E301=1,A301<=Inputs!$C$15),0,MAX(Inputs!$C$8*I301-(F301+G301+H301+J301-K301),0)) -> 0 | M301: =L301*INDEX(Rates!$B$2:$C$101,C301+1,IF(Inputs!$C$5="Male",1,2))/1000/12*Inputs!$C$16 -> 0 | N301: =IF($V$1=1,MAX(F301+G301+H301+J301-K301-M301,0)*Inputs!$C$22/12,0) -> 0 | O301: =IF(AND(MOD(A301,12)=0,B301>=Inputs!$C$18),MAX(F301+G301+H301+J301-K301-M301-N301,0)*Inputs!$C$17,0) -> 0 | P301: =F301+G301+H301+J301-K301-M301-N301+O301 -> 0 | Q301: =IF(OR(E301=1,P301<=0),0,P301) -> 0 | R301: =IF(OR(E301=1,AND(P301<=0,I301>0)),1,0) -> 1 | S301: =IF(L301>0,1,0) -> 0

Sheet Calc_BI4
A1: Month | B1: Policy year | C1: Age (last b'day) | D1: Gross return p.a. | E1: Lapsed before? | F1: Policy value b/f | G1: Premium | H1: Investment bonus | I1: Net premiums to date | J1: Investment growth | K1: Policy fee + mgmt fee | L1: Sum at risk (charged) | M1: Insurance charge (COI) | N1: Dividend paid out | O1: Loyalty bonus | P1: PV before floor | Q1: Policy value c/f | R1: Lapsed? | S1: SAR>0 flag | U1: Dividend payout on? (1/0) | V1: 0
A2: 1 | B2: =INT((A2-1)/12)+1 -> 1 | C2: =MIN(Inputs!$C$4+B2-1,99) -> 74 | D2: =0.04 -> 0.04 | E2: 0 | F2: 0 | G2: =IF(AND(MOD(A2-1,12)=0,B2<=Inputs!$C$7,E2=0),Inputs!$C$6,0) -> 24000 | H2: =IF(B2=1,G2*Inputs!$C$9,0) -> 960 | I2: =G2 -> 24000 | J2: =(F2+G2+H2)*((1+D2)^(1/12)-1) -> 81.712545 | K2: =(F2+G2+H2+J2)*(Inputs!$C$19+IF(B2<=10,Inputs!$C$12,Inputs!$C$13))/12 -> 83.472375 | L2: =IF(OR(E2=1,A2<=Inputs!$C$15),0,MAX(Inputs!$C$8*I2-(F2+G2+H2+J2-K2),0)) -> 0 | M2: =L2*INDEX(Rates!$B$2:$C$101,C2+1,IF(Inputs!$C$5="Male",1,2))/1000/12*Inputs!$C$16 -> 0 | N2: =IF($V$1=1,MAX(F2+G2+H2+J2-K2-M2,0)*Inputs!$C$22/12,0) -> 0 | O2: =IF(AND(MOD(A2,12)=0,B2>=Inputs!$C$18),MAX(F2+G2+H2+J2-K2-M2-N2,0)*Inputs!$C$17,0) -> 0 | P2: =F2+G2+H2+J2-K2-M2-N2+O2 -> 24958.24 | Q2: =IF(OR(E2=1,P2<=0),0,P2) -> 24958.24 | R2: =IF(OR(E2=1,AND(P2<=0,I2>0)),1,0) -> 0 | S2: =IF(L2>0,1,0) -> 0 | U2: BI check 4%
A3: 2 | B3: =INT((A3-1)/12)+1 -> 1 | C3: =MIN(Inputs!$C$4+B3-1,99) -> 74 | D3: =0.04 -> 0.04 | E3: =R2 -> 0 | F3: =Q2 -> 24958.24 | G3: =IF(AND(MOD(A3-1,12)=0,B3<=Inputs!$C$7,E3=0),Inputs!$C$6,0) -> 0 | H3: =IF(B3=1,G3*Inputs!$C$9,0) -> 0 | I3: =I2+G3 -> 24000 | J3: =(F3+G3+H3)*((1+D3)^(1/12)-1) -> 81.706784 | K3: =(F3+G3+H3+J3)*(Inputs!$C$19+IF(B3<=10,Inputs!$C$12,Inputs!$C$13))/12 -> 83.46649 | L3: =IF(OR(E3=1,A3<=Inputs!$C$15),0,MAX(Inputs!$C$8*I3-(F3+G3+H3+J3-K3),0)) -> 0 | M3: =L3*INDEX(Rates!$B$2:$C$101,C3+1,IF(Inputs!$C$5="Male",1,2))/1000/12*Inputs!$C$16 -> 0 | N3: =IF($V$1=1,MAX(F3+G3+H3+J3-K3-M3,0)*Inputs!$C$22/12,0) -> 0 | O3: =IF(AND(MOD(A3,12)=0,B3>=Inputs!$C$18),MAX(F3+G3+H3+J3-K3-M3-N3,0)*Inputs!$C$17,0) -> 0 | P3: =F3+G3+H3+J3-K3-M3-N3+O3 -> 24956.48 | Q3: =IF(OR(E3=1,P3<=0),0,P3) -> 24956.48 | R3: =IF(OR(E3=1,AND(P3<=0,I3>0)),1,0) -> 0 | S3: =IF(L3>0,1,0) -> 0
A4: 3 | B4: =INT((A4-1)/12)+1 -> 1 | C4: =MIN(Inputs!$C$4+B4-1,99) -> 74 | D4: =0.04 -> 0.04 | E4: =R3 -> 0 | F4: =Q3 -> 24956.48 | G4: =IF(AND(MOD(A4-1,12)=0,B4<=Inputs!$C$7,E4=0),Inputs!$C$6,0) -> 0 | H4: =IF(B4=1,G4*Inputs!$C$9,0) -> 0 | I4: =I3+G4 -> 24000 | J4: =(F4+G4+H4)*((1+D4)^(1/12)-1) -> 81.701023 | K4: =(F4+G4+H4+J4)*(Inputs!$C$19+IF(B4<=10,Inputs!$C$12,Inputs!$C$13))/12 -> 83.460605 | L4: =IF(OR(E4=1,A4<=Inputs!$C$15),0,MAX(Inputs!$C$8*I4-(F4+G4+H4+J4-K4),0)) -> 0 | M4: =L4*INDEX(Rates!$B$2:$C$101,C4+1,IF(Inputs!$C$5="Male",1,2))/1000/12*Inputs!$C$16 -> 0 | N4: =IF($V$1=1,MAX(F4+G4+H4+J4-K4-M4,0)*Inputs!$C$22/12,0) -> 0 | O4: =IF(AND(MOD(A4,12)=0,B4>=Inputs!$C$18),MAX(F4+G4+H4+J4-K4-M4-N4,0)*Inputs!$C$17,0) -> 0 | P4: =F4+G4+H4+J4-K4-M4-N4+O4 -> 24954.721 | Q4: =IF(OR(E4=1,P4<=0),0,P4) -> 24954.721 | R4: =IF(OR(E4=1,AND(P4<=0,I4>0)),1,0) -> 0 | S4: =IF(L4>0,1,0) -> 0
A5: 4 | B5: =INT((A5-1)/12)+1 -> 1 | C5: =MIN(Inputs!$C$4+B5-1,99) -> 74 | D5: =0.04 -> 0.04 | E5: =R4 -> 0 | F5: =Q4 -> 24954.721 | G5: =IF(AND(MOD(A5-1,12)=0,B5<=Inputs!$C$7,E5=0),Inputs!$C$6,0) -> 0 | H5: =IF(B5=1,G5*Inputs!$C$9,0) -> 0 | I5: =I4+G5 -> 24000 | J5: =(F5+G5+H5)*((1+D5)^(1/12)-1) -> 81.695263 | K5: =(F5+G5+H5+J5)*(Inputs!$C$19+IF(B5<=10,Inputs!$C$12,Inputs!$C$13))/12 -> 83.45472 | L5: =IF(OR(E5=1,A5<=Inputs!$C$15),0,MAX(Inputs!$C$8*I5-(F5+G5+H5+J5-K5),0)) -> 0 | M5: =L5*INDEX(Rates!$B$2:$C$101,C5+1,IF(Inputs!$C$5="Male",1,2))/1000/12*Inputs!$C$16 -> 0 | N5: =IF($V$1=1,MAX(F5+G5+H5+J5-K5-M5,0)*Inputs!$C$22/12,0) -> 0 | O5: =IF(AND(MOD(A5,12)=0,B5>=Inputs!$C$18),MAX(F5+G5+H5+J5-K5-M5-N5,0)*Inputs!$C$17,0) -> 0 | P5: =F5+G5+H5+J5-K5-M5-N5+O5 -> 24952.961 | Q5: =IF(OR(E5=1,P5<=0),0,P5) -> 24952.961 | R5: =IF(OR(E5=1,AND(P5<=0,I5>0)),1,0) -> 0 | S5: =IF(L5>0,1,0) -> 0
A6: 5 | B6: =INT((A6-1)/12)+1 -> 1 | C6: =MIN(Inputs!$C$4+B6-1,99) -> 74 | D6: =0.04 -> 0.04 | E6: =R5 -> 0 | F6: =Q5 -> 24952.961 | G6: =IF(AND(MOD(A6-1,12)=0,B6<=Inputs!$C$7,E6=0),Inputs!$C$6,0) -> 0 | H6: =IF(B6=1,G6*Inputs!$C$9,0) -> 0 | I6: =I5+G6 -> 24000 | J6: =(F6+G6+H6)*((1+D6)^(1/12)-1) -> 81.689502 | K6: =(F6+G6+H6+J6)*(Inputs!$C$19+IF(B6<=10,Inputs!$C$12,Inputs!$C$13))/12 -> 83.448836 | L6: =IF(OR(E6=1,A6<=Inputs!$C$15),0,MAX(Inputs!$C$8*I6-(F6+G6+H6+J6-K6),0)) -> 0 | M6: =L6*INDEX(Rates!$B$2:$C$101,C6+1,IF(Inputs!$C$5="Male",1,2))/1000/12*Inputs!$C$16 -> 0 | N6: =IF($V$1=1,MAX(F6+G6+H6+J6-K6-M6,0)*Inputs!$C$22/12,0) -> 0 | O6: =IF(AND(MOD(A6,12)=0,B6>=Inputs!$C$18),MAX(F6+G6+H6+J6-K6-M6-N6,0)*Inputs!$C$17,0) -> 0 | P6: =F6+G6+H6+J6-K6-M6-N6+O6 -> 24951.202 | Q6: =IF(OR(E6=1,P6<=0),0,P6) -> 24951.202 | R6: =IF(OR(E6=1,AND(P6<=0,I6>0)),1,0) -> 0 | S6: =IF(L6>0,1,0) -> 0
A7: 6 | B7: =INT((A7-1)/12)+1 -> 1 | C7: =MIN(Inputs!$C$4+B7-1,99) -> 74 | D7: =0.04 -> 0.04 | E7: =R6 -> 0 | F7: =Q6 -> 24951.202 | G7: =IF(AND(MOD(A7-1,12)=0,B7<=Inputs!$C$7,E7=0),Inputs!$C$6,0) -> 0 | H7: =IF(B7=1,G7*Inputs!$C$9,0) -> 0 | I7: =I6+G7 -> 24000 | J7: =(F7+G7+H7)*((1+D7)^(1/12)-1) -> 81.683743 | K7: =(F7+G7+H7+J7)*(Inputs!$C$19+IF(B7<=10,Inputs!$C$12,Inputs!$C$13))/12 -> 83.442953 | L7: =IF(OR(E7=1,A7<=Inputs!$C$15),0,MAX(Inputs!$C$8*I7-(F7+G7+H7+J7-K7),0)) -> 0 | M7: =L7*INDEX(Rates!$B$2:$C$101,C7+1,IF(Inputs!$C$5="Male",1,2))/1000/12*Inputs!$C$16 -> 0 | N7: =IF($V$1=1,MAX(F7+G7+H7+J7-K7-M7,0)*Inputs!$C$22/12,0) -> 0 | O7: =IF(AND(MOD(A7,12)=0,B7>=Inputs!$C$18),MAX(F7+G7+H7+J7-K7-M7-N7,0)*Inputs!$C$17,0) -> 0 | P7: =F7+G7+H7+J7-K7-M7-N7+O7 -> 24949.443 | Q7: =IF(OR(E7=1,P7<=0),0,P7) -> 24949.443 | R7: =IF(OR(E7=1,AND(P7<=0,I7>0)),1,0) -> 0 | S7: =IF(L7>0,1,0) -> 0
A8: 7 | B8: =INT((A8-1)/12)+1 -> 1 | C8: =MIN(Inputs!$C$4+B8-1,99) -> 74 | D8: =0.04 -> 0.04 | E8: =R7 -> 0 | F8: =Q7 -> 24949.443 | G8: =IF(AND(MOD(A8-1,12)=0,B8<=Inputs!$C$7,E8=0),Inputs!$C$6,0) -> 0 | H8: =IF(B8=1,G8*Inputs!$C$9,0) -> 0 | I8: =I7+G8 -> 24000 | J8: =(F8+G8+H8)*((1+D8)^(1/12)-1) -> 81.677984 | K8: =(F8+G8+H8+J8)*(Inputs!$C$19+IF(B8<=10,Inputs!$C$12,Inputs!$C$13))/12 -> 83.43707 | L8: =IF(OR(E8=1,A8<=Inputs!$C$15),0,MAX(Inputs!$C$8*I8-(F8+G8+H8+J8-K8),0)) -> 0 | M8: =L8*INDEX(Rates!$B$2:$C$101,C8+1,IF(Inputs!$C$5="Male",1,2))/1000/12*Inputs!$C$16 -> 0 | N8: =IF($V$1=1,MAX(F8+G8+H8+J8-K8-M8,0)*Inputs!$C$22/12,0) -> 0 | O8: =IF(AND(MOD(A8,12)=0,B8>=Inputs!$C$18),MAX(F8+G8+H8+J8-K8-M8-N8,0)*Inputs!$C$17,0) -> 0 | P8: =F8+G8+H8+J8-K8-M8-N8+O8 -> 24947.684 | Q8: =IF(OR(E8=1,P8<=0),0,P8) -> 24947.684 | R8: =IF(OR(E8=1,AND(P8<=0,I8>0)),1,0) -> 0 | S8: =IF(L8>0,1,0) -> 0
A9: 8 | B9: =INT((A9-1)/12)+1 -> 1 | C9: =MIN(Inputs!$C$4+B9-1,99) -> 74 | D9: =0.04 -> 0.04 | E9: =R8 -> 0 | F9: =Q8 -> 24947.684 | G9: =IF(AND(MOD(A9-1,12)=0,B9<=Inputs!$C$7,E9=0),Inputs!$C$6,0) -> 0 | H9: =IF(B9=1,G9*Inputs!$C$9,0) -> 0 | I9: =I8+G9 -> 24000 | J9: =(F9+G9+H9)*((1+D9)^(1/12)-1) -> 81.672225 | K9: =(F9+G9+H9+J9)*(Inputs!$C$19+IF(B9<=10,Inputs!$C$12,Inputs!$C$13))/12 -> 83.431187 | L9: =IF(OR(E9=1,A9<=Inputs!$C$15),0,MAX(Inputs!$C$8*I9-(F9+G9+H9+J9-K9),0)) -> 0 | M9: =L9*INDEX(Rates!$B$2:$C$101,C9+1,IF(Inputs!$C$5="Male",1,2))/1000/12*Inputs!$C$16 -> 0 | N9: =IF($V$1=1,MAX(F9+G9+H9+J9-K9-M9,0)*Inputs!$C$22/12,0) -> 0 | O9: =IF(AND(MOD(A9,12)=0,B9>=Inputs!$C$18),MAX(F9+G9+H9+J9-K9-M9-N9,0)*Inputs!$C$17,0) -> 0 | P9: =F9+G9+H9+J9-K9-M9-N9+O9 -> 24945.925 | Q9: =IF(OR(E9=1,P9<=0),0,P9) -> 24945.925 | R9: =IF(OR(E9=1,AND(P9<=0,I9>0)),1,0) -> 0 | S9: =IF(L9>0,1,0) -> 0
A10: 9 | B10: =INT((A10-1)/12)+1 -> 1 | C10: =MIN(Inputs!$C$4+B10-1,99) -> 74 | D10: =0.04 -> 0.04 | E10: =R9 -> 0 | F10: =Q9 -> 24945.925 | G10: =IF(AND(MOD(A10-1,12)=0,B10<=Inputs!$C$7,E10=0),Inputs!$C$6,0) -> 0 | H10: =IF(B10=1,G10*Inputs!$C$9,0) -> 0 | I10: =I9+G10 -> 24000 | J10: =(F10+G10+H10)*((1+D10)^(1/12)-1) -> 81.666467 | K10: =(F10+G10+H10+J10)*(Inputs!$C$19+IF(B10<=10,Inputs!$C$12,Inputs!$C$13))/12 -> 83.425304 | L10: =IF(OR(E10=1,A10<=Inputs!$C$15),0,MAX(Inputs!$C$8*I10-(F10+G10+H10+J10-K10),0)) -> 0 | M10: =L10*INDEX(Rates!$B$2:$C$101,C10+1,IF(Inputs!$C$5="Male",1,2))/1000/12*Inputs!$C$16 -> 0 | N10: =IF($V$1=1,MAX(F10+G10+H10+J10-K10-M10,0)*Inputs!$C$22/12,0) -> 0 | O10: =IF(AND(MOD(A10,12)=0,B10>=Inputs!$C$18),MAX(F10+G10+H10+J10-K10-M10-N10,0)*Inputs!$C$17,0) -> 0 | P10: =F10+G10+H10+J10-K10-M10-N10+O10 -> 24944.166 | Q10: =IF(OR(E10=1,P10<=0),0,P10) -> 24944.166 | R10: =IF(OR(E10=1,AND(P10<=0,I10>0)),1,0) -> 0 | S10: =IF(L10>0,1,0) -> 0
A11: 10 | B11: =INT((A11-1)/12)+1 -> 1 | C11: =MIN(Inputs!$C$4+B11-1,99) -> 74 | D11: =0.04 -> 0.04 | E11: =R10 -> 0 | F11: =Q10 -> 24944.166 | G11: =IF(AND(MOD(A11-1,12)=0,B11<=Inputs!$C$7,E11=0),Inputs!$C$6,0) -> 0 | H11: =IF(B11=1,G11*Inputs!$C$9,0) -> 0 | I11: =I10+G11 -> 24000 | J11: =(F11+G11+H11)*((1+D11)^(1/12)-1) -> 81.660709 | K11: =(F11+G11+H11+J11)*(Inputs!$C$19+IF(B11<=10,Inputs!$C$12,Inputs!$C$13))/12 -> 83.419422 | L11: =IF(OR(E11=1,A11<=Inputs!$C$15),0,MAX(Inputs!$C$8*I11-(F11+G11+H11+J11-K11),0)) -> 0 | M11: =L11*INDEX(Rates!$B$2:$C$101,C11+1,IF(Inputs!$C$5="Male",1,2))/1000/12*Inputs!$C$16 -> 0 | N11: =IF($V$1=1,MAX(F11+G11+H11+J11-K11-M11,0)*Inputs!$C$22/12,0) -> 0 | O11: =IF(AND(MOD(A11,12)=0,B11>=Inputs!$C$18),MAX(F11+G11+H11+J11-K11-M11-N11,0)*Inputs!$C$17,0) -> 0 | P11: =F11+G11+H11+J11-K11-M11-N11+O11 -> 24942.407 | Q11: =IF(OR(E11=1,P11<=0),0,P11) -> 24942.407 | R11: =IF(OR(E11=1,AND(P11<=0,I11>0)),1,0) -> 0 | S11: =IF(L11>0,1,0) -> 0
A12: 11 | B12: =INT((A12-1)/12)+1 -> 1 | C12: =MIN(Inputs!$C$4+B12-1,99) -> 74 | D12: =0.04 -> 0.04 | E12: =R11 -> 0 | F12: =Q11 -> 24942.407 | G12: =IF(AND(MOD(A12-1,12)=0,B12<=Inputs!$C$7,E12=0),Inputs!$C$6,0) -> 0 | H12: =IF(B12=1,G12*Inputs!$C$9,0) -> 0 | I12: =I11+G12 -> 24000 | J12: =(F12+G12+H12)*((1+D12)^(1/12)-1) -> 81.654951 | K12: =(F12+G12+H12+J12)*(Inputs!$C$19+IF(B12<=10,Inputs!$C$12,Inputs!$C$13))/12 -> 83.413541 | L12: =IF(OR(E12=1,A12<=Inputs!$C$15),0,MAX(Inputs!$C$8*I12-(F12+G12+H12+J12-K12),0)) -> 0 | M12: =L12*INDEX(Rates!$B$2:$C$101,C12+1,IF(Inputs!$C$5="Male",1,2))/1000/12*Inputs!$C$16 -> 0 | N12: =IF($V$1=1,MAX(F12+G12+H12+J12-K12-M12,0)*Inputs!$C$22/12,0) -> 0 | O12: =IF(AND(MOD(A12,12)=0,B12>=Inputs!$C$18),MAX(F12+G12+H12+J12-K12-M12-N12,0)*Inputs!$C$17,0) -> 0 | P12: =F12+G12+H12+J12-K12-M12-N12+O12 -> 24940.649 | Q12: =IF(OR(E12=1,P12<=0),0,P12) -> 24940.649 | R12: =IF(OR(E12=1,AND(P12<=0,I12>0)),1,0) -> 0 | S12: =IF(L12>0,1,0) -> 0
A13: 12 | B13: =INT((A13-1)/12)+1 -> 1 | C13: =MIN(Inputs!$C$4+B13-1,99) -> 74 | D13: =0.04 -> 0.04 | E13: =R12 -> 0 | F13: =Q12 -> 24940.649 | G13: =IF(AND(MOD(A13-1,12)=0,B13<=Inputs!$C$7,E13=0),Inputs!$C$6,0) -> 0 | H13: =IF(B13=1,G13*Inputs!$C$9,0) -> 0 | I13: =I12+G13 -> 24000 | J13: =(F13+G13+H13)*((1+D13)^(1/12)-1) -> 81.649194 | K13: =(F13+G13+H13+J13)*(Inputs!$C$19+IF(B13<=10,Inputs!$C$12,Inputs!$C$13))/12 -> 83.40766 | L13: =IF(OR(E13=1,A13<=Inputs!$C$15),0,MAX(Inputs!$C$8*I13-(F13+G13+H13+J13-K13),0)) -> 0 | M13: =L13*INDEX(Rates!$B$2:$C$101,C13+1,IF(Inputs!$C$5="Male",1,2))/1000/12*Inputs!$C$16 -> 0 | N13: =IF($V$1=1,MAX(F13+G13+H13+J13-K13-M13,0)*Inputs!$C$22/12,0) -> 0 | O13: =IF(AND(MOD(A13,12)=0,B13>=Inputs!$C$18),MAX(F13+G13+H13+J13-K13-M13-N13,0)*Inputs!$C$17,0) -> 0 | P13: =F13+G13+H13+J13-K13-M13-N13+O13 -> 24938.89 | Q13: =IF(OR(E13=1,P13<=0),0,P13) -> 24938.89 | R13: =IF(OR(E13=1,AND(P13<=0,I13>0)),1,0) -> 0 | S13: =IF(L13>0,1,0) -> 0
A14: 13 | B14: =INT((A14-1)/12)+1 -> 2 | C14: =MIN(Inputs!$C$4+B14-1,99) -> 75 | D14: =0.04 -> 0.04 | E14: =R13 -> 0 | F14: =Q13 -> 24938.89 | G14: =IF(AND(MOD(A14-1,12)=0,B14<=Inputs!$C$7,E14=0),Inputs!$C$6,0) -> 24000 | H14: =IF(B14=1,G14*Inputs!$C$9,0) -> 0 | I14: =I13+G14 -> 48000 | J14: =(F14+G14+H14)*((1+D14)^(1/12)-1) -> 160.21319 | K14: =(F14+G14+H14+J14)*(Inputs!$C$19+IF(B14<=10,Inputs!$C$12,Inputs!$C$13))/12 -> 163.66368 | L14: =IF(OR(E14=1,A14<=Inputs!$C$15),0,MAX(Inputs!$C$8*I14-(F14+G14+H14+J14-K14),0)) -> 0 | M14: =L14*INDEX(Rates!$B$2:$C$101,C14+1,IF(Inputs!$C$5="Male",1,2))/1000/12*Inputs!$C$16 -> 0 | N14: =IF($V$1=1,MAX(F14+G14+H14+J14-K14-M14,0)*Inputs!$C$22/12,0) -> 0 | O14: =IF(AND(MOD(A14,12)=0,B14>=Inputs!$C$18),MAX(F14+G14+H14+J14-K14-M14-N14,0)*Inputs!$C$17,0) -> 0 | P14: =F14+G14+H14+J14-K14-M14-N14+O14 -> 48935.44 | Q14: =IF(OR(E14=1,P14<=0),0,P14) -> 48935.44 | R14: =IF(OR(E14=1,AND(P14<=0,I14>0)),1,0) -> 0 | S14: =IF(L14>0,1,0) -> 0
... A301: 300 | B301: =INT((A301-1)/12)+1 -> 25 | C301: =MIN(Inputs!$C$4+B301-1,99) -> 98 | D301: =0.04 -> 0.04 | E301: =R300 -> 0 | F301: =Q300 -> 169403.6 | G301: =IF(AND(MOD(A301-1,12)=0,B301<=Inputs!$C$7,E301=0),Inputs!$C$6,0) -> 0 | H301: =IF(B301=1,G301*Inputs!$C$9,0) -> 0 | I301: =I300+G301 -> 120000 | J301: =(F301+G301+H301)*((1+D301)^(1/12)-1) -> 554.58329 | K301: =(F301+G301+H301+J301)*(Inputs!$C$19+IF(B301<=10,Inputs!$C$12,Inputs!$C$13))/12 -> 297.42681 | L301: =IF(OR(E301=1,A301<=Inputs!$C$15),0,MAX(Inputs!$C$8*I301-(F301+G301+H301+J301-K301),0)) -> 0 | M301: =L301*INDEX(Rates!$B$2:$C$101,C301+1,IF(Inputs!$C$5="Male",1,2))/1000/12*Inputs!$C$16 -> 0 | N301: =IF($V$1=1,MAX(F301+G301+H301+J301-K301-M301,0)*Inputs!$C$22/12,0) -> 0 | O301: =IF(AND(MOD(A301,12)=0,B301>=Inputs!$C$18),MAX(F301+G301+H301+J301-K301-M301-N301,0)*Inputs!$C$17,0) -> 848.30376 | P301: =F301+G301+H301+J301-K301-M301-N301+O301 -> 170509.06 | Q301: =IF(OR(E301=1,P301<=0),0,P301) -> 170509.06 | R301: =IF(OR(E301=1,AND(P301<=0,I301>0)),1,0) -> 0 | S301: =IF(L301>0,1,0) -> 0

Sheet Calc_BI8
A1: Month | B1: Policy year | C1: Age (last b'day) | D1: Gross return p.a. | E1: Lapsed before? | F1: Policy value b/f | G1: Premium | H1: Investment bonus | I1: Net premiums to date | J1: Investment growth | K1: Policy fee + mgmt fee | L1: Sum at risk (charged) | M1: Insurance charge (COI) | N1: Dividend paid out | O1: Loyalty bonus | P1: PV before floor | Q1: Policy value c/f | R1: Lapsed? | S1: SAR>0 flag | U1: Dividend payout on? (1/0) | V1: 0
A2: 1 | B2: =INT((A2-1)/12)+1 -> 1 | C2: =MIN(Inputs!$C$4+B2-1,99) -> 74 | D2: =0.08 -> 0.08 | E2: 0 | F2: 0 | G2: =IF(AND(MOD(A2-1,12)=0,B2<=Inputs!$C$7,E2=0),Inputs!$C$6,0) -> 24000 | H2: =IF(B2=1,G2*Inputs!$C$9,0) -> 960 | I2: =G2 -> 24000 | J2: =(F2+G2+H2)*((1+D2)^(1/12)-1) -> 160.59339 | K2: =(F2+G2+H2+J2)*(Inputs!$C$19+IF(B2<=10,Inputs!$C$12,Inputs!$C$13))/12 -> 83.735311 | L2: =IF(OR(E2=1,A2<=Inputs!$C$15),0,MAX(Inputs!$C$8*I2-(F2+G2+H2+J2-K2),0)) -> 0 | M2: =L2*INDEX(Rates!$B$2:$C$101,C2+1,IF(Inputs!$C$5="Male",1,2))/1000/12*Inputs!$C$16 -> 0 | N2: =IF($V$1=1,MAX(F2+G2+H2+J2-K2-M2,0)*Inputs!$C$22/12,0) -> 0 | O2: =IF(AND(MOD(A2,12)=0,B2>=Inputs!$C$18),MAX(F2+G2+H2+J2-K2-M2-N2,0)*Inputs!$C$17,0) -> 0 | P2: =F2+G2+H2+J2-K2-M2-N2+O2 -> 25036.858 | Q2: =IF(OR(E2=1,P2<=0),0,P2) -> 25036.858 | R2: =IF(OR(E2=1,AND(P2<=0,I2>0)),1,0) -> 0 | S2: =IF(L2>0,1,0) -> 0 | U2: BI check 8%
A3: 2 | B3: =INT((A3-1)/12)+1 -> 1 | C3: =MIN(Inputs!$C$4+B3-1,99) -> 74 | D3: =0.08 -> 0.08 | E3: =R2 -> 0 | F3: =Q2 -> 25036.858 | G3: =IF(AND(MOD(A3-1,12)=0,B3<=Inputs!$C$7,E3=0),Inputs!$C$6,0) -> 0 | H3: =IF(B3=1,G3*Inputs!$C$9,0) -> 0 | I3: =I2+G3 -> 24000 | J3: =(F3+G3+H3)*((1+D3)^(1/12)-1) -> 161.0879 | K3: =(F3+G3+H3+J3)*(Inputs!$C$19+IF(B3<=10,Inputs!$C$12,Inputs!$C$13))/12 -> 83.993153 | L3: =IF(OR(E3=1,A3<=Inputs!$C$15),0,MAX(Inputs!$C$8*I3-(F3+G3+H3+J3-K3),0)) -> 0 | M3: =L3*INDEX(Rates!$B$2:$C$101,C3+1,IF(Inputs!$C$5="Male",1,2))/1000/12*Inputs!$C$16 -> 0 | N3: =IF($V$1=1,MAX(F3+G3+H3+J3-K3-M3,0)*Inputs!$C$22/12,0) -> 0 | O3: =IF(AND(MOD(A3,12)=0,B3>=Inputs!$C$18),MAX(F3+G3+H3+J3-K3-M3-N3,0)*Inputs!$C$17,0) -> 0 | P3: =F3+G3+H3+J3-K3-M3-N3+O3 -> 25113.953 | Q3: =IF(OR(E3=1,P3<=0),0,P3) -> 25113.953 | R3: =IF(OR(E3=1,AND(P3<=0,I3>0)),1,0) -> 0 | S3: =IF(L3>0,1,0) -> 0
A4: 3 | B4: =INT((A4-1)/12)+1 -> 1 | C4: =MIN(Inputs!$C$4+B4-1,99) -> 74 | D4: =0.08 -> 0.08 | E4: =R3 -> 0 | F4: =Q3 -> 25113.953 | G4: =IF(AND(MOD(A4-1,12)=0,B4<=Inputs!$C$7,E4=0),Inputs!$C$6,0) -> 0 | H4: =IF(B4=1,G4*Inputs!$C$9,0) -> 0 | I4: =I3+G4 -> 24000 | J4: =(F4+G4+H4)*((1+D4)^(1/12)-1) -> 161.58393 | K4: =(F4+G4+H4+J4)*(Inputs!$C$19+IF(B4<=10,Inputs!$C$12,Inputs!$C$13))/12 -> 84.251789 | L4: =IF(OR(E4=1,A4<=Inputs!$C$15),0,MAX(Inputs!$C$8*I4-(F4+G4+H4+J4-K4),0)) -> 0 | M4: =L4*INDEX(Rates!$B$2:$C$101,C4+1,IF(Inputs!$C$5="Male",1,2))/1000/12*Inputs!$C$16 -> 0 | N4: =IF($V$1=1,MAX(F4+G4+H4+J4-K4-M4,0)*Inputs!$C$22/12,0) -> 0 | O4: =IF(AND(MOD(A4,12)=0,B4>=Inputs!$C$18),MAX(F4+G4+H4+J4-K4-M4-N4,0)*Inputs!$C$17,0) -> 0 | P4: =F4+G4+H4+J4-K4-M4-N4+O4 -> 25191.285 | Q4: =IF(OR(E4=1,P4<=0),0,P4) -> 25191.285 | R4: =IF(OR(E4=1,AND(P4<=0,I4>0)),1,0) -> 0 | S4: =IF(L4>0,1,0) -> 0
A5: 4 | B5: =INT((A5-1)/12)+1 -> 1 | C5: =MIN(Inputs!$C$4+B5-1,99) -> 74 | D5: =0.08 -> 0.08 | E5: =R4 -> 0 | F5: =Q4 -> 25191.285 | G5: =IF(AND(MOD(A5-1,12)=0,B5<=Inputs!$C$7,E5=0),Inputs!$C$6,0) -> 0 | H5: =IF(B5=1,G5*Inputs!$C$9,0) -> 0 | I5: =I4+G5 -> 24000 | J5: =(F5+G5+H5)*((1+D5)^(1/12)-1) -> 162.08149 | K5: =(F5+G5+H5+J5)*(Inputs!$C$19+IF(B5<=10,Inputs!$C$12,Inputs!$C$13))/12 -> 84.511222 | L5: =IF(OR(E5=1,A5<=Inputs!$C$15),0,MAX(Inputs!$C$8*I5-(F5+G5+H5+J5-K5),0)) -> 0 | M5: =L5*INDEX(Rates!$B$2:$C$101,C5+1,IF(Inputs!$C$5="Male",1,2))/1000/12*Inputs!$C$16 -> 0 | N5: =IF($V$1=1,MAX(F5+G5+H5+J5-K5-M5,0)*Inputs!$C$22/12,0) -> 0 | O5: =IF(AND(MOD(A5,12)=0,B5>=Inputs!$C$18),MAX(F5+G5+H5+J5-K5-M5-N5,0)*Inputs!$C$17,0) -> 0 | P5: =F5+G5+H5+J5-K5-M5-N5+O5 -> 25268.855 | Q5: =IF(OR(E5=1,P5<=0),0,P5) -> 25268.855 | R5: =IF(OR(E5=1,AND(P5<=0,I5>0)),1,0) -> 0 | S5: =IF(L5>0,1,0) -> 0
A6: 5 | B6: =INT((A6-1)/12)+1 -> 1 | C6: =MIN(Inputs!$C$4+B6-1,99) -> 74 | D6: =0.08 -> 0.08 | E6: =R5 -> 0 | F6: =Q5 -> 25268.855 | G6: =IF(AND(MOD(A6-1,12)=0,B6<=Inputs!$C$7,E6=0),Inputs!$C$6,0) -> 0 | H6: =IF(B6=1,G6*Inputs!$C$9,0) -> 0 | I6: =I5+G6 -> 24000 | J6: =(F6+G6+H6)*((1+D6)^(1/12)-1) -> 162.58058 | K6: =(F6+G6+H6+J6)*(Inputs!$C$19+IF(B6<=10,Inputs!$C$12,Inputs!$C$13))/12 -> 84.771453 | L6: =IF(OR(E6=1,A6<=Inputs!$C$15),0,MAX(Inputs!$C$8*I6-(F6+G6+H6+J6-K6),0)) -> 0 | M6: =L6*INDEX(Rates!$B$2:$C$101,C6+1,IF(Inputs!$C$5="Male",1,2))/1000/12*Inputs!$C$16 -> 0 | N6: =IF($V$1=1,MAX(F6+G6+H6+J6-K6-M6,0)*Inputs!$C$22/12,0) -> 0 | O6: =IF(AND(MOD(A6,12)=0,B6>=Inputs!$C$18),MAX(F6+G6+H6+J6-K6-M6-N6,0)*Inputs!$C$17,0) -> 0 | P6: =F6+G6+H6+J6-K6-M6-N6+O6 -> 25346.664 | Q6: =IF(OR(E6=1,P6<=0),0,P6) -> 25346.664 | R6: =IF(OR(E6=1,AND(P6<=0,I6>0)),1,0) -> 0 | S6: =IF(L6>0,1,0) -> 0
A7: 6 | B7: =INT((A7-1)/12)+1 -> 1 | C7: =MIN(Inputs!$C$4+B7-1,99) -> 74 | D7: =0.08 -> 0.08 | E7: =R6 -> 0 | F7: =Q6 -> 25346.664 | G7: =IF(AND(MOD(A7-1,12)=0,B7<=Inputs!$C$7,E7=0),Inputs!$C$6,0) -> 0 | H7: =IF(B7=1,G7*Inputs!$C$9,0) -> 0 | I7: =I6+G7 -> 24000 | J7: =(F7+G7+H7)*((1+D7)^(1/12)-1) -> 163.0812 | K7: =(F7+G7+H7+J7)*(Inputs!$C$19+IF(B7<=10,Inputs!$C$12,Inputs!$C$13))/12 -> 85.032485 | L7: =IF(OR(E7=1,A7<=Inputs!$C$15),0,MAX(Inputs!$C$8*I7-(F7+G7+H7+J7-K7),0)) -> 0 | M7: =L7*INDEX(Rates!$B$2:$C$101,C7+1,IF(Inputs!$C$5="Male",1,2))/1000/12*Inputs!$C$16 -> 0 | N7: =IF($V$1=1,MAX(F7+G7+H7+J7-K7-M7,0)*Inputs!$C$22/12,0) -> 0 | O7: =IF(AND(MOD(A7,12)=0,B7>=Inputs!$C$18),MAX(F7+G7+H7+J7-K7-M7-N7,0)*Inputs!$C$17,0) -> 0 | P7: =F7+G7+H7+J7-K7-M7-N7+O7 -> 25424.713 | Q7: =IF(OR(E7=1,P7<=0),0,P7) -> 25424.713 | R7: =IF(OR(E7=1,AND(P7<=0,I7>0)),1,0) -> 0 | S7: =IF(L7>0,1,0) -> 0
A8: 7 | B8: =INT((A8-1)/12)+1 -> 1 | C8: =MIN(Inputs!$C$4+B8-1,99) -> 74 | D8: =0.08 -> 0.08 | E8: =R7 -> 0 | F8: =Q7 -> 25424.713 | G8: =IF(AND(MOD(A8-1,12)=0,B8<=Inputs!$C$7,E8=0),Inputs!$C$6,0) -> 0 | H8: =IF(B8=1,G8*Inputs!$C$9,0) -> 0 | I8: =I7+G8 -> 24000 | J8: =(F8+G8+H8)*((1+D8)^(1/12)-1) -> 163.58337 | K8: =(F8+G8+H8+J8)*(Inputs!$C$19+IF(B8<=10,Inputs!$C$12,Inputs!$C$13))/12 -> 85.294321 | L8: =IF(OR(E8=1,A8<=Inputs!$C$15),0,MAX(Inputs!$C$8*I8-(F8+G8+H8+J8-K8),0)) -> 0 | M8: =L8*INDEX(Rates!$B$2:$C$101,C8+1,IF(Inputs!$C$5="Male",1,2))/1000/12*Inputs!$C$16 -> 0 | N8: =IF($V$1=1,MAX(F8+G8+H8+J8-K8-M8,0)*Inputs!$C$22/12,0) -> 0 | O8: =IF(AND(MOD(A8,12)=0,B8>=Inputs!$C$18),MAX(F8+G8+H8+J8-K8-M8-N8,0)*Inputs!$C$17,0) -> 0 | P8: =F8+G8+H8+J8-K8-M8-N8+O8 -> 25503.002 | Q8: =IF(OR(E8=1,P8<=0),0,P8) -> 25503.002 | R8: =IF(OR(E8=1,AND(P8<=0,I8>0)),1,0) -> 0 | S8: =IF(L8>0,1,0) -> 0
A9: 8 | B9: =INT((A9-1)/12)+1 -> 1 | C9: =MIN(Inputs!$C$4+B9-1,99) -> 74 | D9: =0.08 -> 0.08 | E9: =R8 -> 0 | F9: =Q8 -> 25503.002 | G9: =IF(AND(MOD(A9-1,12)=0,B9<=Inputs!$C$7,E9=0),Inputs!$C$6,0) -> 0 | H9: =IF(B9=1,G9*Inputs!$C$9,0) -> 0 | I9: =I8+G9 -> 24000 | J9: =(F9+G9+H9)*((1+D9)^(1/12)-1) -> 164.08708 | K9: =(F9+G9+H9+J9)*(Inputs!$C$19+IF(B9<=10,Inputs!$C$12,Inputs!$C$13))/12 -> 85.556964 | L9: =IF(OR(E9=1,A9<=Inputs!$C$15),0,MAX(Inputs!$C$8*I9-(F9+G9+H9+J9-K9),0)) -> 0 | M9: =L9*INDEX(Rates!$B$2:$C$101,C9+1,IF(Inputs!$C$5="Male",1,2))/1000/12*Inputs!$C$16 -> 0 | N9: =IF($V$1=1,MAX(F9+G9+H9+J9-K9-M9,0)*Inputs!$C$22/12,0) -> 0 | O9: =IF(AND(MOD(A9,12)=0,B9>=Inputs!$C$18),MAX(F9+G9+H9+J9-K9-M9-N9,0)*Inputs!$C$17,0) -> 0 | P9: =F9+G9+H9+J9-K9-M9-N9+O9 -> 25581.532 | Q9: =IF(OR(E9=1,P9<=0),0,P9) -> 25581.532 | R9: =IF(OR(E9=1,AND(P9<=0,I9>0)),1,0) -> 0 | S9: =IF(L9>0,1,0) -> 0
A10: 9 | B10: =INT((A10-1)/12)+1 -> 1 | C10: =MIN(Inputs!$C$4+B10-1,99) -> 74 | D10: =0.08 -> 0.08 | E10: =R9 -> 0 | F10: =Q9 -> 25581.532 | G10: =IF(AND(MOD(A10-1,12)=0,B10<=Inputs!$C$7,E10=0),Inputs!$C$6,0) -> 0 | H10: =IF(B10=1,G10*Inputs!$C$9,0) -> 0 | I10: =I9+G10 -> 24000 | J10: =(F10+G10+H10)*((1+D10)^(1/12)-1) -> 164.59235 | K10: =(F10+G10+H10+J10)*(Inputs!$C$19+IF(B10<=10,Inputs!$C$12,Inputs!$C$13))/12 -> 85.820415 | L10: =IF(OR(E10=1,A10<=Inputs!$C$15),0,MAX(Inputs!$C$8*I10-(F10+G10+H10+J10-K10),0)) -> 0 | M10: =L10*INDEX(Rates!$B$2:$C$101,C10+1,IF(Inputs!$C$5="Male",1,2))/1000/12*Inputs!$C$16 -> 0 | N10: =IF($V$1=1,MAX(F10+G10+H10+J10-K10-M10,0)*Inputs!$C$22/12,0) -> 0 | O10: =IF(AND(MOD(A10,12)=0,B10>=Inputs!$C$18),MAX(F10+G10+H10+J10-K10-M10-N10,0)*Inputs!$C$17,0) -> 0 | P10: =F10+G10+H10+J10-K10-M10-N10+O10 -> 25660.304 | Q10: =IF(OR(E10=1,P10<=0),0,P10) -> 25660.304 | R10: =IF(OR(E10=1,AND(P10<=0,I10>0)),1,0) -> 0 | S10: =IF(L10>0,1,0) -> 0
A11: 10 | B11: =INT((A11-1)/12)+1 -> 1 | C11: =MIN(Inputs!$C$4+B11-1,99) -> 74 | D11: =0.08 -> 0.08 | E11: =R10 -> 0 | F11: =Q10 -> 25660.304 | G11: =IF(AND(MOD(A11-1,12)=0,B11<=Inputs!$C$7,E11=0),Inputs!$C$6,0) -> 0 | H11: =IF(B11=1,G11*Inputs!$C$9,0) -> 0 | I11: =I10+G11 -> 24000 | J11: =(F11+G11+H11)*((1+D11)^(1/12)-1) -> 165.09917 | K11: =(F11+G11+H11+J11)*(Inputs!$C$19+IF(B11<=10,Inputs!$C$12,Inputs!$C$13))/12 -> 86.084678 | L11: =IF(OR(E11=1,A11<=Inputs!$C$15),0,MAX(Inputs!$C$8*I11-(F11+G11+H11+J11-K11),0)) -> 0 | M11: =L11*INDEX(Rates!$B$2:$C$101,C11+1,IF(Inputs!$C$5="Male",1,2))/1000/12*Inputs!$C$16 -> 0 | N11: =IF($V$1=1,MAX(F11+G11+H11+J11-K11-M11,0)*Inputs!$C$22/12,0) -> 0 | O11: =IF(AND(MOD(A11,12)=0,B11>=Inputs!$C$18),MAX(F11+G11+H11+J11-K11-M11-N11,0)*Inputs!$C$17,0) -> 0 | P11: =F11+G11+H11+J11-K11-M11-N11+O11 -> 25739.319 | Q11: =IF(OR(E11=1,P11<=0),0,P11) -> 25739.319 | R11: =IF(OR(E11=1,AND(P11<=0,I11>0)),1,0) -> 0 | S11: =IF(L11>0,1,0) -> 0
A12: 11 | B12: =INT((A12-1)/12)+1 -> 1 | C12: =MIN(Inputs!$C$4+B12-1,99) -> 74 | D12: =0.08 -> 0.08 | E12: =R11 -> 0 | F12: =Q11 -> 25739.319 | G12: =IF(AND(MOD(A12-1,12)=0,B12<=Inputs!$C$7,E12=0),Inputs!$C$6,0) -> 0 | H12: =IF(B12=1,G12*Inputs!$C$9,0) -> 0 | I12: =I11+G12 -> 24000 | J12: =(F12+G12+H12)*((1+D12)^(1/12)-1) -> 165.60755 | K12: =(F12+G12+H12+J12)*(Inputs!$C$19+IF(B12<=10,Inputs!$C$12,Inputs!$C$13))/12 -> 86.349754 | L12: =IF(OR(E12=1,A12<=Inputs!$C$15),0,MAX(Inputs!$C$8*I12-(F12+G12+H12+J12-K12),0)) -> 0 | M12: =L12*INDEX(Rates!$B$2:$C$101,C12+1,IF(Inputs!$C$5="Male",1,2))/1000/12*Inputs!$C$16 -> 0 | N12: =IF($V$1=1,MAX(F12+G12+H12+J12-K12-M12,0)*Inputs!$C$22/12,0) -> 0 | O12: =IF(AND(MOD(A12,12)=0,B12>=Inputs!$C$18),MAX(F12+G12+H12+J12-K12-M12-N12,0)*Inputs!$C$17,0) -> 0 | P12: =F12+G12+H12+J12-K12-M12-N12+O12 -> 25818.576 | Q12: =IF(OR(E12=1,P12<=0),0,P12) -> 25818.576 | R12: =IF(OR(E12=1,AND(P12<=0,I12>0)),1,0) -> 0 | S12: =IF(L12>0,1,0) -> 0
A13: 12 | B13: =INT((A13-1)/12)+1 -> 1 | C13: =MIN(Inputs!$C$4+B13-1,99) -> 74 | D13: =0.08 -> 0.08 | E13: =R12 -> 0 | F13: =Q12 -> 25818.576 | G13: =IF(AND(MOD(A13-1,12)=0,B13<=Inputs!$C$7,E13=0),Inputs!$C$6,0) -> 0 | H13: =IF(B13=1,G13*Inputs!$C$9,0) -> 0 | I13: =I12+G13 -> 24000 | J13: =(F13+G13+H13)*((1+D13)^(1/12)-1) -> 166.1175 | K13: =(F13+G13+H13+J13)*(Inputs!$C$19+IF(B13<=10,Inputs!$C$12,Inputs!$C$13))/12 -> 86.615647 | L13: =IF(OR(E13=1,A13<=Inputs!$C$15),0,MAX(Inputs!$C$8*I13-(F13+G13+H13+J13-K13),0)) -> 0 | M13: =L13*INDEX(Rates!$B$2:$C$101,C13+1,IF(Inputs!$C$5="Male",1,2))/1000/12*Inputs!$C$16 -> 0 | N13: =IF($V$1=1,MAX(F13+G13+H13+J13-K13-M13,0)*Inputs!$C$22/12,0) -> 0 | O13: =IF(AND(MOD(A13,12)=0,B13>=Inputs!$C$18),MAX(F13+G13+H13+J13-K13-M13-N13,0)*Inputs!$C$17,0) -> 0 | P13: =F13+G13+H13+J13-K13-M13-N13+O13 -> 25898.078 | Q13: =IF(OR(E13=1,P13<=0),0,P13) -> 25898.078 | R13: =IF(OR(E13=1,AND(P13<=0,I13>0)),1,0) -> 0 | S13: =IF(L13>0,1,0) -> 0
A14: 13 | B14: =INT((A14-1)/12)+1 -> 2 | C14: =MIN(Inputs!$C$4+B14-1,99) -> 75 | D14: =0.08 -> 0.08 | E14: =R13 -> 0 | F14: =Q13 -> 25898.078 | G14: =IF(AND(MOD(A14-1,12)=0,B14<=Inputs!$C$7,E14=0),Inputs!$C$6,0) -> 24000 | H14: =IF(B14=1,G14*Inputs!$C$9,0) -> 0 | I14: =I13+G14 -> 48000 | J14: =(F14+G14+H14)*((1+D14)^(1/12)-1) -> 321.04574 | K14: =(F14+G14+H14+J14)*(Inputs!$C$19+IF(B14<=10,Inputs!$C$12,Inputs!$C$13))/12 -> 167.39708 | L14: =IF(OR(E14=1,A14<=Inputs!$C$15),0,MAX(Inputs!$C$8*I14-(F14+G14+H14+J14-K14),0)) -> 0 | M14: =L14*INDEX(Rates!$B$2:$C$101,C14+1,IF(Inputs!$C$5="Male",1,2))/1000/12*Inputs!$C$16 -> 0 | N14: =IF($V$1=1,MAX(F14+G14+H14+J14-K14-M14,0)*Inputs!$C$22/12,0) -> 0 | O14: =IF(AND(MOD(A14,12)=0,B14>=Inputs!$C$18),MAX(F14+G14+H14+J14-K14-M14-N14,0)*Inputs!$C$17,0) -> 0 | P14: =F14+G14+H14+J14-K14-M14-N14+O14 -> 50051.727 | Q14: =IF(OR(E14=1,P14<=0),0,P14) -> 50051.727 | R14: =IF(OR(E14=1,AND(P14<=0,I14>0)),1,0) -> 0 | S14: =IF(L14>0,1,0) -> 0
... A301: 300 | B301: =INT((A301-1)/12)+1 -> 25 | C301: =MIN(Inputs!$C$4+B301-1,99) -> 98 | D301: =0.08 -> 0.08 | E301: =R300 -> 0 | F301: =Q300 -> 404180.43 | G301: =IF(AND(MOD(A301-1,12)=0,B301<=Inputs!$C$7,E301=0),Inputs!$C$6,0) -> 0 | H301: =IF(B301=1,G301*Inputs!$C$9,0) -> 0 | I301: =I300+G301 -> 120000 | J301: =(F301+G301+H301)*((1+D301)^(1/12)-1) -> 2600.509 | K301: =(F301+G301+H301+J301)*(Inputs!$C$19+IF(B301<=10,Inputs!$C$12,Inputs!$C$13))/12 -> 711.86664 | L301: =IF(OR(E301=1,A301<=Inputs!$C$15),0,MAX(Inputs!$C$8*I301-(F301+G301+H301+J301-K301),0)) -> 0 | M301: =L301*INDEX(Rates!$B$2:$C$101,C301+1,IF(Inputs!$C$5="Male",1,2))/1000/12*Inputs!$C$16 -> 0 | N301: =IF($V$1=1,MAX(F301+G301+H301+J301-K301-M301,0)*Inputs!$C$22/12,0) -> 0 | O301: =IF(AND(MOD(A301,12)=0,B301>=Inputs!$C$18),MAX(F301+G301+H301+J301-K301-M301-N301,0)*Inputs!$C$17,0) -> 2030.3454 | P301: =F301+G301+H301+J301-K301-M301-N301+O301 -> 408099.42 | Q301: =IF(OR(E301=1,P301<=0),0,P301) -> 408099.42 | R301: =IF(OR(E301=1,AND(P301<=0,I301>0)),1,0) -> 0 | S301: =IF(L301>0,1,0) -> 0

Sheet S1_R
A1: Month | B1: Policy year | C1: Age (last b'day) | D1: Gross return p.a. | E1: Lapsed before? | F1: Policy value b/f | G1: Premium | H1: Investment bonus | I1: Net premiums to date | J1: Investment growth | K1: Policy fee + mgmt fee | L1: Sum at risk (charged) | M1: Insurance charge (COI) | N1: Dividend paid out | O1: Loyalty bonus | P1: PV before floor | Q1: Policy value c/f | R1: Lapsed? | S1: SAR>0 flag | U1: Dividend payout on? (1/0) | V1: 0
A2: 1 | B2: =INT((A2-1)/12)+1 -> 1 | C2: =MIN(Inputs!$C$4+B2-1,99) -> 74 | D2: =Inputs!$C$25 -> 0.02 | E2: 0 | F2: 0 | G2: =IF(AND(MOD(A2-1,12)=0,B2<=Inputs!$C$7,E2=0),Inputs!$C$6,0) -> 24000 | H2: =IF(B2=1,G2*Inputs!$C$9,0) -> 960 | I2: =G2 -> 24000 | J2: =(F2+G2+H2)*((1+D2)^(1/12)-1) -> 41.223469 | K2: =(F2+G2+H2+J2)*(Inputs!$C$14+IF(B2<=10,Inputs!$C$12,Inputs!$C$13))/12 -> 52.085882 | L2: =IF(OR(E2=1,A2<=Inputs!$C$15),0,MAX(Inputs!$C$8*I2-(F2+G2+H2+J2-K2),0)) -> 0 | M2: =L2*INDEX(Rates!$B$2:$C$101,C2+1,IF(Inputs!$C$5="Male",1,2))/1000/12*Inputs!$C$16 -> 0 | N2: =IF($V$1=1,MAX(F2+G2+H2+J2-K2-M2,0)*Inputs!$C$22/12,0) -> 0 | O2: =IF(AND(MOD(A2,12)=0,B2>=Inputs!$C$18),MAX(F2+G2+H2+J2-K2-M2-N2,0)*Inputs!$C$17,0) -> 0 | P2: =F2+G2+H2+J2-K2-M2-N2+O2 -> 24949.138 | Q2: =IF(OR(E2=1,P2<=0),0,P2) -> 24949.138 | R2: =IF(OR(E2=1,AND(P2<=0,I2>0)),1,0) -> 0 | S2: =IF(L2>0,1,0) -> 0 | U2: Sensitivity 1 reinvest
A3: 2 | B3: =INT((A3-1)/12)+1 -> 1 | C3: =MIN(Inputs!$C$4+B3-1,99) -> 74 | D3: =Inputs!$C$25 -> 0.02 | E3: =R2 -> 0 | F3: =Q2 -> 24949.138 | G3: =IF(AND(MOD(A3-1,12)=0,B3<=Inputs!$C$7,E3=0),Inputs!$C$6,0) -> 0 | H3: =IF(B3=1,G3*Inputs!$C$9,0) -> 0 | I3: =I2+G3 -> 24000 | J3: =(F3+G3+H3)*((1+D3)^(1/12)-1) -> 41.205529 | K3: =(F3+G3+H3+J3)*(Inputs!$C$14+IF(B3<=10,Inputs!$C$12,Inputs!$C$13))/12 -> 52.063215 | L3: =IF(OR(E3=1,A3<=Inputs!$C$15),0,MAX(Inputs!$C$8*I3-(F3+G3+H3+J3-K3),0)) -> 0 | M3: =L3*INDEX(Rates!$B$2:$C$101,C3+1,IF(Inputs!$C$5="Male",1,2))/1000/12*Inputs!$C$16 -> 0 | N3: =IF($V$1=1,MAX(F3+G3+H3+J3-K3-M3,0)*Inputs!$C$22/12,0) -> 0 | O3: =IF(AND(MOD(A3,12)=0,B3>=Inputs!$C$18),MAX(F3+G3+H3+J3-K3-M3-N3,0)*Inputs!$C$17,0) -> 0 | P3: =F3+G3+H3+J3-K3-M3-N3+O3 -> 24938.28 | Q3: =IF(OR(E3=1,P3<=0),0,P3) -> 24938.28 | R3: =IF(OR(E3=1,AND(P3<=0,I3>0)),1,0) -> 0 | S3: =IF(L3>0,1,0) -> 0
A4: 3 | B4: =INT((A4-1)/12)+1 -> 1 | C4: =MIN(Inputs!$C$4+B4-1,99) -> 74 | D4: =Inputs!$C$25 -> 0.02 | E4: =R3 -> 0 | F4: =Q3 -> 24938.28 | G4: =IF(AND(MOD(A4-1,12)=0,B4<=Inputs!$C$7,E4=0),Inputs!$C$6,0) -> 0 | H4: =IF(B4=1,G4*Inputs!$C$9,0) -> 0 | I4: =I3+G4 -> 24000 | J4: =(F4+G4+H4)*((1+D4)^(1/12)-1) -> 41.187597 | K4: =(F4+G4+H4+J4)*(Inputs!$C$14+IF(B4<=10,Inputs!$C$12,Inputs!$C$13))/12 -> 52.040557 | L4: =IF(OR(E4=1,A4<=Inputs!$C$15),0,MAX(Inputs!$C$8*I4-(F4+G4+H4+J4-K4),0)) -> 0 | M4: =L4*INDEX(Rates!$B$2:$C$101,C4+1,IF(Inputs!$C$5="Male",1,2))/1000/12*Inputs!$C$16 -> 0 | N4: =IF($V$1=1,MAX(F4+G4+H4+J4-K4-M4,0)*Inputs!$C$22/12,0) -> 0 | O4: =IF(AND(MOD(A4,12)=0,B4>=Inputs!$C$18),MAX(F4+G4+H4+J4-K4-M4-N4,0)*Inputs!$C$17,0) -> 0 | P4: =F4+G4+H4+J4-K4-M4-N4+O4 -> 24927.427 | Q4: =IF(OR(E4=1,P4<=0),0,P4) -> 24927.427 | R4: =IF(OR(E4=1,AND(P4<=0,I4>0)),1,0) -> 0 | S4: =IF(L4>0,1,0) -> 0
A5: 4 | B5: =INT((A5-1)/12)+1 -> 1 | C5: =MIN(Inputs!$C$4+B5-1,99) -> 74 | D5: =Inputs!$C$25 -> 0.02 | E5: =R4 -> 0 | F5: =Q4 -> 24927.427 | G5: =IF(AND(MOD(A5-1,12)=0,B5<=Inputs!$C$7,E5=0),Inputs!$C$6,0) -> 0 | H5: =IF(B5=1,G5*Inputs!$C$9,0) -> 0 | I5: =I4+G5 -> 24000 | J5: =(F5+G5+H5)*((1+D5)^(1/12)-1) -> 41.169672 | K5: =(F5+G5+H5+J5)*(Inputs!$C$14+IF(B5<=10,Inputs!$C$12,Inputs!$C$13))/12 -> 52.01791 | L5: =IF(OR(E5=1,A5<=Inputs!$C$15),0,MAX(Inputs!$C$8*I5-(F5+G5+H5+J5-K5),0)) -> 0 | M5: =L5*INDEX(Rates!$B$2:$C$101,C5+1,IF(Inputs!$C$5="Male",1,2))/1000/12*Inputs!$C$16 -> 0 | N5: =IF($V$1=1,MAX(F5+G5+H5+J5-K5-M5,0)*Inputs!$C$22/12,0) -> 0 | O5: =IF(AND(MOD(A5,12)=0,B5>=Inputs!$C$18),MAX(F5+G5+H5+J5-K5-M5-N5,0)*Inputs!$C$17,0) -> 0 | P5: =F5+G5+H5+J5-K5-M5-N5+O5 -> 24916.579 | Q5: =IF(OR(E5=1,P5<=0),0,P5) -> 24916.579 | R5: =IF(OR(E5=1,AND(P5<=0,I5>0)),1,0) -> 0 | S5: =IF(L5>0,1,0) -> 0
A6: 5 | B6: =INT((A6-1)/12)+1 -> 1 | C6: =MIN(Inputs!$C$4+B6-1,99) -> 74 | D6: =Inputs!$C$25 -> 0.02 | E6: =R5 -> 0 | F6: =Q5 -> 24916.579 | G6: =IF(AND(MOD(A6-1,12)=0,B6<=Inputs!$C$7,E6=0),Inputs!$C$6,0) -> 0 | H6: =IF(B6=1,G6*Inputs!$C$9,0) -> 0 | I6: =I5+G6 -> 24000 | J6: =(F6+G6+H6)*((1+D6)^(1/12)-1) -> 41.151755 | K6: =(F6+G6+H6+J6)*(Inputs!$C$14+IF(B6<=10,Inputs!$C$12,Inputs!$C$13))/12 -> 51.995272 | L6: =IF(OR(E6=1,A6<=Inputs!$C$15),0,MAX(Inputs!$C$8*I6-(F6+G6+H6+J6-K6),0)) -> 0 | M6: =L6*INDEX(Rates!$B$2:$C$101,C6+1,IF(Inputs!$C$5="Male",1,2))/1000/12*Inputs!$C$16 -> 0 | N6: =IF($V$1=1,MAX(F6+G6+H6+J6-K6-M6,0)*Inputs!$C$22/12,0) -> 0 | O6: =IF(AND(MOD(A6,12)=0,B6>=Inputs!$C$18),MAX(F6+G6+H6+J6-K6-M6-N6,0)*Inputs!$C$17,0) -> 0 | P6: =F6+G6+H6+J6-K6-M6-N6+O6 -> 24905.735 | Q6: =IF(OR(E6=1,P6<=0),0,P6) -> 24905.735 | R6: =IF(OR(E6=1,AND(P6<=0,I6>0)),1,0) -> 0 | S6: =IF(L6>0,1,0) -> 0
A7: 6 | B7: =INT((A7-1)/12)+1 -> 1 | C7: =MIN(Inputs!$C$4+B7-1,99) -> 74 | D7: =Inputs!$C$25 -> 0.02 | E7: =R6 -> 0 | F7: =Q6 -> 24905.735 | G7: =IF(AND(MOD(A7-1,12)=0,B7<=Inputs!$C$7,E7=0),Inputs!$C$6,0) -> 0 | H7: =IF(B7=1,G7*Inputs!$C$9,0) -> 0 | I7: =I6+G7 -> 24000 | J7: =(F7+G7+H7)*((1+D7)^(1/12)-1) -> 41.133847 | K7: =(F7+G7+H7+J7)*(Inputs!$C$14+IF(B7<=10,Inputs!$C$12,Inputs!$C$13))/12 -> 51.972644 | L7: =IF(OR(E7=1,A7<=Inputs!$C$15),0,MAX(Inputs!$C$8*I7-(F7+G7+H7+J7-K7),0)) -> 0 | M7: =L7*INDEX(Rates!$B$2:$C$101,C7+1,IF(Inputs!$C$5="Male",1,2))/1000/12*Inputs!$C$16 -> 0 | N7: =IF($V$1=1,MAX(F7+G7+H7+J7-K7-M7,0)*Inputs!$C$22/12,0) -> 0 | O7: =IF(AND(MOD(A7,12)=0,B7>=Inputs!$C$18),MAX(F7+G7+H7+J7-K7-M7-N7,0)*Inputs!$C$17,0) -> 0 | P7: =F7+G7+H7+J7-K7-M7-N7+O7 -> 24894.896 | Q7: =IF(OR(E7=1,P7<=0),0,P7) -> 24894.896 | R7: =IF(OR(E7=1,AND(P7<=0,I7>0)),1,0) -> 0 | S7: =IF(L7>0,1,0) -> 0
A8: 7 | B8: =INT((A8-1)/12)+1 -> 1 | C8: =MIN(Inputs!$C$4+B8-1,99) -> 74 | D8: =Inputs!$C$25 -> 0.02 | E8: =R7 -> 0 | F8: =Q7 -> 24894.896 | G8: =IF(AND(MOD(A8-1,12)=0,B8<=Inputs!$C$7,E8=0),Inputs!$C$6,0) -> 0 | H8: =IF(B8=1,G8*Inputs!$C$9,0) -> 0 | I8: =I7+G8 -> 24000 | J8: =(F8+G8+H8)*((1+D8)^(1/12)-1) -> 41.115945 | K8: =(F8+G8+H8+J8)*(Inputs!$C$14+IF(B8<=10,Inputs!$C$12,Inputs!$C$13))/12 -> 51.950026 | L8: =IF(OR(E8=1,A8<=Inputs!$C$15),0,MAX(Inputs!$C$8*I8-(F8+G8+H8+J8-K8),0)) -> 0 | M8: =L8*INDEX(Rates!$B$2:$C$101,C8+1,IF(Inputs!$C$5="Male",1,2))/1000/12*Inputs!$C$16 -> 0 | N8: =IF($V$1=1,MAX(F8+G8+H8+J8-K8-M8,0)*Inputs!$C$22/12,0) -> 0 | O8: =IF(AND(MOD(A8,12)=0,B8>=Inputs!$C$18),MAX(F8+G8+H8+J8-K8-M8-N8,0)*Inputs!$C$17,0) -> 0 | P8: =F8+G8+H8+J8-K8-M8-N8+O8 -> 24884.062 | Q8: =IF(OR(E8=1,P8<=0),0,P8) -> 24884.062 | R8: =IF(OR(E8=1,AND(P8<=0,I8>0)),1,0) -> 0 | S8: =IF(L8>0,1,0) -> 0
A9: 8 | B9: =INT((A9-1)/12)+1 -> 1 | C9: =MIN(Inputs!$C$4+B9-1,99) -> 74 | D9: =Inputs!$C$25 -> 0.02 | E9: =R8 -> 0 | F9: =Q8 -> 24884.062 | G9: =IF(AND(MOD(A9-1,12)=0,B9<=Inputs!$C$7,E9=0),Inputs!$C$6,0) -> 0 | H9: =IF(B9=1,G9*Inputs!$C$9,0) -> 0 | I9: =I8+G9 -> 24000 | J9: =(F9+G9+H9)*((1+D9)^(1/12)-1) -> 41.098052 | K9: =(F9+G9+H9+J9)*(Inputs!$C$14+IF(B9<=10,Inputs!$C$12,Inputs!$C$13))/12 -> 51.927417 | L9: =IF(OR(E9=1,A9<=Inputs!$C$15),0,MAX(Inputs!$C$8*I9-(F9+G9+H9+J9-K9),0)) -> 0 | M9: =L9*INDEX(Rates!$B$2:$C$101,C9+1,IF(Inputs!$C$5="Male",1,2))/1000/12*Inputs!$C$16 -> 0 | N9: =IF($V$1=1,MAX(F9+G9+H9+J9-K9-M9,0)*Inputs!$C$22/12,0) -> 0 | O9: =IF(AND(MOD(A9,12)=0,B9>=Inputs!$C$18),MAX(F9+G9+H9+J9-K9-M9-N9,0)*Inputs!$C$17,0) -> 0 | P9: =F9+G9+H9+J9-K9-M9-N9+O9 -> 24873.233 | Q9: =IF(OR(E9=1,P9<=0),0,P9) -> 24873.233 | R9: =IF(OR(E9=1,AND(P9<=0,I9>0)),1,0) -> 0 | S9: =IF(L9>0,1,0) -> 0
A10: 9 | B10: =INT((A10-1)/12)+1 -> 1 | C10: =MIN(Inputs!$C$4+B10-1,99) -> 74 | D10: =Inputs!$C$25 -> 0.02 | E10: =R9 -> 0 | F10: =Q9 -> 24873.233 | G10: =IF(AND(MOD(A10-1,12)=0,B10<=Inputs!$C$7,E10=0),Inputs!$C$6,0) -> 0 | H10: =IF(B10=1,G10*Inputs!$C$9,0) -> 0 | I10: =I9+G10 -> 24000 | J10: =(F10+G10+H10)*((1+D10)^(1/12)-1) -> 41.080166 | K10: =(F10+G10+H10+J10)*(Inputs!$C$14+IF(B10<=10,Inputs!$C$12,Inputs!$C$13))/12 -> 51.904819 | L10: =IF(OR(E10=1,A10<=Inputs!$C$15),0,MAX(Inputs!$C$8*I10-(F10+G10+H10+J10-K10),0)) -> 0 | M10: =L10*INDEX(Rates!$B$2:$C$101,C10+1,IF(Inputs!$C$5="Male",1,2))/1000/12*Inputs!$C$16 -> 0 | N10: =IF($V$1=1,MAX(F10+G10+H10+J10-K10-M10,0)*Inputs!$C$22/12,0) -> 0 | O10: =IF(AND(MOD(A10,12)=0,B10>=Inputs!$C$18),MAX(F10+G10+H10+J10-K10-M10-N10,0)*Inputs!$C$17,0) -> 0 | P10: =F10+G10+H10+J10-K10-M10-N10+O10 -> 24862.408 | Q10: =IF(OR(E10=1,P10<=0),0,P10) -> 24862.408 | R10: =IF(OR(E10=1,AND(P10<=0,I10>0)),1,0) -> 0 | S10: =IF(L10>0,1,0) -> 0
A11: 10 | B11: =INT((A11-1)/12)+1 -> 1 | C11: =MIN(Inputs!$C$4+B11-1,99) -> 74 | D11: =Inputs!$C$25 -> 0.02 | E11: =R10 -> 0 | F11: =Q10 -> 24862.408 | G11: =IF(AND(MOD(A11-1,12)=0,B11<=Inputs!$C$7,E11=0),Inputs!$C$6,0) -> 0 | H11: =IF(B11=1,G11*Inputs!$C$9,0) -> 0 | I11: =I10+G11 -> 24000 | J11: =(F11+G11+H11)*((1+D11)^(1/12)-1) -> 41.062289 | K11: =(F11+G11+H11+J11)*(Inputs!$C$14+IF(B11<=10,Inputs!$C$12,Inputs!$C$13))/12 -> 51.88223 | L11: =IF(OR(E11=1,A11<=Inputs!$C$15),0,MAX(Inputs!$C$8*I11-(F11+G11+H11+J11-K11),0)) -> 0 | M11: =L11*INDEX(Rates!$B$2:$C$101,C11+1,IF(Inputs!$C$5="Male",1,2))/1000/12*Inputs!$C$16 -> 0 | N11: =IF($V$1=1,MAX(F11+G11+H11+J11-K11-M11,0)*Inputs!$C$22/12,0) -> 0 | O11: =IF(AND(MOD(A11,12)=0,B11>=Inputs!$C$18),MAX(F11+G11+H11+J11-K11-M11-N11,0)*Inputs!$C$17,0) -> 0 | P11: =F11+G11+H11+J11-K11-M11-N11+O11 -> 24851.588 | Q11: =IF(OR(E11=1,P11<=0),0,P11) -> 24851.588 | R11: =IF(OR(E11=1,AND(P11<=0,I11>0)),1,0) -> 0 | S11: =IF(L11>0,1,0) -> 0
A12: 11 | B12: =INT((A12-1)/12)+1 -> 1 | C12: =MIN(Inputs!$C$4+B12-1,99) -> 74 | D12: =Inputs!$C$25 -> 0.02 | E12: =R11 -> 0 | F12: =Q11 -> 24851.588 | G12: =IF(AND(MOD(A12-1,12)=0,B12<=Inputs!$C$7,E12=0),Inputs!$C$6,0) -> 0 | H12: =IF(B12=1,G12*Inputs!$C$9,0) -> 0 | I12: =I11+G12 -> 24000 | J12: =(F12+G12+H12)*((1+D12)^(1/12)-1) -> 41.044419 | K12: =(F12+G12+H12+J12)*(Inputs!$C$14+IF(B12<=10,Inputs!$C$12,Inputs!$C$13))/12 -> 51.859652 | L12: =IF(OR(E12=1,A12<=Inputs!$C$15),0,MAX(Inputs!$C$8*I12-(F12+G12+H12+J12-K12),0)) -> 0 | M12: =L12*INDEX(Rates!$B$2:$C$101,C12+1,IF(Inputs!$C$5="Male",1,2))/1000/12*Inputs!$C$16 -> 0 | N12: =IF($V$1=1,MAX(F12+G12+H12+J12-K12-M12,0)*Inputs!$C$22/12,0) -> 0 | O12: =IF(AND(MOD(A12,12)=0,B12>=Inputs!$C$18),MAX(F12+G12+H12+J12-K12-M12-N12,0)*Inputs!$C$17,0) -> 0 | P12: =F12+G12+H12+J12-K12-M12-N12+O12 -> 24840.773 | Q12: =IF(OR(E12=1,P12<=0),0,P12) -> 24840.773 | R12: =IF(OR(E12=1,AND(P12<=0,I12>0)),1,0) -> 0 | S12: =IF(L12>0,1,0) -> 0
A13: 12 | B13: =INT((A13-1)/12)+1 -> 1 | C13: =MIN(Inputs!$C$4+B13-1,99) -> 74 | D13: =Inputs!$C$25 -> 0.02 | E13: =R12 -> 0 | F13: =Q12 -> 24840.773 | G13: =IF(AND(MOD(A13-1,12)=0,B13<=Inputs!$C$7,E13=0),Inputs!$C$6,0) -> 0 | H13: =IF(B13=1,G13*Inputs!$C$9,0) -> 0 | I13: =I12+G13 -> 24000 | J13: =(F13+G13+H13)*((1+D13)^(1/12)-1) -> 41.026556 | K13: =(F13+G13+H13+J13)*(Inputs!$C$14+IF(B13<=10,Inputs!$C$12,Inputs!$C$13))/12 -> 51.837083 | L13: =IF(OR(E13=1,A13<=Inputs!$C$15),0,MAX(Inputs!$C$8*I13-(F13+G13+H13+J13-K13),0)) -> 0 | M13: =L13*INDEX(Rates!$B$2:$C$101,C13+1,IF(Inputs!$C$5="Male",1,2))/1000/12*Inputs!$C$16 -> 0 | N13: =IF($V$1=1,MAX(F13+G13+H13+J13-K13-M13,0)*Inputs!$C$22/12,0) -> 0 | O13: =IF(AND(MOD(A13,12)=0,B13>=Inputs!$C$18),MAX(F13+G13+H13+J13-K13-M13-N13,0)*Inputs!$C$17,0) -> 0 | P13: =F13+G13+H13+J13-K13-M13-N13+O13 -> 24829.963 | Q13: =IF(OR(E13=1,P13<=0),0,P13) -> 24829.963 | R13: =IF(OR(E13=1,AND(P13<=0,I13>0)),1,0) -> 0 | S13: =IF(L13>0,1,0) -> 0
A14: 13 | B14: =INT((A14-1)/12)+1 -> 2 | C14: =MIN(Inputs!$C$4+B14-1,99) -> 75 | D14: =Inputs!$C$25 -> 0.02 | E14: =R13 -> 0 | F14: =Q13 -> 24829.963 | G14: =IF(AND(MOD(A14-1,12)=0,B14<=Inputs!$C$7,E14=0),Inputs!$C$6,0) -> 24000 | H14: =IF(B14=1,G14*Inputs!$C$9,0) -> 0 | I14: =I13+G14 -> 48000 | J14: =(F14+G14+H14)*((1+D14)^(1/12)-1) -> 80.646653 | K14: =(F14+G14+H14+J14)*(Inputs!$C$14+IF(B14<=10,Inputs!$C$12,Inputs!$C$13))/12 -> 101.8971 | L14: =IF(OR(E14=1,A14<=Inputs!$C$15),0,MAX(Inputs!$C$8*I14-(F14+G14+H14+J14-K14),0)) -> 0 | M14: =L14*INDEX(Rates!$B$2:$C$101,C14+1,IF(Inputs!$C$5="Male",1,2))/1000/12*Inputs!$C$16 -> 0 | N14: =IF($V$1=1,MAX(F14+G14+H14+J14-K14-M14,0)*Inputs!$C$22/12,0) -> 0 | O14: =IF(AND(MOD(A14,12)=0,B14>=Inputs!$C$18),MAX(F14+G14+H14+J14-K14-M14-N14,0)*Inputs!$C$17,0) -> 0 | P14: =F14+G14+H14+J14-K14-M14-N14+O14 -> 48808.712 | Q14: =IF(OR(E14=1,P14<=0),0,P14) -> 48808.712 | R14: =IF(OR(E14=1,AND(P14<=0,I14>0)),1,0) -> 0 | S14: =IF(L14>0,1,0) -> 0
... A301: 300 | B301: =INT((A301-1)/12)+1 -> 25 | C301: =MIN(Inputs!$C$4+B301-1,99) -> 98 | D301: =Inputs!$C$25 -> 0.02 | E301: =R300 -> 0 | F301: =Q300 -> 150482.65 | G301: =IF(AND(MOD(A301-1,12)=0,B301<=Inputs!$C$7,E301=0),Inputs!$C$6,0) -> 0 | H301: =IF(B301=1,G301*Inputs!$C$9,0) -> 0 | I301: =I300+G301 -> 120000 | J301: =(F301+G301+H301)*((1+D301)^(1/12)-1) -> 248.53433 | K301: =(F301+G301+H301+J301)*(Inputs!$C$14+IF(B301<=10,Inputs!$C$12,Inputs!$C$13))/12 -> 75.365593 | L301: =IF(OR(E301=1,A301<=Inputs!$C$15),0,MAX(Inputs!$C$8*I301-(F301+G301+H301+J301-K301),0)) -> 0 | M301: =L301*INDEX(Rates!$B$2:$C$101,C301+1,IF(Inputs!$C$5="Male",1,2))/1000/12*Inputs!$C$16 -> 0 | N301: =IF($V$1=1,MAX(F301+G301+H301+J301-K301-M301,0)*Inputs!$C$22/12,0) -> 0 | O301: =IF(AND(MOD(A301,12)=0,B301>=Inputs!$C$18),MAX(F301+G301+H301+J301-K301-M301-N301,0)*Inputs!$C$17,0) -> 753.2791 | P301: =F301+G301+H301+J301-K301-M301-N301+O301 -> 151409.1 | Q301: =IF(OR(E301=1,P301<=0),0,P301) -> 151409.1 | R301: =IF(OR(E301=1,AND(P301<=0,I301>0)),1,0) -> 0 | S301: =IF(L301>0,1,0) -> 0

Sheet S1_P
A1: Month | B1: Policy year | C1: Age (last b'day) | D1: Gross return p.a. | E1: Lapsed before? | F1: Policy value b/f | G1: Premium | H1: Investment bonus | I1: Net premiums to date | J1: Investment growth | K1: Policy fee + mgmt fee | L1: Sum at risk (charged) | M1: Insurance charge (COI) | N1: Dividend paid out | O1: Loyalty bonus | P1: PV before floor | Q1: Policy value c/f | R1: Lapsed? | S1: SAR>0 flag | U1: Dividend payout on? (1/0) | V1: 1
A2: 1 | B2: =INT((A2-1)/12)+1 -> 1 | C2: =MIN(Inputs!$C$4+B2-1,99) -> 74 | D2: =Inputs!$C$25 -> 0.02 | E2: 0 | F2: 0 | G2: =IF(AND(MOD(A2-1,12)=0,B2<=Inputs!$C$7,E2=0),Inputs!$C$6,0) -> 24000 | H2: =IF(B2=1,G2*Inputs!$C$9,0) -> 960 | I2: =G2 -> 24000 | J2: =(F2+G2+H2)*((1+D2)^(1/12)-1) -> 41.223469 | K2: =(F2+G2+H2+J2)*(Inputs!$C$14+IF(B2<=10,Inputs!$C$12,Inputs!$C$13))/12 -> 52.085882 | L2: =IF(OR(E2=1,A2<=Inputs!$C$15),0,MAX(Inputs!$C$8*I2-(F2+G2+H2+J2-K2),0)) -> 0 | M2: =L2*INDEX(Rates!$B$2:$C$101,C2+1,IF(Inputs!$C$5="Male",1,2))/1000/12*Inputs!$C$16 -> 0 | N2: =IF($V$1=1,MAX(F2+G2+H2+J2-K2-M2,0)*Inputs!$C$22/12,0) -> 166.32758 | O2: =IF(AND(MOD(A2,12)=0,B2>=Inputs!$C$18),MAX(F2+G2+H2+J2-K2-M2-N2,0)*Inputs!$C$17,0) -> 0 | P2: =F2+G2+H2+J2-K2-M2-N2+O2 -> 24782.81 | Q2: =IF(OR(E2=1,P2<=0),0,P2) -> 24782.81 | R2: =IF(OR(E2=1,AND(P2<=0,I2>0)),1,0) -> 0 | S2: =IF(L2>0,1,0) -> 0 | U2: Sensitivity 1 payout
A3: 2 | B3: =INT((A3-1)/12)+1 -> 1 | C3: =MIN(Inputs!$C$4+B3-1,99) -> 74 | D3: =Inputs!$C$25 -> 0.02 | E3: =R2 -> 0 | F3: =Q2 -> 24782.81 | G3: =IF(AND(MOD(A3-1,12)=0,B3<=Inputs!$C$7,E3=0),Inputs!$C$6,0) -> 0 | H3: =IF(B3=1,G3*Inputs!$C$9,0) -> 0 | I3: =I2+G3 -> 24000 | J3: =(F3+G3+H3)*((1+D3)^(1/12)-1) -> 40.930826 | K3: =(F3+G3+H3+J3)*(Inputs!$C$14+IF(B3<=10,Inputs!$C$12,Inputs!$C$13))/12 -> 51.716127 | L3: =IF(OR(E3=1,A3<=Inputs!$C$15),0,MAX(Inputs!$C$8*I3-(F3+G3+H3+J3-K3),0)) -> 0 | M3: =L3*INDEX(Rates!$B$2:$C$101,C3+1,IF(Inputs!$C$5="Male",1,2))/1000/12*Inputs!$C$16 -> 0 | N3: =IF($V$1=1,MAX(F3+G3+H3+J3-K3-M3,0)*Inputs!$C$22/12,0) -> 165.14683 | O3: =IF(AND(MOD(A3,12)=0,B3>=Inputs!$C$18),MAX(F3+G3+H3+J3-K3-M3-N3,0)*Inputs!$C$17,0) -> 0 | P3: =F3+G3+H3+J3-K3-M3-N3+O3 -> 24606.878 | Q3: =IF(OR(E3=1,P3<=0),0,P3) -> 24606.878 | R3: =IF(OR(E3=1,AND(P3<=0,I3>0)),1,0) -> 0 | S3: =IF(L3>0,1,0) -> 0
A4: 3 | B4: =INT((A4-1)/12)+1 -> 1 | C4: =MIN(Inputs!$C$4+B4-1,99) -> 74 | D4: =Inputs!$C$25 -> 0.02 | E4: =R3 -> 0 | F4: =Q3 -> 24606.878 | G4: =IF(AND(MOD(A4-1,12)=0,B4<=Inputs!$C$7,E4=0),Inputs!$C$6,0) -> 0 | H4: =IF(B4=1,G4*Inputs!$C$9,0) -> 0 | I4: =I3+G4 -> 24000 | J4: =(F4+G4+H4)*((1+D4)^(1/12)-1) -> 40.640259 | K4: =(F4+G4+H4+J4)*(Inputs!$C$14+IF(B4<=10,Inputs!$C$12,Inputs!$C$13))/12 -> 51.348996 | L4: =IF(OR(E4=1,A4<=Inputs!$C$15),0,MAX(Inputs!$C$8*I4-(F4+G4+H4+J4-K4),0)) -> 0 | M4: =L4*INDEX(Rates!$B$2:$C$101,C4+1,IF(Inputs!$C$5="Male",1,2))/1000/12*Inputs!$C$16 -> 0 | N4: =IF($V$1=1,MAX(F4+G4+H4+J4-K4-M4,0)*Inputs!$C$22/12,0) -> 163.97446 | O4: =IF(AND(MOD(A4,12)=0,B4>=Inputs!$C$18),MAX(F4+G4+H4+J4-K4-M4-N4,0)*Inputs!$C$17,0) -> 0 | P4: =F4+G4+H4+J4-K4-M4-N4+O4 -> 24432.195 | Q4: =IF(OR(E4=1,P4<=0),0,P4) -> 24432.195 | R4: =IF(OR(E4=1,AND(P4<=0,I4>0)),1,0) -> 0 | S4: =IF(L4>0,1,0) -> 0
A5: 4 | B5: =INT((A5-1)/12)+1 -> 1 | C5: =MIN(Inputs!$C$4+B5-1,99) -> 74 | D5: =Inputs!$C$25 -> 0.02 | E5: =R4 -> 0 | F5: =Q4 -> 24432.195 | G5: =IF(AND(MOD(A5-1,12)=0,B5<=Inputs!$C$7,E5=0),Inputs!$C$6,0) -> 0 | H5: =IF(B5=1,G5*Inputs!$C$9,0) -> 0 | I5: =I4+G5 -> 24000 | J5: =(F5+G5+H5)*((1+D5)^(1/12)-1) -> 40.351756 | K5: =(F5+G5+H5+J5)*(Inputs!$C$14+IF(B5<=10,Inputs!$C$12,Inputs!$C$13))/12 -> 50.984472 | L5: =IF(OR(E5=1,A5<=Inputs!$C$15),0,MAX(Inputs!$C$8*I5-(F5+G5+H5+J5-K5),0)) -> 0 | M5: =L5*INDEX(Rates!$B$2:$C$101,C5+1,IF(Inputs!$C$5="Male",1,2))/1000/12*Inputs!$C$16 -> 0 | N5: =IF($V$1=1,MAX(F5+G5+H5+J5-K5-M5,0)*Inputs!$C$22/12,0) -> 162.81041 | O5: =IF(AND(MOD(A5,12)=0,B5>=Inputs!$C$18),MAX(F5+G5+H5+J5-K5-M5-N5,0)*Inputs!$C$17,0) -> 0 | P5: =F5+G5+H5+J5-K5-M5-N5+O5 -> 24258.752 | Q5: =IF(OR(E5=1,P5<=0),0,P5) -> 24258.752 | R5: =IF(OR(E5=1,AND(P5<=0,I5>0)),1,0) -> 0 | S5: =IF(L5>0,1,0) -> 0
A6: 5 | B6: =INT((A6-1)/12)+1 -> 1 | C6: =MIN(Inputs!$C$4+B6-1,99) -> 74 | D6: =Inputs!$C$25 -> 0.02 | E6: =R5 -> 0 | F6: =Q5 -> 24258.752 | G6: =IF(AND(MOD(A6-1,12)=0,B6<=Inputs!$C$7,E6=0),Inputs!$C$6,0) -> 0 | H6: =IF(B6=1,G6*Inputs!$C$9,0) -> 0 | I6: =I5+G6 -> 24000 | J6: =(F6+G6+H6)*((1+D6)^(1/12)-1) -> 40.0653 | K6: =(F6+G6+H6+J6)*(Inputs!$C$14+IF(B6<=10,Inputs!$C$12,Inputs!$C$13))/12 -> 50.622535 | L6: =IF(OR(E6=1,A6<=Inputs!$C$15),0,MAX(Inputs!$C$8*I6-(F6+G6+H6+J6-K6),0)) -> 0 | M6: =L6*INDEX(Rates!$B$2:$C$101,C6+1,IF(Inputs!$C$5="Male",1,2))/1000/12*Inputs!$C$16 -> 0 | N6: =IF($V$1=1,MAX(F6+G6+H6+J6-K6-M6,0)*Inputs!$C$22/12,0) -> 161.65463 | O6: =IF(AND(MOD(A6,12)=0,B6>=Inputs!$C$18),MAX(F6+G6+H6+J6-K6-M6-N6,0)*Inputs!$C$17,0) -> 0 | P6: =F6+G6+H6+J6-K6-M6-N6+O6 -> 24086.54 | Q6: =IF(OR(E6=1,P6<=0),0,P6) -> 24086.54 | R6: =IF(OR(E6=1,AND(P6<=0,I6>0)),1,0) -> 0 | S6: =IF(L6>0,1,0) -> 0
A7: 6 | B7: =INT((A7-1)/12)+1 -> 1 | C7: =MIN(Inputs!$C$4+B7-1,99) -> 74 | D7: =Inputs!$C$25 -> 0.02 | E7: =R6 -> 0 | F7: =Q6 -> 24086.54 | G7: =IF(AND(MOD(A7-1,12)=0,B7<=Inputs!$C$7,E7=0),Inputs!$C$6,0) -> 0 | H7: =IF(B7=1,G7*Inputs!$C$9,0) -> 0 | I7: =I6+G7 -> 24000 | J7: =(F7+G7+H7)*((1+D7)^(1/12)-1) -> 39.780879 | K7: =(F7+G7+H7+J7)*(Inputs!$C$14+IF(B7<=10,Inputs!$C$12,Inputs!$C$13))/12 -> 50.263168 | L7: =IF(OR(E7=1,A7<=Inputs!$C$15),0,MAX(Inputs!$C$8*I7-(F7+G7+H7+J7-K7),0)) -> 0 | M7: =L7*INDEX(Rates!$B$2:$C$101,C7+1,IF(Inputs!$C$5="Male",1,2))/1000/12*Inputs!$C$16 -> 0 | N7: =IF($V$1=1,MAX(F7+G7+H7+J7-K7-M7,0)*Inputs!$C$22/12,0) -> 160.50705 | O7: =IF(AND(MOD(A7,12)=0,B7>=Inputs!$C$18),MAX(F7+G7+H7+J7-K7-M7-N7,0)*Inputs!$C$17,0) -> 0 | P7: =F7+G7+H7+J7-K7-M7-N7+O7 -> 23915.55 | Q7: =IF(OR(E7=1,P7<=0),0,P7) -> 23915.55 | R7: =IF(OR(E7=1,AND(P7<=0,I7>0)),1,0) -> 0 | S7: =IF(L7>0,1,0) -> 0
A8: 7 | B8: =INT((A8-1)/12)+1 -> 1 | C8: =MIN(Inputs!$C$4+B8-1,99) -> 74 | D8: =Inputs!$C$25 -> 0.02 | E8: =R7 -> 0 | F8: =Q7 -> 23915.55 | G8: =IF(AND(MOD(A8-1,12)=0,B8<=Inputs!$C$7,E8=0),Inputs!$C$6,0) -> 0 | H8: =IF(B8=1,G8*Inputs!$C$9,0) -> 0 | I8: =I7+G8 -> 24000 | J8: =(F8+G8+H8)*((1+D8)^(1/12)-1) -> 39.498476 | K8: =(F8+G8+H8+J8)*(Inputs!$C$14+IF(B8<=10,Inputs!$C$12,Inputs!$C$13))/12 -> 49.906352 | L8: =IF(OR(E8=1,A8<=Inputs!$C$15),0,MAX(Inputs!$C$8*I8-(F8+G8+H8+J8-K8),0)) -> 0 | M8: =L8*INDEX(Rates!$B$2:$C$101,C8+1,IF(Inputs!$C$5="Male",1,2))/1000/12*Inputs!$C$16 -> 0 | N8: =IF($V$1=1,MAX(F8+G8+H8+J8-K8-M8,0)*Inputs!$C$22/12,0) -> 159.36762 | O8: =IF(AND(MOD(A8,12)=0,B8>=Inputs!$C$18),MAX(F8+G8+H8+J8-K8-M8-N8,0)*Inputs!$C$17,0) -> 0 | P8: =F8+G8+H8+J8-K8-M8-N8+O8 -> 23745.775 | Q8: =IF(OR(E8=1,P8<=0),0,P8) -> 23745.775 | R8: =IF(OR(E8=1,AND(P8<=0,I8>0)),1,0) -> 0 | S8: =IF(L8>0,1,0) -> 0
A9: 8 | B9: =INT((A9-1)/12)+1 -> 1 | C9: =MIN(Inputs!$C$4+B9-1,99) -> 74 | D9: =Inputs!$C$25 -> 0.02 | E9: =R8 -> 0 | F9: =Q8 -> 23745.775 | G9: =IF(AND(MOD(A9-1,12)=0,B9<=Inputs!$C$7,E9=0),Inputs!$C$6,0) -> 0 | H9: =IF(B9=1,G9*Inputs!$C$9,0) -> 0 | I9: =I8+G9 -> 24000 | J9: =(F9+G9+H9)*((1+D9)^(1/12)-1) -> 39.218078 | K9: =(F9+G9+H9+J9)*(Inputs!$C$14+IF(B9<=10,Inputs!$C$12,Inputs!$C$13))/12 -> 49.552069 | L9: =IF(OR(E9=1,A9<=Inputs!$C$15),0,MAX(Inputs!$C$8*I9-(F9+G9+H9+J9-K9),0)) -> 0 | M9: =L9*INDEX(Rates!$B$2:$C$101,C9+1,IF(Inputs!$C$5="Male",1,2))/1000/12*Inputs!$C$16 -> 0 | N9: =IF($V$1=1,MAX(F9+G9+H9+J9-K9-M9,0)*Inputs!$C$22/12,0) -> 158.23627 | O9: =IF(AND(MOD(A9,12)=0,B9>=Inputs!$C$18),MAX(F9+G9+H9+J9-K9-M9-N9,0)*Inputs!$C$17,0) -> 0 | P9: =F9+G9+H9+J9-K9-M9-N9+O9 -> 23577.205 | Q9: =IF(OR(E9=1,P9<=0),0,P9) -> 23577.205 | R9: =IF(OR(E9=1,AND(P9<=0,I9>0)),1,0) -> 0 | S9: =IF(L9>0,1,0) -> 0
A10: 9 | B10: =INT((A10-1)/12)+1 -> 1 | C10: =MIN(Inputs!$C$4+B10-1,99) -> 74 | D10: =Inputs!$C$25 -> 0.02 | E10: =R9 -> 0 | F10: =Q9 -> 23577.205 | G10: =IF(AND(MOD(A10-1,12)=0,B10<=Inputs!$C$7,E10=0),Inputs!$C$6,0) -> 0 | H10: =IF(B10=1,G10*Inputs!$C$9,0) -> 0 | I10: =I9+G10 -> 24000 | J10: =(F10+G10+H10)*((1+D10)^(1/12)-1) -> 38.93967 | K10: =(F10+G10+H10+J10)*(Inputs!$C$14+IF(B10<=10,Inputs!$C$12,Inputs!$C$13))/12 -> 49.200301 | L10: =IF(OR(E10=1,A10<=Inputs!$C$15),0,MAX(Inputs!$C$8*I10-(F10+G10+H10+J10-K10),0)) -> 0 | M10: =L10*INDEX(Rates!$B$2:$C$101,C10+1,IF(Inputs!$C$5="Male",1,2))/1000/12*Inputs!$C$16 -> 0 | N10: =IF($V$1=1,MAX(F10+G10+H10+J10-K10-M10,0)*Inputs!$C$22/12,0) -> 157.11296 | O10: =IF(AND(MOD(A10,12)=0,B10>=Inputs!$C$18),MAX(F10+G10+H10+J10-K10-M10-N10,0)*Inputs!$C$17,0) -> 0 | P10: =F10+G10+H10+J10-K10-M10-N10+O10 -> 23409.831 | Q10: =IF(OR(E10=1,P10<=0),0,P10) -> 23409.831 | R10: =IF(OR(E10=1,AND(P10<=0,I10>0)),1,0) -> 0 | S10: =IF(L10>0,1,0) -> 0
A11: 10 | B11: =INT((A11-1)/12)+1 -> 1 | C11: =MIN(Inputs!$C$4+B11-1,99) -> 74 | D11: =Inputs!$C$25 -> 0.02 | E11: =R10 -> 0 | F11: =Q10 -> 23409.831 | G11: =IF(AND(MOD(A11-1,12)=0,B11<=Inputs!$C$7,E11=0),Inputs!$C$6,0) -> 0 | H11: =IF(B11=1,G11*Inputs!$C$9,0) -> 0 | I11: =I10+G11 -> 24000 | J11: =(F11+G11+H11)*((1+D11)^(1/12)-1) -> 38.663239 | K11: =(F11+G11+H11+J11)*(Inputs!$C$14+IF(B11<=10,Inputs!$C$12,Inputs!$C$13))/12 -> 48.85103 | L11: =IF(OR(E11=1,A11<=Inputs!$C$15),0,MAX(Inputs!$C$8*I11-(F11+G11+H11+J11-K11),0)) -> 0 | M11: =L11*INDEX(Rates!$B$2:$C$101,C11+1,IF(Inputs!$C$5="Male",1,2))/1000/12*Inputs!$C$16 -> 0 | N11: =IF($V$1=1,MAX(F11+G11+H11+J11-K11-M11,0)*Inputs!$C$22/12,0) -> 155.99762 | O11: =IF(AND(MOD(A11,12)=0,B11>=Inputs!$C$18),MAX(F11+G11+H11+J11-K11-M11-N11,0)*Inputs!$C$17,0) -> 0 | P11: =F11+G11+H11+J11-K11-M11-N11+O11 -> 23243.646 | Q11: =IF(OR(E11=1,P11<=0),0,P11) -> 23243.646 | R11: =IF(OR(E11=1,AND(P11<=0,I11>0)),1,0) -> 0 | S11: =IF(L11>0,1,0) -> 0
A12: 11 | B12: =INT((A12-1)/12)+1 -> 1 | C12: =MIN(Inputs!$C$4+B12-1,99) -> 74 | D12: =Inputs!$C$25 -> 0.02 | E12: =R11 -> 0 | F12: =Q11 -> 23243.646 | G12: =IF(AND(MOD(A12-1,12)=0,B12<=Inputs!$C$7,E12=0),Inputs!$C$6,0) -> 0 | H12: =IF(B12=1,G12*Inputs!$C$9,0) -> 0 | I12: =I11+G12 -> 24000 | J12: =(F12+G12+H12)*((1+D12)^(1/12)-1) -> 38.38877 | K12: =(F12+G12+H12+J12)*(Inputs!$C$14+IF(B12<=10,Inputs!$C$12,Inputs!$C$13))/12 -> 48.504238 | L12: =IF(OR(E12=1,A12<=Inputs!$C$15),0,MAX(Inputs!$C$8*I12-(F12+G12+H12+J12-K12),0)) -> 0 | M12: =L12*INDEX(Rates!$B$2:$C$101,C12+1,IF(Inputs!$C$5="Male",1,2))/1000/12*Inputs!$C$16 -> 0 | N12: =IF($V$1=1,MAX(F12+G12+H12+J12-K12-M12,0)*Inputs!$C$22/12,0) -> 154.8902 | O12: =IF(AND(MOD(A12,12)=0,B12>=Inputs!$C$18),MAX(F12+G12+H12+J12-K12-M12-N12,0)*Inputs!$C$17,0) -> 0 | P12: =F12+G12+H12+J12-K12-M12-N12+O12 -> 23078.64 | Q12: =IF(OR(E12=1,P12<=0),0,P12) -> 23078.64 | R12: =IF(OR(E12=1,AND(P12<=0,I12>0)),1,0) -> 0 | S12: =IF(L12>0,1,0) -> 0
A13: 12 | B13: =INT((A13-1)/12)+1 -> 1 | C13: =MIN(Inputs!$C$4+B13-1,99) -> 74 | D13: =Inputs!$C$25 -> 0.02 | E13: =R12 -> 0 | F13: =Q12 -> 23078.64 | G13: =IF(AND(MOD(A13-1,12)=0,B13<=Inputs!$C$7,E13=0),Inputs!$C$6,0) -> 0 | H13: =IF(B13=1,G13*Inputs!$C$9,0) -> 0 | I13: =I12+G13 -> 24000 | J13: =(F13+G13+H13)*((1+D13)^(1/12)-1) -> 38.11625 | K13: =(F13+G13+H13+J13)*(Inputs!$C$14+IF(B13<=10,Inputs!$C$12,Inputs!$C$13))/12 -> 48.159909 | L13: =IF(OR(E13=1,A13<=Inputs!$C$15),0,MAX(Inputs!$C$8*I13-(F13+G13+H13+J13-K13),0)) -> 0 | M13: =L13*INDEX(Rates!$B$2:$C$101,C13+1,IF(Inputs!$C$5="Male",1,2))/1000/12*Inputs!$C$16 -> 0 | N13: =IF($V$1=1,MAX(F13+G13+H13+J13-K13-M13,0)*Inputs!$C$22/12,0) -> 153.79064 | O13: =IF(AND(MOD(A13,12)=0,B13>=Inputs!$C$18),MAX(F13+G13+H13+J13-K13-M13-N13,0)*Inputs!$C$17,0) -> 0 | P13: =F13+G13+H13+J13-K13-M13-N13+O13 -> 22914.806 | Q13: =IF(OR(E13=1,P13<=0),0,P13) -> 22914.806 | R13: =IF(OR(E13=1,AND(P13<=0,I13>0)),1,0) -> 0 | S13: =IF(L13>0,1,0) -> 0
A14: 13 | B14: =INT((A14-1)/12)+1 -> 2 | C14: =MIN(Inputs!$C$4+B14-1,99) -> 75 | D14: =Inputs!$C$25 -> 0.02 | E14: =R13 -> 0 | F14: =Q13 -> 22914.806 | G14: =IF(AND(MOD(A14-1,12)=0,B14<=Inputs!$C$7,E14=0),Inputs!$C$6,0) -> 24000 | H14: =IF(B14=1,G14*Inputs!$C$9,0) -> 0 | I14: =I13+G14 -> 48000 | J14: =(F14+G14+H14)*((1+D14)^(1/12)-1) -> 77.483616 | K14: =(F14+G14+H14+J14)*(Inputs!$C$14+IF(B14<=10,Inputs!$C$12,Inputs!$C$13))/12 -> 97.900603 | L14: =IF(OR(E14=1,A14<=Inputs!$C$15),0,MAX(Inputs!$C$8*I14-(F14+G14+H14+J14-K14),0)) -> 0 | M14: =L14*INDEX(Rates!$B$2:$C$101,C14+1,IF(Inputs!$C$5="Male",1,2))/1000/12*Inputs!$C$16 -> 0 | N14: =IF($V$1=1,MAX(F14+G14+H14+J14-K14-M14,0)*Inputs!$C$22/12,0) -> 312.62926 | O14: =IF(AND(MOD(A14,12)=0,B14>=Inputs!$C$18),MAX(F14+G14+H14+J14-K14-M14-N14,0)*Inputs!$C$17,0) -> 0 | P14: =F14+G14+H14+J14-K14-M14-N14+O14 -> 46581.759 | Q14: =IF(OR(E14=1,P14<=0),0,P14) -> 46581.759 | R14: =IF(OR(E14=1,AND(P14<=0,I14>0)),1,0) -> 0 | S14: =IF(L14>0,1,0) -> 0
... A301: 300 | B301: =INT((A301-1)/12)+1 -> 25 | C301: =MIN(Inputs!$C$4+B301-1,99) -> 98 | D301: =Inputs!$C$25 -> 0.02 | E301: =R300 -> 1 | F301: =Q300 -> 0 | G301: =IF(AND(MOD(A301-1,12)=0,B301<=Inputs!$C$7,E301=0),Inputs!$C$6,0) -> 0 | H301: =IF(B301=1,G301*Inputs!$C$9,0) -> 0 | I301: =I300+G301 -> 120000 | J301: =(F301+G301+H301)*((1+D301)^(1/12)-1) -> 0 | K301: =(F301+G301+H301+J301)*(Inputs!$C$14+IF(B301<=10,Inputs!$C$12,Inputs!$C$13))/12 -> 0 | L301: =IF(OR(E301=1,A301<=Inputs!$C$15),0,MAX(Inputs!$C$8*I301-(F301+G301+H301+J301-K301),0)) -> 0 | M301: =L301*INDEX(Rates!$B$2:$C$101,C301+1,IF(Inputs!$C$5="Male",1,2))/1000/12*Inputs!$C$16 -> 0 | N301: =IF($V$1=1,MAX(F301+G301+H301+J301-K301-M301,0)*Inputs!$C$22/12,0) -> 0 | O301: =IF(AND(MOD(A301,12)=0,B301>=Inputs!$C$18),MAX(F301+G301+H301+J301-K301-M301-N301,0)*Inputs!$C$17,0) -> 0 | P301: =F301+G301+H301+J301-K301-M301-N301+O301 -> 0 | Q301: =IF(OR(E301=1,P301<=0),0,P301) -> 0 | R301: =IF(OR(E301=1,AND(P301<=0,I301>0)),1,0) -> 1 | S301: =IF(L301>0,1,0) -> 0

Sheet S2_R
A1: Month | B1: Policy year | C1: Age (last b'day) | D1: Gross return p.a. | E1: Lapsed before? | F1: Policy value b/f | G1: Premium | H1: Investment bonus | I1: Net premiums to date | J1: Investment growth | K1: Policy fee + mgmt fee | L1: Sum at risk (charged) | M1: Insurance charge (COI) | N1: Dividend paid out | O1: Loyalty bonus | P1: PV before floor | Q1: Policy value c/f | R1: Lapsed? | S1: SAR>0 flag | U1: Dividend payout on? (1/0) | V1: 0
A2: 1 | B2: =INT((A2-1)/12)+1 -> 1 | C2: =MIN(Inputs!$C$4+B2-1,99) -> 74 | D2: =Inputs!$C$26 -> 0.03 | E2: 0 | F2: 0 | G2: =IF(AND(MOD(A2-1,12)=0,B2<=Inputs!$C$7,E2=0),Inputs!$C$6,0) -> 24000 | H2: =IF(B2=1,G2*Inputs!$C$9,0) -> 960 | I2: =G2 -> 24000 | J2: =(F2+G2+H2)*((1+D2)^(1/12)-1) -> 61.558094 | K2: =(F2+G2+H2+J2)*(Inputs!$C$14+IF(B2<=10,Inputs!$C$12,Inputs!$C$13))/12 -> 52.128246 | L2: =IF(OR(E2=1,A2<=Inputs!$C$15),0,MAX(Inputs!$C$8*I2-(F2+G2+H2+J2-K2),0)) -> 0 | M2: =L2*INDEX(Rates!$B$2:$C$101,C2+1,IF(Inputs!$C$5="Male",1,2))/1000/12*Inputs!$C$16 -> 0 | N2: =IF($V$1=1,MAX(F2+G2+H2+J2-K2-M2,0)*Inputs!$C$22/12,0) -> 0 | O2: =IF(AND(MOD(A2,12)=0,B2>=Inputs!$C$18),MAX(F2+G2+H2+J2-K2-M2-N2,0)*Inputs!$C$17,0) -> 0 | P2: =F2+G2+H2+J2-K2-M2-N2+O2 -> 24969.43 | Q2: =IF(OR(E2=1,P2<=0),0,P2) -> 24969.43 | R2: =IF(OR(E2=1,AND(P2<=0,I2>0)),1,0) -> 0 | S2: =IF(L2>0,1,0) -> 0 | U2: Sensitivity 2 reinvest
A3: 2 | B3: =INT((A3-1)/12)+1 -> 1 | C3: =MIN(Inputs!$C$4+B3-1,99) -> 74 | D3: =Inputs!$C$26 -> 0.03 | E3: =R2 -> 0 | F3: =Q2 -> 24969.43 | G3: =IF(AND(MOD(A3-1,12)=0,B3<=Inputs!$C$7,E3=0),Inputs!$C$6,0) -> 0 | H3: =IF(B3=1,G3*Inputs!$C$9,0) -> 0 | I3: =I2+G3 -> 24000 | J3: =(F3+G3+H3)*((1+D3)^(1/12)-1) -> 61.58135 | K3: =(F3+G3+H3+J3)*(Inputs!$C$14+IF(B3<=10,Inputs!$C$12,Inputs!$C$13))/12 -> 52.14794 | L3: =IF(OR(E3=1,A3<=Inputs!$C$15),0,MAX(Inputs!$C$8*I3-(F3+G3+H3+J3-K3),0)) -> 0 | M3: =L3*INDEX(Rates!$B$2:$C$101,C3+1,IF(Inputs!$C$5="Male",1,2))/1000/12*Inputs!$C$16 -> 0 | N3: =IF($V$1=1,MAX(F3+G3+H3+J3-K3-M3,0)*Inputs!$C$22/12,0) -> 0 | O3: =IF(AND(MOD(A3,12)=0,B3>=Inputs!$C$18),MAX(F3+G3+H3+J3-K3-M3-N3,0)*Inputs!$C$17,0) -> 0 | P3: =F3+G3+H3+J3-K3-M3-N3+O3 -> 24978.863 | Q3: =IF(OR(E3=1,P3<=0),0,P3) -> 24978.863 | R3: =IF(OR(E3=1,AND(P3<=0,I3>0)),1,0) -> 0 | S3: =IF(L3>0,1,0) -> 0
A4: 3 | B4: =INT((A4-1)/12)+1 -> 1 | C4: =MIN(Inputs!$C$4+B4-1,99) -> 74 | D4: =Inputs!$C$26 -> 0.03 | E4: =R3 -> 0 | F4: =Q3 -> 24978.863 | G4: =IF(AND(MOD(A4-1,12)=0,B4<=Inputs!$C$7,E4=0),Inputs!$C$6,0) -> 0 | H4: =IF(B4=1,G4*Inputs!$C$9,0) -> 0 | I4: =I3+G4 -> 24000 | J4: =(F4+G4+H4)*((1+D4)^(1/12)-1) -> 61.604615 | K4: =(F4+G4+H4+J4)*(Inputs!$C$14+IF(B4<=10,Inputs!$C$12,Inputs!$C$13))/12 -> 52.167641 | L4: =IF(OR(E4=1,A4<=Inputs!$C$15),0,MAX(Inputs!$C$8*I4-(F4+G4+H4+J4-K4),0)) -> 0 | M4: =L4*INDEX(Rates!$B$2:$C$101,C4+1,IF(Inputs!$C$5="Male",1,2))/1000/12*Inputs!$C$16 -> 0 | N4: =IF($V$1=1,MAX(F4+G4+H4+J4-K4-M4,0)*Inputs!$C$22/12,0) -> 0 | O4: =IF(AND(MOD(A4,12)=0,B4>=Inputs!$C$18),MAX(F4+G4+H4+J4-K4-M4-N4,0)*Inputs!$C$17,0) -> 0 | P4: =F4+G4+H4+J4-K4-M4-N4+O4 -> 24988.3 | Q4: =IF(OR(E4=1,P4<=0),0,P4) -> 24988.3 | R4: =IF(OR(E4=1,AND(P4<=0,I4>0)),1,0) -> 0 | S4: =IF(L4>0,1,0) -> 0
A5: 4 | B5: =INT((A5-1)/12)+1 -> 1 | C5: =MIN(Inputs!$C$4+B5-1,99) -> 74 | D5: =Inputs!$C$26 -> 0.03 | E5: =R4 -> 0 | F5: =Q4 -> 24988.3 | G5: =IF(AND(MOD(A5-1,12)=0,B5<=Inputs!$C$7,E5=0),Inputs!$C$6,0) -> 0 | H5: =IF(B5=1,G5*Inputs!$C$9,0) -> 0 | I5: =I4+G5 -> 24000 | J5: =(F5+G5+H5)*((1+D5)^(1/12)-1) -> 61.62789 | K5: =(F5+G5+H5+J5)*(Inputs!$C$14+IF(B5<=10,Inputs!$C$12,Inputs!$C$13))/12 -> 52.18735 | L5: =IF(OR(E5=1,A5<=Inputs!$C$15),0,MAX(Inputs!$C$8*I5-(F5+G5+H5+J5-K5),0)) -> 0 | M5: =L5*INDEX(Rates!$B$2:$C$101,C5+1,IF(Inputs!$C$5="Male",1,2))/1000/12*Inputs!$C$16 -> 0 | N5: =IF($V$1=1,MAX(F5+G5+H5+J5-K5-M5,0)*Inputs!$C$22/12,0) -> 0 | O5: =IF(AND(MOD(A5,12)=0,B5>=Inputs!$C$18),MAX(F5+G5+H5+J5-K5-M5-N5,0)*Inputs!$C$17,0) -> 0 | P5: =F5+G5+H5+J5-K5-M5-N5+O5 -> 24997.741 | Q5: =IF(OR(E5=1,P5<=0),0,P5) -> 24997.741 | R5: =IF(OR(E5=1,AND(P5<=0,I5>0)),1,0) -> 0 | S5: =IF(L5>0,1,0) -> 0
A6: 5 | B6: =INT((A6-1)/12)+1 -> 1 | C6: =MIN(Inputs!$C$4+B6-1,99) -> 74 | D6: =Inputs!$C$26 -> 0.03 | E6: =R5 -> 0 | F6: =Q5 -> 24997.741 | G6: =IF(AND(MOD(A6-1,12)=0,B6<=Inputs!$C$7,E6=0),Inputs!$C$6,0) -> 0 | H6: =IF(B6=1,G6*Inputs!$C$9,0) -> 0 | I6: =I5+G6 -> 24000 | J6: =(F6+G6+H6)*((1+D6)^(1/12)-1) -> 61.651172 | K6: =(F6+G6+H6+J6)*(Inputs!$C$14+IF(B6<=10,Inputs!$C$12,Inputs!$C$13))/12 -> 52.207067 | L6: =IF(OR(E6=1,A6<=Inputs!$C$15),0,MAX(Inputs!$C$8*I6-(F6+G6+H6+J6-K6),0)) -> 0 | M6: =L6*INDEX(Rates!$B$2:$C$101,C6+1,IF(Inputs!$C$5="Male",1,2))/1000/12*Inputs!$C$16 -> 0 | N6: =IF($V$1=1,MAX(F6+G6+H6+J6-K6-M6,0)*Inputs!$C$22/12,0) -> 0 | O6: =IF(AND(MOD(A6,12)=0,B6>=Inputs!$C$18),MAX(F6+G6+H6+J6-K6-M6-N6,0)*Inputs!$C$17,0) -> 0 | P6: =F6+G6+H6+J6-K6-M6-N6+O6 -> 25007.185 | Q6: =IF(OR(E6=1,P6<=0),0,P6) -> 25007.185 | R6: =IF(OR(E6=1,AND(P6<=0,I6>0)),1,0) -> 0 | S6: =IF(L6>0,1,0) -> 0
A7: 6 | B7: =INT((A7-1)/12)+1 -> 1 | C7: =MIN(Inputs!$C$4+B7-1,99) -> 74 | D7: =Inputs!$C$26 -> 0.03 | E7: =R6 -> 0 | F7: =Q6 -> 25007.185 | G7: =IF(AND(MOD(A7-1,12)=0,B7<=Inputs!$C$7,E7=0),Inputs!$C$6,0) -> 0 | H7: =IF(B7=1,G7*Inputs!$C$9,0) -> 0 | I7: =I6+G7 -> 24000 | J7: =(F7+G7+H7)*((1+D7)^(1/12)-1) -> 61.674464 | K7: =(F7+G7+H7+J7)*(Inputs!$C$14+IF(B7<=10,Inputs!$C$12,Inputs!$C$13))/12 -> 52.22679 | L7: =IF(OR(E7=1,A7<=Inputs!$C$15),0,MAX(Inputs!$C$8*I7-(F7+G7+H7+J7-K7),0)) -> 0 | M7: =L7*INDEX(Rates!$B$2:$C$101,C7+1,IF(Inputs!$C$5="Male",1,2))/1000/12*Inputs!$C$16 -> 0 | N7: =IF($V$1=1,MAX(F7+G7+H7+J7-K7-M7,0)*Inputs!$C$22/12,0) -> 0 | O7: =IF(AND(MOD(A7,12)=0,B7>=Inputs!$C$18),MAX(F7+G7+H7+J7-K7-M7-N7,0)*Inputs!$C$17,0) -> 0 | P7: =F7+G7+H7+J7-K7-M7-N7+O7 -> 25016.633 | Q7: =IF(OR(E7=1,P7<=0),0,P7) -> 25016.633 | R7: =IF(OR(E7=1,AND(P7<=0,I7>0)),1,0) -> 0 | S7: =IF(L7>0,1,0) -> 0
A8: 7 | B8: =INT((A8-1)/12)+1 -> 1 | C8: =MIN(Inputs!$C$4+B8-1,99) -> 74 | D8: =Inputs!$C$26 -> 0.03 | E8: =R7 -> 0 | F8: =Q7 -> 25016.633 | G8: =IF(AND(MOD(A8-1,12)=0,B8<=Inputs!$C$7,E8=0),Inputs!$C$6,0) -> 0 | H8: =IF(B8=1,G8*Inputs!$C$9,0) -> 0 | I8: =I7+G8 -> 24000 | J8: =(F8+G8+H8)*((1+D8)^(1/12)-1) -> 61.697765 | K8: =(F8+G8+H8+J8)*(Inputs!$C$14+IF(B8<=10,Inputs!$C$12,Inputs!$C$13))/12 -> 52.246521 | L8: =IF(OR(E8=1,A8<=Inputs!$C$15),0,MAX(Inputs!$C$8*I8-(F8+G8+H8+J8-K8),0)) -> 0 | M8: =L8*INDEX(Rates!$B$2:$C$101,C8+1,IF(Inputs!$C$5="Male",1,2))/1000/12*Inputs!$C$16 -> 0 | N8: =IF($V$1=1,MAX(F8+G8+H8+J8-K8-M8,0)*Inputs!$C$22/12,0) -> 0 | O8: =IF(AND(MOD(A8,12)=0,B8>=Inputs!$C$18),MAX(F8+G8+H8+J8-K8-M8-N8,0)*Inputs!$C$17,0) -> 0 | P8: =F8+G8+H8+J8-K8-M8-N8+O8 -> 25026.084 | Q8: =IF(OR(E8=1,P8<=0),0,P8) -> 25026.084 | R8: =IF(OR(E8=1,AND(P8<=0,I8>0)),1,0) -> 0 | S8: =IF(L8>0,1,0) -> 0
A9: 8 | B9: =INT((A9-1)/12)+1 -> 1 | C9: =MIN(Inputs!$C$4+B9-1,99) -> 74 | D9: =Inputs!$C$26 -> 0.03 | E9: =R8 -> 0 | F9: =Q8 -> 25026.084 | G9: =IF(AND(MOD(A9-1,12)=0,B9<=Inputs!$C$7,E9=0),Inputs!$C$6,0) -> 0 | H9: =IF(B9=1,G9*Inputs!$C$9,0) -> 0 | I9: =I8+G9 -> 24000 | J9: =(F9+G9+H9)*((1+D9)^(1/12)-1) -> 61.721074 | K9: =(F9+G9+H9+J9)*(Inputs!$C$14+IF(B9<=10,Inputs!$C$12,Inputs!$C$13))/12 -> 52.26626 | L9: =IF(OR(E9=1,A9<=Inputs!$C$15),0,MAX(Inputs!$C$8*I9-(F9+G9+H9+J9-K9),0)) -> 0 | M9: =L9*INDEX(Rates!$B$2:$C$101,C9+1,IF(Inputs!$C$5="Male",1,2))/1000/12*Inputs!$C$16 -> 0 | N9: =IF($V$1=1,MAX(F9+G9+H9+J9-K9-M9,0)*Inputs!$C$22/12,0) -> 0 | O9: =IF(AND(MOD(A9,12)=0,B9>=Inputs!$C$18),MAX(F9+G9+H9+J9-K9-M9-N9,0)*Inputs!$C$17,0) -> 0 | P9: =F9+G9+H9+J9-K9-M9-N9+O9 -> 25035.539 | Q9: =IF(OR(E9=1,P9<=0),0,P9) -> 25035.539 | R9: =IF(OR(E9=1,AND(P9<=0,I9>0)),1,0) -> 0 | S9: =IF(L9>0,1,0) -> 0
A10: 9 | B10: =INT((A10-1)/12)+1 -> 1 | C10: =MIN(Inputs!$C$4+B10-1,99) -> 74 | D10: =Inputs!$C$26 -> 0.03 | E10: =R9 -> 0 | F10: =Q9 -> 25035.539 | G10: =IF(AND(MOD(A10-1,12)=0,B10<=Inputs!$C$7,E10=0),Inputs!$C$6,0) -> 0 | H10: =IF(B10=1,G10*Inputs!$C$9,0) -> 0 | I10: =I9+G10 -> 24000 | J10: =(F10+G10+H10)*((1+D10)^(1/12)-1) -> 61.744392 | K10: =(F10+G10+H10+J10)*(Inputs!$C$14+IF(B10<=10,Inputs!$C$12,Inputs!$C$13))/12 -> 52.286006 | L10: =IF(OR(E10=1,A10<=Inputs!$C$15),0,MAX(Inputs!$C$8*I10-(F10+G10+H10+J10-K10),0)) -> 0 | M10: =L10*INDEX(Rates!$B$2:$C$101,C10+1,IF(Inputs!$C$5="Male",1,2))/1000/12*Inputs!$C$16 -> 0 | N10: =IF($V$1=1,MAX(F10+G10+H10+J10-K10-M10,0)*Inputs!$C$22/12,0) -> 0 | O10: =IF(AND(MOD(A10,12)=0,B10>=Inputs!$C$18),MAX(F10+G10+H10+J10-K10-M10-N10,0)*Inputs!$C$17,0) -> 0 | P10: =F10+G10+H10+J10-K10-M10-N10+O10 -> 25044.997 | Q10: =IF(OR(E10=1,P10<=0),0,P10) -> 25044.997 | R10: =IF(OR(E10=1,AND(P10<=0,I10>0)),1,0) -> 0 | S10: =IF(L10>0,1,0) -> 0
A11: 10 | B11: =INT((A11-1)/12)+1 -> 1 | C11: =MIN(Inputs!$C$4+B11-1,99) -> 74 | D11: =Inputs!$C$26 -> 0.03 | E11: =R10 -> 0 | F11: =Q10 -> 25044.997 | G11: =IF(AND(MOD(A11-1,12)=0,B11<=Inputs!$C$7,E11=0),Inputs!$C$6,0) -> 0 | H11: =IF(B11=1,G11*Inputs!$C$9,0) -> 0 | I11: =I10+G11 -> 24000 | J11: =(F11+G11+H11)*((1+D11)^(1/12)-1) -> 61.767719 | K11: =(F11+G11+H11+J11)*(Inputs!$C$14+IF(B11<=10,Inputs!$C$12,Inputs!$C$13))/12 -> 52.30576 | L11: =IF(OR(E11=1,A11<=Inputs!$C$15),0,MAX(Inputs!$C$8*I11-(F11+G11+H11+J11-K11),0)) -> 0 | M11: =L11*INDEX(Rates!$B$2:$C$101,C11+1,IF(Inputs!$C$5="Male",1,2))/1000/12*Inputs!$C$16 -> 0 | N11: =IF($V$1=1,MAX(F11+G11+H11+J11-K11-M11,0)*Inputs!$C$22/12,0) -> 0 | O11: =IF(AND(MOD(A11,12)=0,B11>=Inputs!$C$18),MAX(F11+G11+H11+J11-K11-M11-N11,0)*Inputs!$C$17,0) -> 0 | P11: =F11+G11+H11+J11-K11-M11-N11+O11 -> 25054.459 | Q11: =IF(OR(E11=1,P11<=0),0,P11) -> 25054.459 | R11: =IF(OR(E11=1,AND(P11<=0,I11>0)),1,0) -> 0 | S11: =IF(L11>0,1,0) -> 0
A12: 11 | B12: =INT((A12-1)/12)+1 -> 1 | C12: =MIN(Inputs!$C$4+B12-1,99) -> 74 | D12: =Inputs!$C$26 -> 0.03 | E12: =R11 -> 0 | F12: =Q11 -> 25054.459 | G12: =IF(AND(MOD(A12-1,12)=0,B12<=Inputs!$C$7,E12=0),Inputs!$C$6,0) -> 0 | H12: =IF(B12=1,G12*Inputs!$C$9,0) -> 0 | I12: =I11+G12 -> 24000 | J12: =(F12+G12+H12)*((1+D12)^(1/12)-1) -> 61.791055 | K12: =(F12+G12+H12+J12)*(Inputs!$C$14+IF(B12<=10,Inputs!$C$12,Inputs!$C$13))/12 -> 52.325521 | L12: =IF(OR(E12=1,A12<=Inputs!$C$15),0,MAX(Inputs!$C$8*I12-(F12+G12+H12+J12-K12),0)) -> 0 | M12: =L12*INDEX(Rates!$B$2:$C$101,C12+1,IF(Inputs!$C$5="Male",1,2))/1000/12*Inputs!$C$16 -> 0 | N12: =IF($V$1=1,MAX(F12+G12+H12+J12-K12-M12,0)*Inputs!$C$22/12,0) -> 0 | O12: =IF(AND(MOD(A12,12)=0,B12>=Inputs!$C$18),MAX(F12+G12+H12+J12-K12-M12-N12,0)*Inputs!$C$17,0) -> 0 | P12: =F12+G12+H12+J12-K12-M12-N12+O12 -> 25063.924 | Q12: =IF(OR(E12=1,P12<=0),0,P12) -> 25063.924 | R12: =IF(OR(E12=1,AND(P12<=0,I12>0)),1,0) -> 0 | S12: =IF(L12>0,1,0) -> 0
A13: 12 | B13: =INT((A13-1)/12)+1 -> 1 | C13: =MIN(Inputs!$C$4+B13-1,99) -> 74 | D13: =Inputs!$C$26 -> 0.03 | E13: =R12 -> 0 | F13: =Q12 -> 25063.924 | G13: =IF(AND(MOD(A13-1,12)=0,B13<=Inputs!$C$7,E13=0),Inputs!$C$6,0) -> 0 | H13: =IF(B13=1,G13*Inputs!$C$9,0) -> 0 | I13: =I12+G13 -> 24000 | J13: =(F13+G13+H13)*((1+D13)^(1/12)-1) -> 61.814399 | K13: =(F13+G13+H13+J13)*(Inputs!$C$14+IF(B13<=10,Inputs!$C$12,Inputs!$C$13))/12 -> 52.345289 | L13: =IF(OR(E13=1,A13<=Inputs!$C$15),0,MAX(Inputs!$C$8*I13-(F13+G13+H13+J13-K13),0)) -> 0 | M13: =L13*INDEX(Rates!$B$2:$C$101,C13+1,IF(Inputs!$C$5="Male",1,2))/1000/12*Inputs!$C$16 -> 0 | N13: =IF($V$1=1,MAX(F13+G13+H13+J13-K13-M13,0)*Inputs!$C$22/12,0) -> 0 | O13: =IF(AND(MOD(A13,12)=0,B13>=Inputs!$C$18),MAX(F13+G13+H13+J13-K13-M13-N13,0)*Inputs!$C$17,0) -> 0 | P13: =F13+G13+H13+J13-K13-M13-N13+O13 -> 25073.394 | Q13: =IF(OR(E13=1,P13<=0),0,P13) -> 25073.394 | R13: =IF(OR(E13=1,AND(P13<=0,I13>0)),1,0) -> 0 | S13: =IF(L13>0,1,0) -> 0
A14: 13 | B14: =INT((A14-1)/12)+1 -> 2 | C14: =MIN(Inputs!$C$4+B14-1,99) -> 75 | D14: =Inputs!$C$26 -> 0.03 | E14: =R13 -> 0 | F14: =Q13 -> 25073.394 | G14: =IF(AND(MOD(A14-1,12)=0,B14<=Inputs!$C$7,E14=0),Inputs!$C$6,0) -> 24000 | H14: =IF(B14=1,G14*Inputs!$C$9,0) -> 0 | I14: =I13+G14 -> 48000 | J14: =(F14+G14+H14)*((1+D14)^(1/12)-1) -> 121.02823 | K14: =(F14+G14+H14+J14)*(Inputs!$C$14+IF(B14<=10,Inputs!$C$12,Inputs!$C$13))/12 -> 102.48838 | L14: =IF(OR(E14=1,A14<=Inputs!$C$15),0,MAX(Inputs!$C$8*I14-(F14+G14+H14+J14-K14),0)) -> 0 | M14: =L14*INDEX(Rates!$B$2:$C$101,C14+1,IF(Inputs!$C$5="Male",1,2))/1000/12*Inputs!$C$16 -> 0 | N14: =IF($V$1=1,MAX(F14+G14+H14+J14-K14-M14,0)*Inputs!$C$22/12,0) -> 0 | O14: =IF(AND(MOD(A14,12)=0,B14>=Inputs!$C$18),MAX(F14+G14+H14+J14-K14-M14-N14,0)*Inputs!$C$17,0) -> 0 | P14: =F14+G14+H14+J14-K14-M14-N14+O14 -> 49091.933 | Q14: =IF(OR(E14=1,P14<=0),0,P14) -> 49091.933 | R14: =IF(OR(E14=1,AND(P14<=0,I14>0)),1,0) -> 0 | S14: =IF(L14>0,1,0) -> 0
... A301: 300 | B301: =INT((A301-1)/12)+1 -> 25 | C301: =MIN(Inputs!$C$4+B301-1,99) -> 98 | D301: =Inputs!$C$26 -> 0.03 | E301: =R300 -> 0 | F301: =Q300 -> 192101.5 | G301: =IF(AND(MOD(A301-1,12)=0,B301<=Inputs!$C$7,E301=0),Inputs!$C$6,0) -> 0 | H301: =IF(B301=1,G301*Inputs!$C$9,0) -> 0 | I301: =I300+G301 -> 120000 | J301: =(F301+G301+H301)*((1+D301)^(1/12)-1) -> 473.77413 | K301: =(F301+G301+H301+J301)*(Inputs!$C$14+IF(B301<=10,Inputs!$C$12,Inputs!$C$13))/12 -> 96.287639 | L301: =IF(OR(E301=1,A301<=Inputs!$C$15),0,MAX(Inputs!$C$8*I301-(F301+G301+H301+J301-K301),0)) -> 0 | M301: =L301*INDEX(Rates!$B$2:$C$101,C301+1,IF(Inputs!$C$5="Male",1,2))/1000/12*Inputs!$C$16 -> 0 | N301: =IF($V$1=1,MAX(F301+G301+H301+J301-K301-M301,0)*Inputs!$C$22/12,0) -> 0 | O301: =IF(AND(MOD(A301,12)=0,B301>=Inputs!$C$18),MAX(F301+G301+H301+J301-K301-M301-N301,0)*Inputs!$C$17,0) -> 962.39495 | P301: =F301+G301+H301+J301-K301-M301-N301+O301 -> 193441.39 | Q301: =IF(OR(E301=1,P301<=0),0,P301) -> 193441.39 | R301: =IF(OR(E301=1,AND(P301<=0,I301>0)),1,0) -> 0 | S301: =IF(L301>0,1,0) -> 0

Sheet S2_P
A1: Month | B1: Policy year | C1: Age (last b'day) | D1: Gross return p.a. | E1: Lapsed before? | F1: Policy value b/f | G1: Premium | H1: Investment bonus | I1: Net premiums to date | J1: Investment growth | K1: Policy fee + mgmt fee | L1: Sum at risk (charged) | M1: Insurance charge (COI) | N1: Dividend paid out | O1: Loyalty bonus | P1: PV before floor | Q1: Policy value c/f | R1: Lapsed? | S1: SAR>0 flag | U1: Dividend payout on? (1/0) | V1: 1
A2: 1 | B2: =INT((A2-1)/12)+1 -> 1 | C2: =MIN(Inputs!$C$4+B2-1,99) -> 74 | D2: =Inputs!$C$26 -> 0.03 | E2: 0 | F2: 0 | G2: =IF(AND(MOD(A2-1,12)=0,B2<=Inputs!$C$7,E2=0),Inputs!$C$6,0) -> 24000 | H2: =IF(B2=1,G2*Inputs!$C$9,0) -> 960 | I2: =G2 -> 24000 | J2: =(F2+G2+H2)*((1+D2)^(1/12)-1) -> 61.558094 | K2: =(F2+G2+H2+J2)*(Inputs!$C$14+IF(B2<=10,Inputs!$C$12,Inputs!$C$13))/12 -> 52.128246 | L2: =IF(OR(E2=1,A2<=Inputs!$C$15),0,MAX(Inputs!$C$8*I2-(F2+G2+H2+J2-K2),0)) -> 0 | M2: =L2*INDEX(Rates!$B$2:$C$101,C2+1,IF(Inputs!$C$5="Male",1,2))/1000/12*Inputs!$C$16 -> 0 | N2: =IF($V$1=1,MAX(F2+G2+H2+J2-K2-M2,0)*Inputs!$C$22/12,0) -> 166.46287 | O2: =IF(AND(MOD(A2,12)=0,B2>=Inputs!$C$18),MAX(F2+G2+H2+J2-K2-M2-N2,0)*Inputs!$C$17,0) -> 0 | P2: =F2+G2+H2+J2-K2-M2-N2+O2 -> 24802.967 | Q2: =IF(OR(E2=1,P2<=0),0,P2) -> 24802.967 | R2: =IF(OR(E2=1,AND(P2<=0,I2>0)),1,0) -> 0 | S2: =IF(L2>0,1,0) -> 0 | U2: Sensitivity 2 payout
A3: 2 | B3: =INT((A3-1)/12)+1 -> 1 | C3: =MIN(Inputs!$C$4+B3-1,99) -> 74 | D3: =Inputs!$C$26 -> 0.03 | E3: =R2 -> 0 | F3: =Q2 -> 24802.967 | G3: =IF(AND(MOD(A3-1,12)=0,B3<=Inputs!$C$7,E3=0),Inputs!$C$6,0) -> 0 | H3: =IF(B3=1,G3*Inputs!$C$9,0) -> 0 | I3: =I2+G3 -> 24000 | J3: =(F3+G3+H3)*((1+D3)^(1/12)-1) -> 61.170808 | K3: =(F3+G3+H3+J3)*(Inputs!$C$14+IF(B3<=10,Inputs!$C$12,Inputs!$C$13))/12 -> 51.800287 | L3: =IF(OR(E3=1,A3<=Inputs!$C$15),0,MAX(Inputs!$C$8*I3-(F3+G3+H3+J3-K3),0)) -> 0 | M3: =L3*INDEX(Rates!$B$2:$C$101,C3+1,IF(Inputs!$C$5="Male",1,2))/1000/12*Inputs!$C$16 -> 0 | N3: =IF($V$1=1,MAX(F3+G3+H3+J3-K3-M3,0)*Inputs!$C$22/12,0) -> 165.41558 | O3: =IF(AND(MOD(A3,12)=0,B3>=Inputs!$C$18),MAX(F3+G3+H3+J3-K3-M3-N3,0)*Inputs!$C$17,0) -> 0 | P3: =F3+G3+H3+J3-K3-M3-N3+O3 -> 24646.922 | Q3: =IF(OR(E3=1,P3<=0),0,P3) -> 24646.922 | R3: =IF(OR(E3=1,AND(P3<=0,I3>0)),1,0) -> 0 | S3: =IF(L3>0,1,0) -> 0
A4: 3 | B4: =INT((A4-1)/12)+1 -> 1 | C4: =MIN(Inputs!$C$4+B4-1,99) -> 74 | D4: =Inputs!$C$26 -> 0.03 | E4: =R3 -> 0 | F4: =Q3 -> 24646.922 | G4: =IF(AND(MOD(A4-1,12)=0,B4<=Inputs!$C$7,E4=0),Inputs!$C$6,0) -> 0 | H4: =IF(B4=1,G4*Inputs!$C$9,0) -> 0 | I4: =I3+G4 -> 24000 | J4: =(F4+G4+H4)*((1+D4)^(1/12)-1) -> 60.785959 | K4: =(F4+G4+H4+J4)*(Inputs!$C$14+IF(B4<=10,Inputs!$C$12,Inputs!$C$13))/12 -> 51.474391 | L4: =IF(OR(E4=1,A4<=Inputs!$C$15),0,MAX(Inputs!$C$8*I4-(F4+G4+H4+J4-K4),0)) -> 0 | M4: =L4*INDEX(Rates!$B$2:$C$101,C4+1,IF(Inputs!$C$5="Male",1,2))/1000/12*Inputs!$C$16 -> 0 | N4: =IF($V$1=1,MAX(F4+G4+H4+J4-K4-M4,0)*Inputs!$C$22/12,0) -> 164.37489 | O4: =IF(AND(MOD(A4,12)=0,B4>=Inputs!$C$18),MAX(F4+G4+H4+J4-K4-M4-N4,0)*Inputs!$C$17,0) -> 0 | P4: =F4+G4+H4+J4-K4-M4-N4+O4 -> 24491.859 | Q4: =IF(OR(E4=1,P4<=0),0,P4) -> 24491.859 | R4: =IF(OR(E4=1,AND(P4<=0,I4>0)),1,0) -> 0 | S4: =IF(L4>0,1,0) -> 0
A5: 4 | B5: =INT((A5-1)/12)+1 -> 1 | C5: =MIN(Inputs!$C$4+B5-1,99) -> 74 | D5: =Inputs!$C$26 -> 0.03 | E5: =R4 -> 0 | F5: =Q4 -> 24491.859 | G5: =IF(AND(MOD(A5-1,12)=0,B5<=Inputs!$C$7,E5=0),Inputs!$C$6,0) -> 0 | H5: =IF(B5=1,G5*Inputs!$C$9,0) -> 0 | I5: =I4+G5 -> 24000 | J5: =(F5+G5+H5)*((1+D5)^(1/12)-1) -> 60.403531 | K5: =(F5+G5+H5+J5)*(Inputs!$C$14+IF(B5<=10,Inputs!$C$12,Inputs!$C$13))/12 -> 51.150546 | L5: =IF(OR(E5=1,A5<=Inputs!$C$15),0,MAX(Inputs!$C$8*I5-(F5+G5+H5+J5-K5),0)) -> 0 | M5: =L5*INDEX(Rates!$B$2:$C$101,C5+1,IF(Inputs!$C$5="Male",1,2))/1000/12*Inputs!$C$16 -> 0 | N5: =IF($V$1=1,MAX(F5+G5+H5+J5-K5-M5,0)*Inputs!$C$22/12,0) -> 163.34074 | O5: =IF(AND(MOD(A5,12)=0,B5>=Inputs!$C$18),MAX(F5+G5+H5+J5-K5-M5-N5,0)*Inputs!$C$17,0) -> 0 | P5: =F5+G5+H5+J5-K5-M5-N5+O5 -> 24337.771 | Q5: =IF(OR(E5=1,P5<=0),0,P5) -> 24337.771 | R5: =IF(OR(E5=1,AND(P5<=0,I5>0)),1,0) -> 0 | S5: =IF(L5>0,1,0) -> 0
A6: 5 | B6: =INT((A6-1)/12)+1 -> 1 | C6: =MIN(Inputs!$C$4+B6-1,99) -> 74 | D6: =Inputs!$C$26 -> 0.03 | E6: =R5 -> 0 | F6: =Q5 -> 24337.771 | G6: =IF(AND(MOD(A6-1,12)=0,B6<=Inputs!$C$7,E6=0),Inputs!$C$6,0) -> 0 | H6: =IF(B6=1,G6*Inputs!$C$9,0) -> 0 | I6: =I5+G6 -> 24000 | J6: =(F6+G6+H6)*((1+D6)^(1/12)-1) -> 60.023509 | K6: =(F6+G6+H6+J6)*(Inputs!$C$14+IF(B6<=10,Inputs!$C$12,Inputs!$C$13))/12 -> 50.828738 | L6: =IF(OR(E6=1,A6<=Inputs!$C$15),0,MAX(Inputs!$C$8*I6-(F6+G6+H6+J6-K6),0)) -> 0 | M6: =L6*INDEX(Rates!$B$2:$C$101,C6+1,IF(Inputs!$C$5="Male",1,2))/1000/12*Inputs!$C$16 -> 0 | N6: =IF($V$1=1,MAX(F6+G6+H6+J6-K6-M6,0)*Inputs!$C$22/12,0) -> 162.3131 | O6: =IF(AND(MOD(A6,12)=0,B6>=Inputs!$C$18),MAX(F6+G6+H6+J6-K6-M6-N6,0)*Inputs!$C$17,0) -> 0 | P6: =F6+G6+H6+J6-K6-M6-N6+O6 -> 24184.653 | Q6: =IF(OR(E6=1,P6<=0),0,P6) -> 24184.653 | R6: =IF(OR(E6=1,AND(P6<=0,I6>0)),1,0) -> 0 | S6: =IF(L6>0,1,0) -> 0
A7: 6 | B7: =INT((A7-1)/12)+1 -> 1 | C7: =MIN(Inputs!$C$4+B7-1,99) -> 74 | D7: =Inputs!$C$26 -> 0.03 | E7: =R6 -> 0 | F7: =Q6 -> 24184.653 | G7: =IF(AND(MOD(A7-1,12)=0,B7<=Inputs!$C$7,E7=0),Inputs!$C$6,0) -> 0 | H7: =IF(B7=1,G7*Inputs!$C$9,0) -> 0 | I7: =I6+G7 -> 24000 | J7: =(F7+G7+H7)*((1+D7)^(1/12)-1) -> 59.645877 | K7: =(F7+G7+H7+J7)*(Inputs!$C$14+IF(B7<=10,Inputs!$C$12,Inputs!$C$13))/12 -> 50.508955 | L7: =IF(OR(E7=1,A7<=Inputs!$C$15),0,MAX(Inputs!$C$8*I7-(F7+G7+H7+J7-K7),0)) -> 0 | M7: =L7*INDEX(Rates!$B$2:$C$101,C7+1,IF(Inputs!$C$5="Male",1,2))/1000/12*Inputs!$C$16 -> 0 | N7: =IF($V$1=1,MAX(F7+G7+H7+J7-K7-M7,0)*Inputs!$C$22/12,0) -> 161.29193 | O7: =IF(AND(MOD(A7,12)=0,B7>=Inputs!$C$18),MAX(F7+G7+H7+J7-K7-M7-N7,0)*Inputs!$C$17,0) -> 0 | P7: =F7+G7+H7+J7-K7-M7-N7+O7 -> 24032.497 | Q7: =IF(OR(E7=1,P7<=0),0,P7) -> 24032.497 | R7: =IF(OR(E7=1,AND(P7<=0,I7>0)),1,0) -> 0 | S7: =IF(L7>0,1,0) -> 0
A8: 7 | B8: =INT((A8-1)/12)+1 -> 1 | C8: =MIN(Inputs!$C$4+B8-1,99) -> 74 | D8: =Inputs!$C$26 -> 0.03 | E8: =R7 -> 0 | F8: =Q7 -> 24032.497 | G8: =IF(AND(MOD(A8-1,12)=0,B8<=Inputs!$C$7,E8=0),Inputs!$C$6,0) -> 0 | H8: =IF(B8=1,G8*Inputs!$C$9,0) -> 0 | I8: =I7+G8 -> 24000 | J8: =(F8+G8+H8)*((1+D8)^(1/12)-1) -> 59.270622 | K8: =(F8+G8+H8+J8)*(Inputs!$C$14+IF(B8<=10,Inputs!$C$12,Inputs!$C$13))/12 -> 50.191184 | L8: =IF(OR(E8=1,A8<=Inputs!$C$15),0,MAX(Inputs!$C$8*I8-(F8+G8+H8+J8-K8),0)) -> 0 | M8: =L8*INDEX(Rates!$B$2:$C$101,C8+1,IF(Inputs!$C$5="Male",1,2))/1000/12*Inputs!$C$16 -> 0 | N8: =IF($V$1=1,MAX(F8+G8+H8+J8-K8-M8,0)*Inputs!$C$22/12,0) -> 160.27718 | O8: =IF(AND(MOD(A8,12)=0,B8>=Inputs!$C$18),MAX(F8+G8+H8+J8-K8-M8-N8,0)*Inputs!$C$17,0) -> 0 | P8: =F8+G8+H8+J8-K8-M8-N8+O8 -> 23881.3 | Q8: =IF(OR(E8=1,P8<=0),0,P8) -> 23881.3 | R8: =IF(OR(E8=1,AND(P8<=0,I8>0)),1,0) -> 0 | S8: =IF(L8>0,1,0) -> 0
A9: 8 | B9: =INT((A9-1)/12)+1 -> 1 | C9: =MIN(Inputs!$C$4+B9-1,99) -> 74 | D9: =Inputs!$C$26 -> 0.03 | E9: =R8 -> 0 | F9: =Q8 -> 23881.3 | G9: =IF(AND(MOD(A9-1,12)=0,B9<=Inputs!$C$7,E9=0),Inputs!$C$6,0) -> 0 | H9: =IF(B9=1,G9*Inputs!$C$9,0) -> 0 | I9: =I8+G9 -> 24000 | J9: =(F9+G9+H9)*((1+D9)^(1/12)-1) -> 58.897728 | K9: =(F9+G9+H9+J9)*(Inputs!$C$14+IF(B9<=10,Inputs!$C$12,Inputs!$C$13))/12 -> 49.875411 | L9: =IF(OR(E9=1,A9<=Inputs!$C$15),0,MAX(Inputs!$C$8*I9-(F9+G9+H9+J9-K9),0)) -> 0 | M9: =L9*INDEX(Rates!$B$2:$C$101,C9+1,IF(Inputs!$C$5="Male",1,2))/1000/12*Inputs!$C$16 -> 0 | N9: =IF($V$1=1,MAX(F9+G9+H9+J9-K9-M9,0)*Inputs!$C$22/12,0) -> 159.26881 | O9: =IF(AND(MOD(A9,12)=0,B9>=Inputs!$C$18),MAX(F9+G9+H9+J9-K9-M9-N9,0)*Inputs!$C$17,0) -> 0 | P9: =F9+G9+H9+J9-K9-M9-N9+O9 -> 23731.053 | Q9: =IF(OR(E9=1,P9<=0),0,P9) -> 23731.053 | R9: =IF(OR(E9=1,AND(P9<=0,I9>0)),1,0) -> 0 | S9: =IF(L9>0,1,0) -> 0
A10: 9 | B10: =INT((A10-1)/12)+1 -> 1 | C10: =MIN(Inputs!$C$4+B10-1,99) -> 74 | D10: =Inputs!$C$26 -> 0.03 | E10: =R9 -> 0 | F10: =Q9 -> 23731.053 | G10: =IF(AND(MOD(A10-1,12)=0,B10<=Inputs!$C$7,E10=0),Inputs!$C$6,0) -> 0 | H10: =IF(B10=1,G10*Inputs!$C$9,0) -> 0 | I10: =I9+G10 -> 24000 | J10: =(F10+G10+H10)*((1+D10)^(1/12)-1) -> 58.527179 | K10: =(F10+G10+H10+J10)*(Inputs!$C$14+IF(B10<=10,Inputs!$C$12,Inputs!$C$13))/12 -> 49.561626 | L10: =IF(OR(E10=1,A10<=Inputs!$C$15),0,MAX(Inputs!$C$8*I10-(F10+G10+H10+J10-K10),0)) -> 0 | M10: =L10*INDEX(Rates!$B$2:$C$101,C10+1,IF(Inputs!$C$5="Male",1,2))/1000/12*Inputs!$C$16 -> 0 | N10: =IF($V$1=1,MAX(F10+G10+H10+J10-K10-M10,0)*Inputs!$C$22/12,0) -> 158.26679 | O10: =IF(AND(MOD(A10,12)=0,B10>=Inputs!$C$18),MAX(F10+G10+H10+J10-K10-M10-N10,0)*Inputs!$C$17,0) -> 0 | P10: =F10+G10+H10+J10-K10-M10-N10+O10 -> 23581.752 | Q10: =IF(OR(E10=1,P10<=0),0,P10) -> 23581.752 | R10: =IF(OR(E10=1,AND(P10<=0,I10>0)),1,0) -> 0 | S10: =IF(L10>0,1,0) -> 0
A11: 10 | B11: =INT((A11-1)/12)+1 -> 1 | C11: =MIN(Inputs!$C$4+B11-1,99) -> 74 | D11: =Inputs!$C$26 -> 0.03 | E11: =R10 -> 0 | F11: =Q10 -> 23581.752 | G11: =IF(AND(MOD(A11-1,12)=0,B11<=Inputs!$C$7,E11=0),Inputs!$C$6,0) -> 0 | H11: =IF(B11=1,G11*Inputs!$C$9,0) -> 0 | I11: =I10+G11 -> 24000 | J11: =(F11+G11+H11)*((1+D11)^(1/12)-1) -> 58.158962 | K11: =(F11+G11+H11+J11)*(Inputs!$C$14+IF(B11<=10,Inputs!$C$12,Inputs!$C$13))/12 -> 49.249815 | L11: =IF(OR(E11=1,A11<=Inputs!$C$15),0,MAX(Inputs!$C$8*I11-(F11+G11+H11+J11-K11),0)) -> 0 | M11: =L11*INDEX(Rates!$B$2:$C$101,C11+1,IF(Inputs!$C$5="Male",1,2))/1000/12*Inputs!$C$16 -> 0 | N11: =IF($V$1=1,MAX(F11+G11+H11+J11-K11-M11,0)*Inputs!$C$22/12,0) -> 157.27107 | O11: =IF(AND(MOD(A11,12)=0,B11>=Inputs!$C$18),MAX(F11+G11+H11+J11-K11-M11-N11,0)*Inputs!$C$17,0) -> 0 | P11: =F11+G11+H11+J11-K11-M11-N11+O11 -> 23433.39 | Q11: =IF(OR(E11=1,P11<=0),0,P11) -> 23433.39 | R11: =IF(OR(E11=1,AND(P11<=0,I11>0)),1,0) -> 0 | S11: =IF(L11>0,1,0) -> 0
A12: 11 | B12: =INT((A12-1)/12)+1 -> 1 | C12: =MIN(Inputs!$C$4+B12-1,99) -> 74 | D12: =Inputs!$C$26 -> 0.03 | E12: =R11 -> 0 | F12: =Q11 -> 23433.39 | G12: =IF(AND(MOD(A12-1,12)=0,B12<=Inputs!$C$7,E12=0),Inputs!$C$6,0) -> 0 | H12: =IF(B12=1,G12*Inputs!$C$9,0) -> 0 | I12: =I11+G12 -> 24000 | J12: =(F12+G12+H12)*((1+D12)^(1/12)-1) -> 57.793062 | K12: =(F12+G12+H12+J12)*(Inputs!$C$14+IF(B12<=10,Inputs!$C$12,Inputs!$C$13))/12 -> 48.939965 | L12: =IF(OR(E12=1,A12<=Inputs!$C$15),0,MAX(Inputs!$C$8*I12-(F12+G12+H12+J12-K12),0)) -> 0 | M12: =L12*INDEX(Rates!$B$2:$C$101,C12+1,IF(Inputs!$C$5="Male",1,2))/1000/12*Inputs!$C$16 -> 0 | N12: =IF($V$1=1,MAX(F12+G12+H12+J12-K12-M12,0)*Inputs!$C$22/12,0) -> 156.28162 | O12: =IF(AND(MOD(A12,12)=0,B12>=Inputs!$C$18),MAX(F12+G12+H12+J12-K12-M12-N12,0)*Inputs!$C$17,0) -> 0 | P12: =F12+G12+H12+J12-K12-M12-N12+O12 -> 23285.962 | Q12: =IF(OR(E12=1,P12<=0),0,P12) -> 23285.962 | R12: =IF(OR(E12=1,AND(P12<=0,I12>0)),1,0) -> 0 | S12: =IF(L12>0,1,0) -> 0
A13: 12 | B13: =INT((A13-1)/12)+1 -> 1 | C13: =MIN(Inputs!$C$4+B13-1,99) -> 74 | D13: =Inputs!$C$26 -> 0.03 | E13: =R12 -> 0 | F13: =Q12 -> 23285.962 | G13: =IF(AND(MOD(A13-1,12)=0,B13<=Inputs!$C$7,E13=0),Inputs!$C$6,0) -> 0 | H13: =IF(B13=1,G13*Inputs!$C$9,0) -> 0 | I13: =I12+G13 -> 24000 | J13: =(F13+G13+H13)*((1+D13)^(1/12)-1) -> 57.429463 | K13: =(F13+G13+H13+J13)*(Inputs!$C$14+IF(B13<=10,Inputs!$C$12,Inputs!$C$13))/12 -> 48.632065 | L13: =IF(OR(E13=1,A13<=Inputs!$C$15),0,MAX(Inputs!$C$8*I13-(F13+G13+H13+J13-K13),0)) -> 0 | M13: =L13*INDEX(Rates!$B$2:$C$101,C13+1,IF(Inputs!$C$5="Male",1,2))/1000/12*Inputs!$C$16 -> 0 | N13: =IF($V$1=1,MAX(F13+G13+H13+J13-K13-M13,0)*Inputs!$C$22/12,0) -> 155.29839 | O13: =IF(AND(MOD(A13,12)=0,B13>=Inputs!$C$18),MAX(F13+G13+H13+J13-K13-M13-N13,0)*Inputs!$C$17,0) -> 0 | P13: =F13+G13+H13+J13-K13-M13-N13+O13 -> 23139.461 | Q13: =IF(OR(E13=1,P13<=0),0,P13) -> 23139.461 | R13: =IF(OR(E13=1,AND(P13<=0,I13>0)),1,0) -> 0 | S13: =IF(L13>0,1,0) -> 0
A14: 13 | B14: =INT((A14-1)/12)+1 -> 2 | C14: =MIN(Inputs!$C$4+B14-1,99) -> 75 | D14: =Inputs!$C$26 -> 0.03 | E14: =R13 -> 0 | F14: =Q13 -> 23139.461 | G14: =IF(AND(MOD(A14-1,12)=0,B14<=Inputs!$C$7,E14=0),Inputs!$C$6,0) -> 24000 | H14: =IF(B14=1,G14*Inputs!$C$9,0) -> 0 | I14: =I13+G14 -> 48000 | J14: =(F14+G14+H14)*((1+D14)^(1/12)-1) -> 116.25863 | K14: =(F14+G14+H14+J14)*(Inputs!$C$14+IF(B14<=10,Inputs!$C$12,Inputs!$C$13))/12 -> 98.449415 | L14: =IF(OR(E14=1,A14<=Inputs!$C$15),0,MAX(Inputs!$C$8*I14-(F14+G14+H14+J14-K14),0)) -> 0 | M14: =L14*INDEX(Rates!$B$2:$C$101,C14+1,IF(Inputs!$C$5="Male",1,2))/1000/12*Inputs!$C$16 -> 0 | N14: =IF($V$1=1,MAX(F14+G14+H14+J14-K14-M14,0)*Inputs!$C$22/12,0) -> 314.3818 | O14: =IF(AND(MOD(A14,12)=0,B14>=Inputs!$C$18),MAX(F14+G14+H14+J14-K14-M14-N14,0)*Inputs!$C$17,0) -> 0 | P14: =F14+G14+H14+J14-K14-M14-N14+O14 -> 46842.888 | Q14: =IF(OR(E14=1,P14<=0),0,P14) -> 46842.888 | R14: =IF(OR(E14=1,AND(P14<=0,I14>0)),1,0) -> 0 | S14: =IF(L14>0,1,0) -> 0
... A301: 300 | B301: =INT((A301-1)/12)+1 -> 25 | C301: =MIN(Inputs!$C$4+B301-1,99) -> 98 | D301: =Inputs!$C$26 -> 0.03 | E301: =R300 -> 1 | F301: =Q300 -> 0 | G301: =IF(AND(MOD(A301-1,12)=0,B301<=Inputs!$C$7,E301=0),Inputs!$C$6,0) -> 0 | H301: =IF(B301=1,G301*Inputs!$C$9,0) -> 0 | I301: =I300+G301 -> 120000 | J301: =(F301+G301+H301)*((1+D301)^(1/12)-1) -> 0 | K301: =(F301+G301+H301+J301)*(Inputs!$C$14+IF(B301<=10,Inputs!$C$12,Inputs!$C$13))/12 -> 0 | L301: =IF(OR(E301=1,A301<=Inputs!$C$15),0,MAX(Inputs!$C$8*I301-(F301+G301+H301+J301-K301),0)) -> 0 | M301: =L301*INDEX(Rates!$B$2:$C$101,C301+1,IF(Inputs!$C$5="Male",1,2))/1000/12*Inputs!$C$16 -> 0 | N301: =IF($V$1=1,MAX(F301+G301+H301+J301-K301-M301,0)*Inputs!$C$22/12,0) -> 0 | O301: =IF(AND(MOD(A301,12)=0,B301>=Inputs!$C$18),MAX(F301+G301+H301+J301-K301-M301-N301,0)*Inputs!$C$17,0) -> 0 | P301: =F301+G301+H301+J301-K301-M301-N301+O301 -> 0 | Q301: =IF(OR(E301=1,P301<=0),0,P301) -> 0 | R301: =IF(OR(E301=1,AND(P301<=0,I301>0)),1,0) -> 1 | S301: =IF(L301>0,1,0) -> 0

Sheet S3_R
A1: Month | B1: Policy year | C1: Age (last b'day) | D1: Gross return p.a. | E1: Lapsed before? | F1: Policy value b/f | G1: Premium | H1: Investment bonus | I1: Net premiums to date | J1: Investment growth | K1: Policy fee + mgmt fee | L1: Sum at risk (charged) | M1: Insurance charge (COI) | N1: Dividend paid out | O1: Loyalty bonus | P1: PV before floor | Q1: Policy value c/f | R1: Lapsed? | S1: SAR>0 flag | U1: Dividend payout on? (1/0) | V1: 0
A2: 1 | B2: =INT((A2-1)/12)+1 -> 1 | C2: =MIN(Inputs!$C$4+B2-1,99) -> 74 | D2: =Inputs!$C$27 -> 0.04 | E2: 0 | F2: 0 | G2: =IF(AND(MOD(A2-1,12)=0,B2<=Inputs!$C$7,E2=0),Inputs!$C$6,0) -> 24000 | H2: =IF(B2=1,G2*Inputs!$C$9,0) -> 960 | I2: =G2 -> 24000 | J2: =(F2+G2+H2)*((1+D2)^(1/12)-1) -> 81.712545 | K2: =(F2+G2+H2+J2)*(Inputs!$C$14+IF(B2<=10,Inputs!$C$12,Inputs!$C$13))/12 -> 52.170234 | L2: =IF(OR(E2=1,A2<=Inputs!$C$15),0,MAX(Inputs!$C$8*I2-(F2+G2+H2+J2-K2),0)) -> 0 | M2: =L2*INDEX(Rates!$B$2:$C$101,C2+1,IF(Inputs!$C$5="Male",1,2))/1000/12*Inputs!$C$16 -> 0 | N2: =IF($V$1=1,MAX(F2+G2+H2+J2-K2-M2,0)*Inputs!$C$22/12,0) -> 0 | O2: =IF(AND(MOD(A2,12)=0,B2>=Inputs!$C$18),MAX(F2+G2+H2+J2-K2-M2-N2,0)*Inputs!$C$17,0) -> 0 | P2: =F2+G2+H2+J2-K2-M2-N2+O2 -> 24989.542 | Q2: =IF(OR(E2=1,P2<=0),0,P2) -> 24989.542 | R2: =IF(OR(E2=1,AND(P2<=0,I2>0)),1,0) -> 0 | S2: =IF(L2>0,1,0) -> 0 | U2: Sensitivity 3 reinvest
A3: 2 | B3: =INT((A3-1)/12)+1 -> 1 | C3: =MIN(Inputs!$C$4+B3-1,99) -> 74 | D3: =Inputs!$C$27 -> 0.04 | E3: =R2 -> 0 | F3: =Q2 -> 24989.542 | G3: =IF(AND(MOD(A3-1,12)=0,B3<=Inputs!$C$7,E3=0),Inputs!$C$6,0) -> 0 | H3: =IF(B3=1,G3*Inputs!$C$9,0) -> 0 | I3: =I2+G3 -> 24000 | J3: =(F3+G3+H3)*((1+D3)^(1/12)-1) -> 81.809259 | K3: =(F3+G3+H3+J3)*(Inputs!$C$14+IF(B3<=10,Inputs!$C$12,Inputs!$C$13))/12 -> 52.231982 | L3: =IF(OR(E3=1,A3<=Inputs!$C$15),0,MAX(Inputs!$C$8*I3-(F3+G3+H3+J3-K3),0)) -> 0 | M3: =L3*INDEX(Rates!$B$2:$C$101,C3+1,IF(Inputs!$C$5="Male",1,2))/1000/12*Inputs!$C$16 -> 0 | N3: =IF($V$1=1,MAX(F3+G3+H3+J3-K3-M3,0)*Inputs!$C$22/12,0) -> 0 | O3: =IF(AND(MOD(A3,12)=0,B3>=Inputs!$C$18),MAX(F3+G3+H3+J3-K3-M3-N3,0)*Inputs!$C$17,0) -> 0 | P3: =F3+G3+H3+J3-K3-M3-N3+O3 -> 25019.12 | Q3: =IF(OR(E3=1,P3<=0),0,P3) -> 25019.12 | R3: =IF(OR(E3=1,AND(P3<=0,I3>0)),1,0) -> 0 | S3: =IF(L3>0,1,0) -> 0
A4: 3 | B4: =INT((A4-1)/12)+1 -> 1 | C4: =MIN(Inputs!$C$4+B4-1,99) -> 74 | D4: =Inputs!$C$27 -> 0.04 | E4: =R3 -> 0 | F4: =Q3 -> 25019.12 | G4: =IF(AND(MOD(A4-1,12)=0,B4<=Inputs!$C$7,E4=0),Inputs!$C$6,0) -> 0 | H4: =IF(B4=1,G4*Inputs!$C$9,0) -> 0 | I4: =I3+G4 -> 24000 | J4: =(F4+G4+H4)*((1+D4)^(1/12)-1) -> 81.906087 | K4: =(F4+G4+H4+J4)*(Inputs!$C$14+IF(B4<=10,Inputs!$C$12,Inputs!$C$13))/12 -> 52.293803 | L4: =IF(OR(E4=1,A4<=Inputs!$C$15),0,MAX(Inputs!$C$8*I4-(F4+G4+H4+J4-K4),0)) -> 0 | M4: =L4*INDEX(Rates!$B$2:$C$101,C4+1,IF(Inputs!$C$5="Male",1,2))/1000/12*Inputs!$C$16 -> 0 | N4: =IF($V$1=1,MAX(F4+G4+H4+J4-K4-M4,0)*Inputs!$C$22/12,0) -> 0 | O4: =IF(AND(MOD(A4,12)=0,B4>=Inputs!$C$18),MAX(F4+G4+H4+J4-K4-M4-N4,0)*Inputs!$C$17,0) -> 0 | P4: =F4+G4+H4+J4-K4-M4-N4+O4 -> 25048.732 | Q4: =IF(OR(E4=1,P4<=0),0,P4) -> 25048.732 | R4: =IF(OR(E4=1,AND(P4<=0,I4>0)),1,0) -> 0 | S4: =IF(L4>0,1,0) -> 0
A5: 4 | B5: =INT((A5-1)/12)+1 -> 1 | C5: =MIN(Inputs!$C$4+B5-1,99) -> 74 | D5: =Inputs!$C$27 -> 0.04 | E5: =R4 -> 0 | F5: =Q4 -> 25048.732 | G5: =IF(AND(MOD(A5-1,12)=0,B5<=Inputs!$C$7,E5=0),Inputs!$C$6,0) -> 0 | H5: =IF(B5=1,G5*Inputs!$C$9,0) -> 0 | I5: =I4+G5 -> 24000 | J5: =(F5+G5+H5)*((1+D5)^(1/12)-1) -> 82.00303 | K5: =(F5+G5+H5+J5)*(Inputs!$C$14+IF(B5<=10,Inputs!$C$12,Inputs!$C$13))/12 -> 52.355698 | L5: =IF(OR(E5=1,A5<=Inputs!$C$15),0,MAX(Inputs!$C$8*I5-(F5+G5+H5+J5-K5),0)) -> 0 | M5: =L5*INDEX(Rates!$B$2:$C$101,C5+1,IF(Inputs!$C$5="Male",1,2))/1000/12*Inputs!$C$16 -> 0 | N5: =IF($V$1=1,MAX(F5+G5+H5+J5-K5-M5,0)*Inputs!$C$22/12,0) -> 0 | O5: =IF(AND(MOD(A5,12)=0,B5>=Inputs!$C$18),MAX(F5+G5+H5+J5-K5-M5-N5,0)*Inputs!$C$17,0) -> 0 | P5: =F5+G5+H5+J5-K5-M5-N5+O5 -> 25078.379 | Q5: =IF(OR(E5=1,P5<=0),0,P5) -> 25078.379 | R5: =IF(OR(E5=1,AND(P5<=0,I5>0)),1,0) -> 0 | S5: =IF(L5>0,1,0) -> 0
A6: 5 | B6: =INT((A6-1)/12)+1 -> 1 | C6: =MIN(Inputs!$C$4+B6-1,99) -> 74 | D6: =Inputs!$C$27 -> 0.04 | E6: =R5 -> 0 | F6: =Q5 -> 25078.379 | G6: =IF(AND(MOD(A6-1,12)=0,B6<=Inputs!$C$7,E6=0),Inputs!$C$6,0) -> 0 | H6: =IF(B6=1,G6*Inputs!$C$9,0) -> 0 | I6: =I5+G6 -> 24000 | J6: =(F6+G6+H6)*((1+D6)^(1/12)-1) -> 82.100088 | K6: =(F6+G6+H6+J6)*(Inputs!$C$14+IF(B6<=10,Inputs!$C$12,Inputs!$C$13))/12 -> 52.417665 | L6: =IF(OR(E6=1,A6<=Inputs!$C$15),0,MAX(Inputs!$C$8*I6-(F6+G6+H6+J6-K6),0)) -> 0 | M6: =L6*INDEX(Rates!$B$2:$C$101,C6+1,IF(Inputs!$C$5="Male",1,2))/1000/12*Inputs!$C$16 -> 0 | N6: =IF($V$1=1,MAX(F6+G6+H6+J6-K6-M6,0)*Inputs!$C$22/12,0) -> 0 | O6: =IF(AND(MOD(A6,12)=0,B6>=Inputs!$C$18),MAX(F6+G6+H6+J6-K6-M6-N6,0)*Inputs!$C$17,0) -> 0 | P6: =F6+G6+H6+J6-K6-M6-N6+O6 -> 25108.062 | Q6: =IF(OR(E6=1,P6<=0),0,P6) -> 25108.062 | R6: =IF(OR(E6=1,AND(P6<=0,I6>0)),1,0) -> 0 | S6: =IF(L6>0,1,0) -> 0
A7: 6 | B7: =INT((A7-1)/12)+1 -> 1 | C7: =MIN(Inputs!$C$4+B7-1,99) -> 74 | D7: =Inputs!$C$27 -> 0.04 | E7: =R6 -> 0 | F7: =Q6 -> 25108.062 | G7: =IF(AND(MOD(A7-1,12)=0,B7<=Inputs!$C$7,E7=0),Inputs!$C$6,0) -> 0 | H7: =IF(B7=1,G7*Inputs!$C$9,0) -> 0 | I7: =I6+G7 -> 24000 | J7: =(F7+G7+H7)*((1+D7)^(1/12)-1) -> 82.19726 | K7: =(F7+G7+H7+J7)*(Inputs!$C$14+IF(B7<=10,Inputs!$C$12,Inputs!$C$13))/12 -> 52.479706 | L7: =IF(OR(E7=1,A7<=Inputs!$C$15),0,MAX(Inputs!$C$8*I7-(F7+G7+H7+J7-K7),0)) -> 0 | M7: =L7*INDEX(Rates!$B$2:$C$101,C7+1,IF(Inputs!$C$5="Male",1,2))/1000/12*Inputs!$C$16 -> 0 | N7: =IF($V$1=1,MAX(F7+G7+H7+J7-K7-M7,0)*Inputs!$C$22/12,0) -> 0 | O7: =IF(AND(MOD(A7,12)=0,B7>=Inputs!$C$18),MAX(F7+G7+H7+J7-K7-M7-N7,0)*Inputs!$C$17,0) -> 0 | P7: =F7+G7+H7+J7-K7-M7-N7+O7 -> 25137.779 | Q7: =IF(OR(E7=1,P7<=0),0,P7) -> 25137.779 | R7: =IF(OR(E7=1,AND(P7<=0,I7>0)),1,0) -> 0 | S7: =IF(L7>0,1,0) -> 0
A8: 7 | B8: =INT((A8-1)/12)+1 -> 1 | C8: =MIN(Inputs!$C$4+B8-1,99) -> 74 | D8: =Inputs!$C$27 -> 0.04 | E8: =R7 -> 0 | F8: =Q7 -> 25137.779 | G8: =IF(AND(MOD(A8-1,12)=0,B8<=Inputs!$C$7,E8=0),Inputs!$C$6,0) -> 0 | H8: =IF(B8=1,G8*Inputs!$C$9,0) -> 0 | I8: =I7+G8 -> 24000 | J8: =(F8+G8+H8)*((1+D8)^(1/12)-1) -> 82.294548 | K8: =(F8+G8+H8+J8)*(Inputs!$C$14+IF(B8<=10,Inputs!$C$12,Inputs!$C$13))/12 -> 52.54182 | L8: =IF(OR(E8=1,A8<=Inputs!$C$15),0,MAX(Inputs!$C$8*I8-(F8+G8+H8+J8-K8),0)) -> 0 | M8: =L8*INDEX(Rates!$B$2:$C$101,C8+1,IF(Inputs!$C$5="Male",1,2))/1000/12*Inputs!$C$16 -> 0 | N8: =IF($V$1=1,MAX(F8+G8+H8+J8-K8-M8,0)*Inputs!$C$22/12,0) -> 0 | O8: =IF(AND(MOD(A8,12)=0,B8>=Inputs!$C$18),MAX(F8+G8+H8+J8-K8-M8-N8,0)*Inputs!$C$17,0) -> 0 | P8: =F8+G8+H8+J8-K8-M8-N8+O8 -> 25167.532 | Q8: =IF(OR(E8=1,P8<=0),0,P8) -> 25167.532 | R8: =IF(OR(E8=1,AND(P8<=0,I8>0)),1,0) -> 0 | S8: =IF(L8>0,1,0) -> 0
A9: 8 | B9: =INT((A9-1)/12)+1 -> 1 | C9: =MIN(Inputs!$C$4+B9-1,99) -> 74 | D9: =Inputs!$C$27 -> 0.04 | E9: =R8 -> 0 | F9: =Q8 -> 25167.532 | G9: =IF(AND(MOD(A9-1,12)=0,B9<=Inputs!$C$7,E9=0),Inputs!$C$6,0) -> 0 | H9: =IF(B9=1,G9*Inputs!$C$9,0) -> 0 | I9: =I8+G9 -> 24000 | J9: =(F9+G9+H9)*((1+D9)^(1/12)-1) -> 82.39195 | K9: =(F9+G9+H9+J9)*(Inputs!$C$14+IF(B9<=10,Inputs!$C$12,Inputs!$C$13))/12 -> 52.604008 | L9: =IF(OR(E9=1,A9<=Inputs!$C$15),0,MAX(Inputs!$C$8*I9-(F9+G9+H9+J9-K9),0)) -> 0 | M9: =L9*INDEX(Rates!$B$2:$C$101,C9+1,IF(Inputs!$C$5="Male",1,2))/1000/12*Inputs!$C$16 -> 0 | N9: =IF($V$1=1,MAX(F9+G9+H9+J9-K9-M9,0)*Inputs!$C$22/12,0) -> 0 | O9: =IF(AND(MOD(A9,12)=0,B9>=Inputs!$C$18),MAX(F9+G9+H9+J9-K9-M9-N9,0)*Inputs!$C$17,0) -> 0 | P9: =F9+G9+H9+J9-K9-M9-N9+O9 -> 25197.32 | Q9: =IF(OR(E9=1,P9<=0),0,P9) -> 25197.32 | R9: =IF(OR(E9=1,AND(P9<=0,I9>0)),1,0) -> 0 | S9: =IF(L9>0,1,0) -> 0
A10: 9 | B10: =INT((A10-1)/12)+1 -> 1 | C10: =MIN(Inputs!$C$4+B10-1,99) -> 74 | D10: =Inputs!$C$27 -> 0.04 | E10: =R9 -> 0 | F10: =Q9 -> 25197.32 | G10: =IF(AND(MOD(A10-1,12)=0,B10<=Inputs!$C$7,E10=0),Inputs!$C$6,0) -> 0 | H10: =IF(B10=1,G10*Inputs!$C$9,0) -> 0 | I10: =I9+G10 -> 24000 | J10: =(F10+G10+H10)*((1+D10)^(1/12)-1) -> 82.489468 | K10: =(F10+G10+H10+J10)*(Inputs!$C$14+IF(B10<=10,Inputs!$C$12,Inputs!$C$13))/12 -> 52.666269 | L10: =IF(OR(E10=1,A10<=Inputs!$C$15),0,MAX(Inputs!$C$8*I10-(F10+G10+H10+J10-K10),0)) -> 0 | M10: =L10*INDEX(Rates!$B$2:$C$101,C10+1,IF(Inputs!$C$5="Male",1,2))/1000/12*Inputs!$C$16 -> 0 | N10: =IF($V$1=1,MAX(F10+G10+H10+J10-K10-M10,0)*Inputs!$C$22/12,0) -> 0 | O10: =IF(AND(MOD(A10,12)=0,B10>=Inputs!$C$18),MAX(F10+G10+H10+J10-K10-M10-N10,0)*Inputs!$C$17,0) -> 0 | P10: =F10+G10+H10+J10-K10-M10-N10+O10 -> 25227.143 | Q10: =IF(OR(E10=1,P10<=0),0,P10) -> 25227.143 | R10: =IF(OR(E10=1,AND(P10<=0,I10>0)),1,0) -> 0 | S10: =IF(L10>0,1,0) -> 0
A11: 10 | B11: =INT((A11-1)/12)+1 -> 1 | C11: =MIN(Inputs!$C$4+B11-1,99) -> 74 | D11: =Inputs!$C$27 -> 0.04 | E11: =R10 -> 0 | F11: =Q10 -> 25227.143 | G11: =IF(AND(MOD(A11-1,12)=0,B11<=Inputs!$C$7,E11=0),Inputs!$C$6,0) -> 0 | H11: =IF(B11=1,G11*Inputs!$C$9,0) -> 0 | I11: =I10+G11 -> 24000 | J11: =(F11+G11+H11)*((1+D11)^(1/12)-1) -> 82.587102 | K11: =(F11+G11+H11+J11)*(Inputs!$C$14+IF(B11<=10,Inputs!$C$12,Inputs!$C$13))/12 -> 52.728604 | L11: =IF(OR(E11=1,A11<=Inputs!$C$15),0,MAX(Inputs!$C$8*I11-(F11+G11+H11+J11-K11),0)) -> 0 | M11: =L11*INDEX(Rates!$B$2:$C$101,C11+1,IF(Inputs!$C$5="Male",1,2))/1000/12*Inputs!$C$16 -> 0 | N11: =IF($V$1=1,MAX(F11+G11+H11+J11-K11-M11,0)*Inputs!$C$22/12,0) -> 0 | O11: =IF(AND(MOD(A11,12)=0,B11>=Inputs!$C$18),MAX(F11+G11+H11+J11-K11-M11-N11,0)*Inputs!$C$17,0) -> 0 | P11: =F11+G11+H11+J11-K11-M11-N11+O11 -> 25257.002 | Q11: =IF(OR(E11=1,P11<=0),0,P11) -> 25257.002 | R11: =IF(OR(E11=1,AND(P11<=0,I11>0)),1,0) -> 0 | S11: =IF(L11>0,1,0) -> 0
A12: 11 | B12: =INT((A12-1)/12)+1 -> 1 | C12: =MIN(Inputs!$C$4+B12-1,99) -> 74 | D12: =Inputs!$C$27 -> 0.04 | E12: =R11 -> 0 | F12: =Q11 -> 25257.002 | G12: =IF(AND(MOD(A12-1,12)=0,B12<=Inputs!$C$7,E12=0),Inputs!$C$6,0) -> 0 | H12: =IF(B12=1,G12*Inputs!$C$9,0) -> 0 | I12: =I11+G12 -> 24000 | J12: =(F12+G12+H12)*((1+D12)^(1/12)-1) -> 82.684851 | K12: =(F12+G12+H12+J12)*(Inputs!$C$14+IF(B12<=10,Inputs!$C$12,Inputs!$C$13))/12 -> 52.791013 | L12: =IF(OR(E12=1,A12<=Inputs!$C$15),0,MAX(Inputs!$C$8*I12-(F12+G12+H12+J12-K12),0)) -> 0 | M12: =L12*INDEX(Rates!$B$2:$C$101,C12+1,IF(Inputs!$C$5="Male",1,2))/1000/12*Inputs!$C$16 -> 0 | N12: =IF($V$1=1,MAX(F12+G12+H12+J12-K12-M12,0)*Inputs!$C$22/12,0) -> 0 | O12: =IF(AND(MOD(A12,12)=0,B12>=Inputs!$C$18),MAX(F12+G12+H12+J12-K12-M12-N12,0)*Inputs!$C$17,0) -> 0 | P12: =F12+G12+H12+J12-K12-M12-N12+O12 -> 25286.895 | Q12: =IF(OR(E12=1,P12<=0),0,P12) -> 25286.895 | R12: =IF(OR(E12=1,AND(P12<=0,I12>0)),1,0) -> 0 | S12: =IF(L12>0,1,0) -> 0
A13: 12 | B13: =INT((A13-1)/12)+1 -> 1 | C13: =MIN(Inputs!$C$4+B13-1,99) -> 74 | D13: =Inputs!$C$27 -> 0.04 | E13: =R12 -> 0 | F13: =Q12 -> 25286.895 | G13: =IF(AND(MOD(A13-1,12)=0,B13<=Inputs!$C$7,E13=0),Inputs!$C$6,0) -> 0 | H13: =IF(B13=1,G13*Inputs!$C$9,0) -> 0 | I13: =I12+G13 -> 24000 | J13: =(F13+G13+H13)*((1+D13)^(1/12)-1) -> 82.782715 | K13: =(F13+G13+H13+J13)*(Inputs!$C$14+IF(B13<=10,Inputs!$C$12,Inputs!$C$13))/12 -> 52.853496 | L13: =IF(OR(E13=1,A13<=Inputs!$C$15),0,MAX(Inputs!$C$8*I13-(F13+G13+H13+J13-K13),0)) -> 0 | M13: =L13*INDEX(Rates!$B$2:$C$101,C13+1,IF(Inputs!$C$5="Male",1,2))/1000/12*Inputs!$C$16 -> 0 | N13: =IF($V$1=1,MAX(F13+G13+H13+J13-K13-M13,0)*Inputs!$C$22/12,0) -> 0 | O13: =IF(AND(MOD(A13,12)=0,B13>=Inputs!$C$18),MAX(F13+G13+H13+J13-K13-M13-N13,0)*Inputs!$C$17,0) -> 0 | P13: =F13+G13+H13+J13-K13-M13-N13+O13 -> 25316.825 | Q13: =IF(OR(E13=1,P13<=0),0,P13) -> 25316.825 | R13: =IF(OR(E13=1,AND(P13<=0,I13>0)),1,0) -> 0 | S13: =IF(L13>0,1,0) -> 0
A14: 13 | B14: =INT((A14-1)/12)+1 -> 2 | C14: =MIN(Inputs!$C$4+B14-1,99) -> 75 | D14: =Inputs!$C$27 -> 0.04 | E14: =R13 -> 0 | F14: =Q13 -> 25316.825 | G14: =IF(AND(MOD(A14-1,12)=0,B14<=Inputs!$C$7,E14=0),Inputs!$C$6,0) -> 24000 | H14: =IF(B14=1,G14*Inputs!$C$9,0) -> 0 | I14: =I13+G14 -> 48000 | J14: =(F14+G14+H14)*((1+D14)^(1/12)-1) -> 161.45045 | K14: =(F14+G14+H14+J14)*(Inputs!$C$14+IF(B14<=10,Inputs!$C$12,Inputs!$C$13))/12 -> 103.07974 | L14: =IF(OR(E14=1,A14<=Inputs!$C$15),0,MAX(Inputs!$C$8*I14-(F14+G14+H14+J14-K14),0)) -> 0 | M14: =L14*INDEX(Rates!$B$2:$C$101,C14+1,IF(Inputs!$C$5="Male",1,2))/1000/12*Inputs!$C$16 -> 0 | N14: =IF($V$1=1,MAX(F14+G14+H14+J14-K14-M14,0)*Inputs!$C$22/12,0) -> 0 | O14: =IF(AND(MOD(A14,12)=0,B14>=Inputs!$C$18),MAX(F14+G14+H14+J14-K14-M14-N14,0)*Inputs!$C$17,0) -> 0 | P14: =F14+G14+H14+J14-K14-M14-N14+O14 -> 49375.195 | Q14: =IF(OR(E14=1,P14<=0),0,P14) -> 49375.195 | R14: =IF(OR(E14=1,AND(P14<=0,I14>0)),1,0) -> 0 | S14: =IF(L14>0,1,0) -> 0
... A301: 300 | B301: =INT((A301-1)/12)+1 -> 25 | C301: =MIN(Inputs!$C$4+B301-1,99) -> 98 | D301: =Inputs!$C$27 -> 0.04 | E301: =R300 -> 0 | F301: =Q300 -> 239793.56 | G301: =IF(AND(MOD(A301-1,12)=0,B301<=Inputs!$C$7,E301=0),Inputs!$C$6,0) -> 0 | H301: =IF(B301=1,G301*Inputs!$C$9,0) -> 0 | I301: =I300+G301 -> 120000 | J301: =(F301+G301+H301)*((1+D301)^(1/12)-1) -> 785.02172 | K301: =(F301+G301+H301+J301)*(Inputs!$C$14+IF(B301<=10,Inputs!$C$12,Inputs!$C$13))/12 -> 120.28929 | L301: =IF(OR(E301=1,A301<=Inputs!$C$15),0,MAX(Inputs!$C$8*I301-(F301+G301+H301+J301-K301),0)) -> 0 | M301: =L301*INDEX(Rates!$B$2:$C$101,C301+1,IF(Inputs!$C$5="Male",1,2))/1000/12*Inputs!$C$16 -> 0 | N301: =IF($V$1=1,MAX(F301+G301+H301+J301-K301-M301,0)*Inputs!$C$22/12,0) -> 0 | O301: =IF(AND(MOD(A301,12)=0,B301>=Inputs!$C$18),MAX(F301+G301+H301+J301-K301-M301-N301,0)*Inputs!$C$17,0) -> 1202.2915 | P301: =F301+G301+H301+J301-K301-M301-N301+O301 -> 241660.58 | Q301: =IF(OR(E301=1,P301<=0),0,P301) -> 241660.58 | R301: =IF(OR(E301=1,AND(P301<=0,I301>0)),1,0) -> 0 | S301: =IF(L301>0,1,0) -> 0

Sheet S3_P
A1: Month | B1: Policy year | C1: Age (last b'day) | D1: Gross return p.a. | E1: Lapsed before? | F1: Policy value b/f | G1: Premium | H1: Investment bonus | I1: Net premiums to date | J1: Investment growth | K1: Policy fee + mgmt fee | L1: Sum at risk (charged) | M1: Insurance charge (COI) | N1: Dividend paid out | O1: Loyalty bonus | P1: PV before floor | Q1: Policy value c/f | R1: Lapsed? | S1: SAR>0 flag | U1: Dividend payout on? (1/0) | V1: 1
A2: 1 | B2: =INT((A2-1)/12)+1 -> 1 | C2: =MIN(Inputs!$C$4+B2-1,99) -> 74 | D2: =Inputs!$C$27 -> 0.04 | E2: 0 | F2: 0 | G2: =IF(AND(MOD(A2-1,12)=0,B2<=Inputs!$C$7,E2=0),Inputs!$C$6,0) -> 24000 | H2: =IF(B2=1,G2*Inputs!$C$9,0) -> 960 | I2: =G2 -> 24000 | J2: =(F2+G2+H2)*((1+D2)^(1/12)-1) -> 81.712545 | K2: =(F2+G2+H2+J2)*(Inputs!$C$14+IF(B2<=10,Inputs!$C$12,Inputs!$C$13))/12 -> 52.170234 | L2: =IF(OR(E2=1,A2<=Inputs!$C$15),0,MAX(Inputs!$C$8*I2-(F2+G2+H2+J2-K2),0)) -> 0 | M2: =L2*INDEX(Rates!$B$2:$C$101,C2+1,IF(Inputs!$C$5="Male",1,2))/1000/12*Inputs!$C$16 -> 0 | N2: =IF($V$1=1,MAX(F2+G2+H2+J2-K2-M2,0)*Inputs!$C$22/12,0) -> 166.59695 | O2: =IF(AND(MOD(A2,12)=0,B2>=Inputs!$C$18),MAX(F2+G2+H2+J2-K2-M2-N2,0)*Inputs!$C$17,0) -> 0 | P2: =F2+G2+H2+J2-K2-M2-N2+O2 -> 24822.945 | Q2: =IF(OR(E2=1,P2<=0),0,P2) -> 24822.945 | R2: =IF(OR(E2=1,AND(P2<=0,I2>0)),1,0) -> 0 | S2: =IF(L2>0,1,0) -> 0 | U2: Sensitivity 3 payout
A3: 2 | B3: =INT((A3-1)/12)+1 -> 1 | C3: =MIN(Inputs!$C$4+B3-1,99) -> 74 | D3: =Inputs!$C$27 -> 0.04 | E3: =R2 -> 0 | F3: =Q2 -> 24822.945 | G3: =IF(AND(MOD(A3-1,12)=0,B3<=Inputs!$C$7,E3=0),Inputs!$C$6,0) -> 0 | H3: =IF(B3=1,G3*Inputs!$C$9,0) -> 0 | I3: =I2+G3 -> 24000 | J3: =(F3+G3+H3)*((1+D3)^(1/12)-1) -> 81.263864 | K3: =(F3+G3+H3+J3)*(Inputs!$C$14+IF(B3<=10,Inputs!$C$12,Inputs!$C$13))/12 -> 51.883769 | L3: =IF(OR(E3=1,A3<=Inputs!$C$15),0,MAX(Inputs!$C$8*I3-(F3+G3+H3+J3-K3),0)) -> 0 | M3: =L3*INDEX(Rates!$B$2:$C$101,C3+1,IF(Inputs!$C$5="Male",1,2))/1000/12*Inputs!$C$16 -> 0 | N3: =IF($V$1=1,MAX(F3+G3+H3+J3-K3-M3,0)*Inputs!$C$22/12,0) -> 165.68217 | O3: =IF(AND(MOD(A3,12)=0,B3>=Inputs!$C$18),MAX(F3+G3+H3+J3-K3-M3-N3,0)*Inputs!$C$17,0) -> 0 | P3: =F3+G3+H3+J3-K3-M3-N3+O3 -> 24686.643 | Q3: =IF(OR(E3=1,P3<=0),0,P3) -> 24686.643 | R3: =IF(OR(E3=1,AND(P3<=0,I3>0)),1,0) -> 0 | S3: =IF(L3>0,1,0) -> 0
A4: 3 | B4: =INT((A4-1)/12)+1 -> 1 | C4: =MIN(Inputs!$C$4+B4-1,99) -> 74 | D4: =Inputs!$C$27 -> 0.04 | E4: =R3 -> 0 | F4: =Q3 -> 24686.643 | G4: =IF(AND(MOD(A4-1,12)=0,B4<=Inputs!$C$7,E4=0),Inputs!$C$6,0) -> 0 | H4: =IF(B4=1,G4*Inputs!$C$9,0) -> 0 | I4: =I3+G4 -> 24000 | J4: =(F4+G4+H4)*((1+D4)^(1/12)-1) -> 80.817646 | K4: =(F4+G4+H4+J4)*(Inputs!$C$14+IF(B4<=10,Inputs!$C$12,Inputs!$C$13))/12 -> 51.598877 | L4: =IF(OR(E4=1,A4<=Inputs!$C$15),0,MAX(Inputs!$C$8*I4-(F4+G4+H4+J4-K4),0)) -> 0 | M4: =L4*INDEX(Rates!$B$2:$C$101,C4+1,IF(Inputs!$C$5="Male",1,2))/1000/12*Inputs!$C$16 -> 0 | N4: =IF($V$1=1,MAX(F4+G4+H4+J4-K4-M4,0)*Inputs!$C$22/12,0) -> 164.77241 | O4: =IF(AND(MOD(A4,12)=0,B4>=Inputs!$C$18),MAX(F4+G4+H4+J4-K4-M4-N4,0)*Inputs!$C$17,0) -> 0 | P4: =F4+G4+H4+J4-K4-M4-N4+O4 -> 24551.09 | Q4: =IF(OR(E4=1,P4<=0),0,P4) -> 24551.09 | R4: =IF(OR(E4=1,AND(P4<=0,I4>0)),1,0) -> 0 | S4: =IF(L4>0,1,0) -> 0
A5: 4 | B5: =INT((A5-1)/12)+1 -> 1 | C5: =MIN(Inputs!$C$4+B5-1,99) -> 74 | D5: =Inputs!$C$27 -> 0.04 | E5: =R4 -> 0 | F5: =Q4 -> 24551.09 | G5: =IF(AND(MOD(A5-1,12)=0,B5<=Inputs!$C$7,E5=0),Inputs!$C$6,0) -> 0 | H5: =IF(B5=1,G5*Inputs!$C$9,0) -> 0 | I5: =I4+G5 -> 24000 | J5: =(F5+G5+H5)*((1+D5)^(1/12)-1) -> 80.373879 | K5: =(F5+G5+H5+J5)*(Inputs!$C$14+IF(B5<=10,Inputs!$C$12,Inputs!$C$13))/12 -> 51.315549 | L5: =IF(OR(E5=1,A5<=Inputs!$C$15),0,MAX(Inputs!$C$8*I5-(F5+G5+H5+J5-K5),0)) -> 0 | M5: =L5*INDEX(Rates!$B$2:$C$101,C5+1,IF(Inputs!$C$5="Male",1,2))/1000/12*Inputs!$C$16 -> 0 | N5: =IF($V$1=1,MAX(F5+G5+H5+J5-K5-M5,0)*Inputs!$C$22/12,0) -> 163.86765 | O5: =IF(AND(MOD(A5,12)=0,B5>=Inputs!$C$18),MAX(F5+G5+H5+J5-K5-M5-N5,0)*Inputs!$C$17,0) -> 0 | P5: =F5+G5+H5+J5-K5-M5-N5+O5 -> 24416.28 | Q5: =IF(OR(E5=1,P5<=0),0,P5) -> 24416.28 | R5: =IF(OR(E5=1,AND(P5<=0,I5>0)),1,0) -> 0 | S5: =IF(L5>0,1,0) -> 0
A6: 5 | B6: =INT((A6-1)/12)+1 -> 1 | C6: =MIN(Inputs!$C$4+B6-1,99) -> 74 | D6: =Inputs!$C$27 -> 0.04 | E6: =R5 -> 0 | F6: =Q5 -> 24416.28 | G6: =IF(AND(MOD(A6-1,12)=0,B6<=Inputs!$C$7,E6=0),Inputs!$C$6,0) -> 0 | H6: =IF(B6=1,G6*Inputs!$C$9,0) -> 0 | I6: =I5+G6 -> 24000 | J6: =(F6+G6+H6)*((1+D6)^(1/12)-1) -> 79.932548 | K6: =(F6+G6+H6+J6)*(Inputs!$C$14+IF(B6<=10,Inputs!$C$12,Inputs!$C$13))/12 -> 51.033777 | L6: =IF(OR(E6=1,A6<=Inputs!$C$15),0,MAX(Inputs!$C$8*I6-(F6+G6+H6+J6-K6),0)) -> 0 | M6: =L6*INDEX(Rates!$B$2:$C$101,C6+1,IF(Inputs!$C$5="Male",1,2))/1000/12*Inputs!$C$16 -> 0 | N6: =IF($V$1=1,MAX(F6+G6+H6+J6-K6-M6,0)*Inputs!$C$22/12,0) -> 162.96786 | O6: =IF(AND(MOD(A6,12)=0,B6>=Inputs!$C$18),MAX(F6+G6+H6+J6-K6-M6-N6,0)*Inputs!$C$17,0) -> 0 | P6: =F6+G6+H6+J6-K6-M6-N6+O6 -> 24282.211 | Q6: =IF(OR(E6=1,P6<=0),0,P6) -> 24282.211 | R6: =IF(OR(E6=1,AND(P6<=0,I6>0)),1,0) -> 0 | S6: =IF(L6>0,1,0) -> 0
A7: 6 | B7: =INT((A7-1)/12)+1 -> 1 | C7: =MIN(Inputs!$C$4+B7-1,99) -> 74 | D7: =Inputs!$C$27 -> 0.04 | E7: =R6 -> 0 | F7: =Q6 -> 24282.211 | G7: =IF(AND(MOD(A7-1,12)=0,B7<=Inputs!$C$7,E7=0),Inputs!$C$6,0) -> 0 | H7: =IF(B7=1,G7*Inputs!$C$9,0) -> 0 | I7: =I6+G7 -> 24000 | J7: =(F7+G7+H7)*((1+D7)^(1/12)-1) -> 79.493641 | K7: =(F7+G7+H7+J7)*(Inputs!$C$14+IF(B7<=10,Inputs!$C$12,Inputs!$C$13))/12 -> 50.753552 | L7: =IF(OR(E7=1,A7<=Inputs!$C$15),0,MAX(Inputs!$C$8*I7-(F7+G7+H7+J7-K7),0)) -> 0 | M7: =L7*INDEX(Rates!$B$2:$C$101,C7+1,IF(Inputs!$C$5="Male",1,2))/1000/12*Inputs!$C$16 -> 0 | N7: =IF($V$1=1,MAX(F7+G7+H7+J7-K7-M7,0)*Inputs!$C$22/12,0) -> 162.07301 | O7: =IF(AND(MOD(A7,12)=0,B7>=Inputs!$C$18),MAX(F7+G7+H7+J7-K7-M7-N7,0)*Inputs!$C$17,0) -> 0 | P7: =F7+G7+H7+J7-K7-M7-N7+O7 -> 24148.878 | Q7: =IF(OR(E7=1,P7<=0),0,P7) -> 24148.878 | R7: =IF(OR(E7=1,AND(P7<=0,I7>0)),1,0) -> 0 | S7: =IF(L7>0,1,0) -> 0
A8: 7 | B8: =INT((A8-1)/12)+1 -> 1 | C8: =MIN(Inputs!$C$4+B8-1,99) -> 74 | D8: =Inputs!$C$27 -> 0.04 | E8: =R7 -> 0 | F8: =Q7 -> 24148.878 | G8: =IF(AND(MOD(A8-1,12)=0,B8<=Inputs!$C$7,E8=0),Inputs!$C$6,0) -> 0 | H8: =IF(B8=1,G8*Inputs!$C$9,0) -> 0 | I8: =I7+G8 -> 24000 | J8: =(F8+G8+H8)*((1+D8)^(1/12)-1) -> 79.057144 | K8: =(F8+G8+H8+J8)*(Inputs!$C$14+IF(B8<=10,Inputs!$C$12,Inputs!$C$13))/12 -> 50.474866 | L8: =IF(OR(E8=1,A8<=Inputs!$C$15),0,MAX(Inputs!$C$8*I8-(F8+G8+H8+J8-K8),0)) -> 0 | M8: =L8*INDEX(Rates!$B$2:$C$101,C8+1,IF(Inputs!$C$5="Male",1,2))/1000/12*Inputs!$C$16 -> 0 | N8: =IF($V$1=1,MAX(F8+G8+H8+J8-K8-M8,0)*Inputs!$C$22/12,0) -> 161.18307 | O8: =IF(AND(MOD(A8,12)=0,B8>=Inputs!$C$18),MAX(F8+G8+H8+J8-K8-M8-N8,0)*Inputs!$C$17,0) -> 0 | P8: =F8+G8+H8+J8-K8-M8-N8+O8 -> 24016.278 | Q8: =IF(OR(E8=1,P8<=0),0,P8) -> 24016.278 | R8: =IF(OR(E8=1,AND(P8<=0,I8>0)),1,0) -> 0 | S8: =IF(L8>0,1,0) -> 0
A9: 8 | B9: =INT((A9-1)/12)+1 -> 1 | C9: =MIN(Inputs!$C$4+B9-1,99) -> 74 | D9: =Inputs!$C$27 -> 0.04 | E9: =R8 -> 0 | F9: =Q8 -> 24016.278 | G9: =IF(AND(MOD(A9-1,12)=0,B9<=Inputs!$C$7,E9=0),Inputs!$C$6,0) -> 0 | H9: =IF(B9=1,G9*Inputs!$C$9,0) -> 0 | I9: =I8+G9 -> 24000 | J9: =(F9+G9+H9)*((1+D9)^(1/12)-1) -> 78.623043 | K9: =(F9+G9+H9+J9)*(Inputs!$C$14+IF(B9<=10,Inputs!$C$12,Inputs!$C$13))/12 -> 50.19771 | L9: =IF(OR(E9=1,A9<=Inputs!$C$15),0,MAX(Inputs!$C$8*I9-(F9+G9+H9+J9-K9),0)) -> 0 | M9: =L9*INDEX(Rates!$B$2:$C$101,C9+1,IF(Inputs!$C$5="Male",1,2))/1000/12*Inputs!$C$16 -> 0 | N9: =IF($V$1=1,MAX(F9+G9+H9+J9-K9-M9,0)*Inputs!$C$22/12,0) -> 160.29802 | O9: =IF(AND(MOD(A9,12)=0,B9>=Inputs!$C$18),MAX(F9+G9+H9+J9-K9-M9-N9,0)*Inputs!$C$17,0) -> 0 | P9: =F9+G9+H9+J9-K9-M9-N9+O9 -> 23884.405 | Q9: =IF(OR(E9=1,P9<=0),0,P9) -> 23884.405 | R9: =IF(OR(E9=1,AND(P9<=0,I9>0)),1,0) -> 0 | S9: =IF(L9>0,1,0) -> 0
A10: 9 | B10: =INT((A10-1)/12)+1 -> 1 | C10: =MIN(Inputs!$C$4+B10-1,99) -> 74 | D10: =Inputs!$C$27 -> 0.04 | E10: =R9 -> 0 | F10: =Q9 -> 23884.405 | G10: =IF(AND(MOD(A10-1,12)=0,B10<=Inputs!$C$7,E10=0),Inputs!$C$6,0) -> 0 | H10: =IF(B10=1,G10*Inputs!$C$9,0) -> 0 | I10: =I9+G10 -> 24000 | J10: =(F10+G10+H10)*((1+D10)^(1/12)-1) -> 78.191326 | K10: =(F10+G10+H10+J10)*(Inputs!$C$14+IF(B10<=10,Inputs!$C$12,Inputs!$C$13))/12 -> 49.922075 | L10: =IF(OR(E10=1,A10<=Inputs!$C$15),0,MAX(Inputs!$C$8*I10-(F10+G10+H10+J10-K10),0)) -> 0 | M10: =L10*INDEX(Rates!$B$2:$C$101,C10+1,IF(Inputs!$C$5="Male",1,2))/1000/12*Inputs!$C$16 -> 0 | N10: =IF($V$1=1,MAX(F10+G10+H10+J10-K10-M10,0)*Inputs!$C$22/12,0) -> 159.41783 | O10: =IF(AND(MOD(A10,12)=0,B10>=Inputs!$C$18),MAX(F10+G10+H10+J10-K10-M10-N10,0)*Inputs!$C$17,0) -> 0 | P10: =F10+G10+H10+J10-K10-M10-N10+O10 -> 23753.256 | Q10: =IF(OR(E10=1,P10<=0),0,P10) -> 23753.256 | R10: =IF(OR(E10=1,AND(P10<=0,I10>0)),1,0) -> 0 | S10: =IF(L10>0,1,0) -> 0
A11: 10 | B11: =INT((A11-1)/12)+1 -> 1 | C11: =MIN(Inputs!$C$4+B11-1,99) -> 74 | D11: =Inputs!$C$27 -> 0.04 | E11: =R10 -> 0 | F11: =Q10 -> 23753.256 | G11: =IF(AND(MOD(A11-1,12)=0,B11<=Inputs!$C$7,E11=0),Inputs!$C$6,0) -> 0 | H11: =IF(B11=1,G11*Inputs!$C$9,0) -> 0 | I11: =I10+G11 -> 24000 | J11: =(F11+G11+H11)*((1+D11)^(1/12)-1) -> 77.76198 | K11: =(F11+G11+H11+J11)*(Inputs!$C$14+IF(B11<=10,Inputs!$C$12,Inputs!$C$13))/12 -> 49.647955 | L11: =IF(OR(E11=1,A11<=Inputs!$C$15),0,MAX(Inputs!$C$8*I11-(F11+G11+H11+J11-K11),0)) -> 0 | M11: =L11*INDEX(Rates!$B$2:$C$101,C11+1,IF(Inputs!$C$5="Male",1,2))/1000/12*Inputs!$C$16 -> 0 | N11: =IF($V$1=1,MAX(F11+G11+H11+J11-K11-M11,0)*Inputs!$C$22/12,0) -> 158.54247 | O11: =IF(AND(MOD(A11,12)=0,B11>=Inputs!$C$18),MAX(F11+G11+H11+J11-K11-M11-N11,0)*Inputs!$C$17,0) -> 0 | P11: =F11+G11+H11+J11-K11-M11-N11+O11 -> 23622.828 | Q11: =IF(OR(E11=1,P11<=0),0,P11) -> 23622.828 | R11: =IF(OR(E11=1,AND(P11<=0,I11>0)),1,0) -> 0 | S11: =IF(L11>0,1,0) -> 0
A12: 11 | B12: =INT((A12-1)/12)+1 -> 1 | C12: =MIN(Inputs!$C$4+B12-1,99) -> 74 | D12: =Inputs!$C$27 -> 0.04 | E12: =R11 -> 0 | F12: =Q11 -> 23622.828 | G12: =IF(AND(MOD(A12-1,12)=0,B12<=Inputs!$C$7,E12=0),Inputs!$C$6,0) -> 0 | H12: =IF(B12=1,G12*Inputs!$C$9,0) -> 0 | I12: =I11+G12 -> 24000 | J12: =(F12+G12+H12)*((1+D12)^(1/12)-1) -> 77.334991 | K12: =(F12+G12+H12+J12)*(Inputs!$C$14+IF(B12<=10,Inputs!$C$12,Inputs!$C$13))/12 -> 49.375339 | L12: =IF(OR(E12=1,A12<=Inputs!$C$15),0,MAX(Inputs!$C$8*I12-(F12+G12+H12+J12-K12),0)) -> 0 | M12: =L12*INDEX(Rates!$B$2:$C$101,C12+1,IF(Inputs!$C$5="Male",1,2))/1000/12*Inputs!$C$16 -> 0 | N12: =IF($V$1=1,MAX(F12+G12+H12+J12-K12-M12,0)*Inputs!$C$22/12,0) -> 157.67192 | O12: =IF(AND(MOD(A12,12)=0,B12>=Inputs!$C$18),MAX(F12+G12+H12+J12-K12-M12-N12,0)*Inputs!$C$17,0) -> 0 | P12: =F12+G12+H12+J12-K12-M12-N12+O12 -> 23493.116 | Q12: =IF(OR(E12=1,P12<=0),0,P12) -> 23493.116 | R12: =IF(OR(E12=1,AND(P12<=0,I12>0)),1,0) -> 0 | S12: =IF(L12>0,1,0) -> 0
A13: 12 | B13: =INT((A13-1)/12)+1 -> 1 | C13: =MIN(Inputs!$C$4+B13-1,99) -> 74 | D13: =Inputs!$C$27 -> 0.04 | E13: =R12 -> 0 | F13: =Q12 -> 23493.116 | G13: =IF(AND(MOD(A13-1,12)=0,B13<=Inputs!$C$7,E13=0),Inputs!$C$6,0) -> 0 | H13: =IF(B13=1,G13*Inputs!$C$9,0) -> 0 | I13: =I12+G13 -> 24000 | J13: =(F13+G13+H13)*((1+D13)^(1/12)-1) -> 76.910347 | K13: =(F13+G13+H13+J13)*(Inputs!$C$14+IF(B13<=10,Inputs!$C$12,Inputs!$C$13))/12 -> 49.104221 | L13: =IF(OR(E13=1,A13<=Inputs!$C$15),0,MAX(Inputs!$C$8*I13-(F13+G13+H13+J13-K13),0)) -> 0 | M13: =L13*INDEX(Rates!$B$2:$C$101,C13+1,IF(Inputs!$C$5="Male",1,2))/1000/12*Inputs!$C$16 -> 0 | N13: =IF($V$1=1,MAX(F13+G13+H13+J13-K13-M13,0)*Inputs!$C$22/12,0) -> 156.80614 | O13: =IF(AND(MOD(A13,12)=0,B13>=Inputs!$C$18),MAX(F13+G13+H13+J13-K13-M13-N13,0)*Inputs!$C$17,0) -> 0 | P13: =F13+G13+H13+J13-K13-M13-N13+O13 -> 23364.116 | Q13: =IF(OR(E13=1,P13<=0),0,P13) -> 23364.116 | R13: =IF(OR(E13=1,AND(P13<=0,I13>0)),1,0) -> 0 | S13: =IF(L13>0,1,0) -> 0
